Workbook

Sheet Overview
A1: World Aviation Festival – Agenda
A3: Source | B3: https://hub.terrapinn.com/a0AN200000t9wgDMAQPA06066985/agenda
A4: Days included | B4: Day 2, Day 3
A5: Note | B5: Built from agenda text copied from the event hub. The site could not be fetched directly from this environment. Speaker job titles/organisations are split from 'Name, Title, Company' on the site; 'Additional speakers' are names hidden behind '+N more' on the site and are not listed here. Registration numbers are a snapshot at the time of copying.
A8: Sessions by stream
A9: Stream / Category | B9: Day 2 | C9: Day 3 | D9: Total
A10: AI / ML | B10: =COUNTIFS('All Sessions'!$E$2:$E$194,$A10,'All Sessions'!$B$2:$B$194,"Day 2") -> 8 | C10: =COUNTIFS('All Sessions'!$E$2:$E$194,$A10,'All Sessions'!$B$2:$B$194,"Day 3") -> 7 | D10: =SUM(B10:C10) -> 15
A11: Airline Keynote | B11: =COUNTIFS('All Sessions'!$E$2:$E$194,$A11,'All Sessions'!$B$2:$B$194,"Day 2") -> 16 | C11: =COUNTIFS('All Sessions'!$E$2:$E$194,$A11,'All Sessions'!$B$2:$B$194,"Day 3") -> 7 | D11: =SUM(B11:C11) -> 23
A12: Airport & Airline Collaboration | B12: =COUNTIFS('All Sessions'!$E$2:$E$194,$A12,'All Sessions'!$B$2:$B$194,"Day 2") -> 6 | C12: =COUNTIFS('All Sessions'!$E$2:$E$194,$A12,'All Sessions'!$B$2:$B$194,"Day 3") -> 5 | D12: =SUM(B12:C12) -> 11
A13: Airport - Operations | B13: =COUNTIFS('All Sessions'!$E$2:$E$194,$A13,'All Sessions'!$B$2:$B$194,"Day 2") -> 3 | C13: =COUNTIFS('All Sessions'!$E$2:$E$194,$A13,'All Sessions'!$B$2:$B$194,"Day 3") -> 2 | D13: =SUM(B13:C13) -> 5
A14: Airport - Traveller | B14: =COUNTIFS('All Sessions'!$E$2:$E$194,$A14,'All Sessions'!$B$2:$B$194,"Day 2") -> 5 | C14: =COUNTIFS('All Sessions'!$E$2:$E$194,$A14,'All Sessions'!$B$2:$B$194,"Day 3") -> 0 | D14: =SUM(B14:C14) -> 5
A15: Airport Keynote | B15: =COUNTIFS('All Sessions'!$E$2:$E$194,$A15,'All Sessions'!$B$2:$B$194,"Day 2") -> 6 | C15: =COUNTIFS('All Sessions'!$E$2:$E$194,$A15,'All Sessions'!$B$2:$B$194,"Day 3") -> 2 | D15: =SUM(B15:C15) -> 8
A16: Ancillaries | B16: =COUNTIFS('All Sessions'!$E$2:$E$194,$A16,'All Sessions'!$B$2:$B$194,"Day 2") -> 3 | C16: =COUNTIFS('All Sessions'!$E$2:$E$194,$A16,'All Sessions'!$B$2:$B$194,"Day 3") -> 0 | D16: =SUM(B16:C16) -> 3
A17: Customer Experience | B17: =COUNTIFS('All Sessions'!$E$2:$E$194,$A17,'All Sessions'!$B$2:$B$194,"Day 2") -> 8 | C17: =COUNTIFS('All Sessions'!$E$2:$E$194,$A17,'All Sessions'!$B$2:$B$194,"Day 3") -> 0 | D17: =SUM(B17:C17) -> 8
A18: Digital & IT | B18: =COUNTIFS('All Sessions'!$E$2:$E$194,$A18,'All Sessions'!$B$2:$B$194,"Day 2") -> 7 | C18: =COUNTIFS('All Sessions'!$E$2:$E$194,$A18,'All Sessions'!$B$2:$B$194,"Day 3") -> 5 | D18: =SUM(B18:C18) -> 12
A19: IROPS | B19: =COUNTIFS('All Sessions'!$E$2:$E$194,$A19,'All Sessions'!$B$2:$B$194,"Day 2") -> 3 | C19: =COUNTIFS('All Sessions'!$E$2:$E$194,$A19,'All Sessions'!$B$2:$B$194,"Day 3") -> 0 | D19: =SUM(B19:C19) -> 3
A20: Innovation | B20: =COUNTIFS('All Sessions'!$E$2:$E$194,$A20,'All Sessions'!$B$2:$B$194,"Day 2") -> 0 | C20: =COUNTIFS('All Sessions'!$E$2:$E$194,$A20,'All Sessions'!$B$2:$B$194,"Day 3") -> 1 | D20: =SUM(B20:C20) -> 1
A21: Loyalty | B21: =COUNTIFS('All Sessions'!$E$2:$E$194,$A21,'All Sessions'!$B$2:$B$194,"Day 2") -> 7 | C21: =COUNTIFS('All Sessions'!$E$2:$E$194,$A21,'All Sessions'!$B$2:$B$194,"Day 3") -> 6 | D21: =SUM(B21:C21) -> 13
... A28: Workshop | B28: =COUNTIFS('All Sessions'!$E$2:$E$194,$A28,'All Sessions'!$B$2:$B$194,"Day 2") -> 3 | C28: =COUNTIFS('All Sessions'!$E$2:$E$194,$A28,'All Sessions'!$B$2:$B$194,"Day 3") -> 1 | D28: =SUM(B28:C28) -> 4
A29: Total | B29: =SUM(B10:B28) -> 138 | C29: =SUM(C10:C28) -> 55 | D29: =SUM(D10:D28) -> 193

Sheet Day 2
A1: # | B1: Day | C1: Start | D1: End | E1: Stream / Category | F1: Format | G1: Session Title | H1: Speakers (Name – Job Title, Company) | I1: Speaker Names | J1: Organisations | K1: Speakers Listed | L1: Additional Speakers (not shown on site) | M1: Room / Stage | N1: Pavilion | O1: Room (as listed on site) | P1: Description / Discussion Points | Q1: Registered | R1: Capacity | S1: Places Left | T1: Registration Status
A2: 1 | B2: Day 2 | C2: 0.34375 | E2: Networking | F2: Networking | G2: Aviation Connect: Session 6 | H2: Host, World Aviation Festival | I2: Host | J2: World Aviation Festival | K2: 1 | M2: Aviation Connect Zone (Pavilion 2) | N2: Pavilion 2 | O2: Aviation Connect Zone Pavilion 2
A3: 2 | B3: Day 2 | C3: 0.38194444 | E3: Airline Keynote | F3: Welcome | G3: Official Welcome | H3: Carlos Oliveira – Chairman, Tap Air Portugal | I3: Carlos Oliveira | J3: Tap Air Portugal | K3: 1 | M3: Keynote Stage 1 (Pavilion 1) | N3: Pavilion 1 | O3: Keynote Theatre (Pavilion 1)
A4: 3 | B4: Day 2 | C4: 0.38541667 | E4: Airport Keynote | F4: Welcome | G4: Official Airport Partner Welcome | H4: Thierry Ligonnière – Chief Executive Officer, ANA Aeroportos de Portugal | I4: Thierry Ligonnière | J4: ANA Aeroportos de Portugal | K4: 1 | M4: Keynote Stage 2 (Pavilion 2) | N4: Pavilion 2 | O4: Keynote Stage 2 (Pavilion 2)
A5: 4 | B5: Day 2 | C5: 0.38888889 | E5: Airport Keynote | F5: Interview | G5: CEO Interview: Stefan Schulte, CEO, Fraport AG | H5: Stefan Schulte – Chief Executive Officer, Fraport AG Ben Thompson – Presenter, BBC | I5: Stefan Schulte, Ben Thompson | J5: Fraport AG, BBC | K5: 2 | M5: Keynote Stage 2 (Pavilion 2) | N5: Pavilion 2 | O5: Keynote Stage 2 (Pavilion 2)
A6: 5 | B6: Day 2 | C6: 0.38888889 | E6: Airline Keynote | F6: Interview | G6: CEO Interview: Luis Rodrigues, CEO, TAP Air Portugal | H6: Luís Rodrigues – Chief Executive Officer, Tap Air Portugal Peter Campbell – Global Transport Correspondent, Financial Times | I6: Luís Rodrigues, Peter Campbell | J6: Tap Air Portugal, Financial Times | K6: 2 | M6: Keynote Stage 1 (Pavilion 1) | N6: Pavilion 1 | O6: Keynote Stage 1 (Pavilion 1)
A7: 6 | B7: Day 2 | C7: 0.39583333 | E7: Airline Keynote | F7: Interview | G7: CEO Interview: Adrian Neuhauser, CEO, ABRA Group | H7: Adrian Neuhauser – Chief Executive Officer, Abra Group Peter Campbell – Global Transport Correspondent, Financial Times | I7: Adrian Neuhauser, Peter Campbell | J7: Abra Group, Financial Times | K7: 2 | M7: Keynote Stage 1 (Pavilion 1) | N7: Pavilion 1 | O7: Keynote Stage 1 (Pavilion 1)
A8: 7 | B8: Day 2 | C8: 0.39583333 | E8: Airport Keynote | F8: Interview | G8: CEO Interview: Thierry Ligonnière, CEO, ANA - Aeroportos de Portugal | H8: Thierry Ligonnière – Chief Executive Officer, ANA Aeroportos de Portugal Ben Thompson – Presenter, BBC | I8: Thierry Ligonnière, Ben Thompson | J8: ANA Aeroportos de Portugal, BBC | K8: 2 | M8: Keynote Stage 2 (Pavilion 2) | N8: Pavilion 2 | O8: Keynote Stage 2 (Pavilion 2)
A9: 8 | B9: Day 2 | C9: 0.40277778 | E9: Airport Keynote | F9: Interview | G9: CEO Interview: Pierre-Hugues Schmit, CEO, London Gatwick | H9: Pierre-Hugues Schmit – Chief Executive Officer, London Gatwick Airport Ben Thompson – Presenter, BBC | I9: Pierre-Hugues Schmit, Ben Thompson | J9: London Gatwick Airport, BBC | K9: 2 | M9: Keynote Stage 2 (Pavilion 2) | N9: Pavilion 2 | O9: Keynote Stage 2 (Pavilion 2)
A10: 9 | B10: Day 2 | C10: 0.40277778 | E10: Airline Keynote | F10: Interview | G10: CEO Interview: Roberto Alvo, CEO, LATAM | H10: Roberto Alvo – CEO, Latam Airlines Group Peter Campbell – Global Transport Correspondent, Financial Times | I10: Roberto Alvo, Peter Campbell | J10: Latam Airlines Group, Financial Times | K10: 2 | M10: Keynote Stage 1 (Pavilion 1) | N10: Pavilion 1 | O10: Keynote Stage 1 (Pavilion 1)
A11: 10 | B11: Day 2 | C11: 0.40972222 | E11: Airline Keynote | F11: Panel | G11: Keynote CEO Panel: Writing the next chapter of aviation history in an age of uncertainty | H11: Luís Rodrigues – Chief Executive Officer, Tap Air Portugal Adrian Neuhauser – Chief Executive Officer, Abra Group Roberto Alvo – CEO, Latam Airlines Group | I11: Luís Rodrigues, Adrian Neuhauser, Roberto Alvo | J11: Tap Air Portugal, Abra Group, Latam Airlines Group | K11: 3 | L11: 1 | M11: Keynote Stage 1 (Pavilion 1) | N11: Pavilion 1 | O11: Keynote Stage 1 (Pavilion 1) | P11: Investing in the right areas for growth: identifying true game changes from the trendy fad • Navigating geopolitical instability and preparing for unknowns to reduce the impact of disruption • Long Term Strategy planning by optimising operations and working with industry to solve supply chain constraint • Working as an industry to improve global challenges including sustainability, workforce challenges and safety
A12: 11 | B12: Day 2 | C12: 0.40972222 | E12: Airport Keynote | F12: Interview | G12: CEO Interview: Paul Griffiths, CEO, Dubai Airports | H12: Paul Griffiths – Chief Executive Officer, Dubai Airports Company Ben Thompson – Presenter, BBC | I12: Paul Griffiths, Ben Thompson | J12: Dubai Airports Company, BBC | K12: 2 | M12: Keynote Stage 2 (Pavilion 2) | N12: Pavilion 2 | O12: Keynote Stage 2 (Pavilion 2)
A13: 12 | B13: Day 2 | C13: 0.41666667 | E13: Airport Keynote | F13: Panel | G13: Keynote Panel: Growth without compromise – rethinking the airport model for sustainable growth | H13: Stefan Schulte – Chief Executive Officer, Fraport AG Warwick Brady – President & CEO, SWISSPORT Paul Griffiths – Chief Executive Officer, Dubai Airports Company | I13: Stefan Schulte, Warwick Brady, Paul Griffiths | J13: Fraport AG, SWISSPORT, Dubai Airports Company | K13: 3 | L13: 2 | M13: Keynote Stage 2 (Pavilion 2) | N13: Pavilion 2 | O13: Keynote Stage 2 (Pavilion 2) | P13: How can airports manage growth and capacity through both infrastructure development and smarter use of existing assets? • As traffic rises, how do we maintain operational resilience while protecting the passenger experience? • How can better coordination across airlines, airports and ground handlers reduce operational complexity? • As competition between hubs intensifies, how can airports differentiate through efficiency, technology and experience? • What investments in infrastructure, operations and digital capability will define the most competitive airports over the next 3-5 years?
A14: 13 | B14: Day 2 | C14: 0.44791667 | D14: 0.47916667 | E14: Roundtable | F14: Roundtable | G14: Table 01: FLYR Roundtable - Funding the move to Offer & Order: Creating the right time for the right move | H14: Rodrigo López Josh Crandall | I14: Rodrigo López, Josh Crandall | K14: 2 | M14: Roundtable Area (Pavilion 2) | N14: Pavilion 2 | O14: Roundtable area, Pavilion 2 | Q14: 36 | R14: 40 | S14: =R14-Q14 -> 4 | T14: Open
A15: 14 | B15: Day 2 | C15: 0.44791667 | D15: 0.47916667 | E15: Roundtable | F15: Roundtable | G15: Table 2: ATPCO Roundtable - Airline product catalogs: a foundation for retailing at scale | H15: Doug Sharpe Megan Humphries | I15: Doug Sharpe, Megan Humphries | K15: 2 | M15: Roundtable Area (Pavilion 2) | N15: Pavilion 2 | O15: Roundtable area, Pavilion 2 | Q15: 12 | R15: 40 | S15: =R15-Q15 -> 28 | T15: Open
A16: 15 | B16: Day 2 | C16: 0.44791667 | D16: 0.47916667 | E16: Roundtable | F16: Roundtable | G16: Table 3: 15Below - 10 years of deploying AI in aviation: what works, what doesn’t and what we’ve learned | H16: Ali Tredinnick Joe Bennett | I16: Ali Tredinnick, Joe Bennett | K16: 2 | M16: Roundtable Area (Pavilion 2) | N16: Pavilion 2 | O16: Roundtable area, Pavilion 2 | Q16: 50 | R16: 50 | S16: =R16-Q16 -> 0 | T16: Full
A17: 16 | B17: Day 2 | C17: 0.44791667 | D17: 0.47916667 | E17: Roundtable | F17: Roundtable | G17: Table 4: OneReg Roundtable - Continuous confidence: reimagining how aviation compliance works | H17: Billie Moore Angel Matsis | I17: Billie Moore, Angel Matsis | K17: 2 | M17: Roundtable Area (Pavilion 2) | N17: Pavilion 2 | O17: Roundtable area, Pavilion 2 | Q17: 7 | R17: 40 | S17: =R17-Q17 -> 33 | T17: Open
A18: 17 | B18: Day 2 | C18: 0.44791667 | D18: 0.47916667 | E18: Roundtable | F18: Roundtable | G18: Table 5: Seatboost Roundtable - The gate-side goldmine: Gamification, dynamic pricing, and monetizing the premium cabin | H18: Kevin Stamler | I18: Kevin Stamler | K18: 1 | M18: Roundtable Area (Pavilion 2) | N18: Pavilion 2 | O18: Roundtable area, Pavilion 2 | Q18: 18 | R18: 40 | S18: =R18-Q18 -> 22 | T18: Open
A19: 18 | B19: Day 2 | C19: 0.44791667 | D19: 0.47916667 | E19: Roundtable | F19: Roundtable | G19: Table 6: Ping Identity Roundtable - Whose agent is it anyway? | H19: Alexander Laurie Emanuela Maftieu | I19: Alexander Laurie, Emanuela Maftieu | K19: 2 | M19: Roundtable Area (Pavilion 2) | N19: Pavilion 2 | O19: Roundtable area, Pavilion 2 | Q19: 1 | R19: 40 | S19: =R19-Q19 -> 39 | T19: Open
A20: 19 | B20: Day 2 | C20: 0.44791667 | D20: 0.47916667 | E20: Roundtable | F20: Roundtable | G20: Table 7: ADA Roundtable - Agentic IROPs: Turning flight re-accom into your biggest loyalty moment | H20: Mike Murchison Tatiana Deabreu | I20: Mike Murchison, Tatiana Deabreu | K20: 2 | M20: Roundtable Area (Pavilion 2) | N20: Pavilion 2 | O20: Roundtable area, Pavilion 2 | Q20: 31 | R20: 40 | S20: =R20-Q20 -> 9 | T20: Open
A21: 20 | B21: Day 2 | C21: 0.44791667 | D21: 0.47916667 | E21: Roundtable | F21: Roundtable | G21: Table 8: Lufthansa Industry Solutions Roundtable - How airports, airlines and partners can create value through collaboration | H21: Karina Mehl Michael Kleinert | I21: Karina Mehl, Michael Kleinert | K21: 2 | M21: Roundtable Area (Pavilion 2) | N21: Pavilion 2 | O21: Roundtable area, Pavilion 2 | Q21: 40 | R21: 40 | S21: =R21-Q21 -> 0 | T21: Full
A22: 21 | B22: Day 2 | C22: 0.44791667 | D22: 0.47916667 | E22: Roundtable | F22: Roundtable | G22: Table 9: Chubb Roundtable - When delays happen, payouts shouldn't wait. Using parametrics to turn flight disruption into passenger loyalty. | H22: Ruben Rivero | I22: Ruben Rivero | K22: 1 | M22: Roundtable Area (Pavilion 2) | N22: Pavilion 2 | O22: Roundtable area, Pavilion 2 | Q22: 9 | R22: 40 | S22: =R22-Q22 -> 31 | T22: Open
A23: 22 | B23: Day 2 | C23: 0.44791667 | D23: 0.47916667 | E23: Roundtable | F23: Roundtable | G23: Table10: Intellicene Roundtable - The connected airport: Turning data into operational intelligence | H23: Matthew Maychrowitz Rebecca Rea | I23: Matthew Maychrowitz, Rebecca Rea | K23: 2 | M23: Roundtable Area (Pavilion 2) | N23: Pavilion 2 | O23: Roundtable area, Pavilion 2 | Q23: 26 | R23: 40 | S23: =R23-Q23 -> 14 | T23: Open
A24: 23 | B24: Day 2 | C24: 0.44791667 | D24: 0.47916667 | E24: Roundtable | F24: Roundtable | G24: Table11: Thoughtspot Roundtable - From Insight to Action: How aviation leaders are scaling agentic analytics | H24: James Davies Charlotte Ross | I24: James Davies, Charlotte Ross | K24: 2 | M24: Roundtable Area (Pavilion 2) | N24: Pavilion 2 | O24: Roundtable area, Pavilion 2 | Q24: 23 | R24: 40 | S24: =R24-Q24 -> 17 | T24: Open (you are registered)
A25: 24 | B25: Day 2 | C25: 0.44791667 | D25: 0.47916667 | E25: Roundtable | F25: Roundtable | G25: Table12: Volantio Roundtable - Beyond the AI hype: Can agents finally connect revenue, operations and customer experience? | H25: Ana Maria Escobar Azim Barodawala | I25: Ana Maria Escobar, Azim Barodawala | K25: 2 | M25: Roundtable Area (Pavilion 2) | N25: Pavilion 2 | O25: Roundtable area, Pavilion 2 | Q25: 13 | R25: 40 | S25: =R25-Q25 -> 27 | T25: Open
... A33: 32 | B33: Day 2 | C33: 0.44791667 | D33: 0.47916667 | E33: Roundtable | F33: Roundtable | G33: Table20: Zingly Roundtable - Case study: AI in production at Pegasus Airlines: Beyond deflection to completed passenger journeys | H33: Baris Findik Gaurav Passi | I33: Baris Findik, Gaurav Passi | K33: 2 | M33: Roundtable Area (Pavilion 2) | N33: Pavilion 2 | O33: Roundtable area, Pavilion 2 | Q33: 10 | R33: 40 | S33: =R33-Q33 -> 30 | T33: Open
A34: 33 | B34: Day 2 | C34: 0.47916667 | E34: Networking | F34: Networking | G34: Aviation Connect: Session 3 | H34: Host, World Aviation Festival | I34: Host | J34: World Aviation Festival | K34: 1 | M34: Aviation Connect Zone (Pavilion 2) | N34: Pavilion 2 | O34: Aviation Connect Zone Pavilion 2 | P34: Aviation Connect is our dedicated networking hour. Book 15 minute meetings via the Aviation Connect Platform and make the most of your time at WAF. No other sessions, workshops or activities are taking place during this time.
A35: 34 | B35: Day 2 | C35: 0.51736111 | E35: Loyalty | F35: Chair Remarks | G35: Chair opening remarks | H35: Harald Deprosse – Partner, Envolved GmbH | I35: Harald Deprosse | J35: Envolved GmbH | K35: 1 | M35: Track 3 (Pavilion 1) | N35: Pavilion 1 | O35: Track 3 (Pavilion 1)
A36: 35 | B36: Day 2 | C36: 0.52083333 | E36: Sustainability | F36: Fireside Chat | G36: Fireside Chat: Growth without compromise – can airlines decarbonise while remaining competitive? | H36: Maria Whittaker – Chief Corporate Responsibility Officer, Abra Group Patrick Edmond – Chief Commercial Officer, Future Energy Global | I36: Maria Whittaker, Patrick Edmond | J36: Abra Group, Future Energy Global | K36: 2 | M36: Track 10 (Pavilion 2) | N36: Pavilion 2 | O36: Track 10 (Pavilion 2)
A37: 36 | B37: Day 2 | C37: 0.52083333 | E37: Loyalty | F37: Welcome | G37: Plusgrade Welcome | H37: Richard Wolfman – SVP Global Business Development, Plusgrade | I37: Richard Wolfman | J37: Plusgrade | K37: 1 | M37: Track 3 (Pavilion 1) | N37: Pavilion 1 | O37: Track 3, Pav 1
A38: 37 | B38: Day 2 | C38: 0.52430556 | E38: AI / ML | F38: Presentation | G38: Presentation: Building tomorrow’s airline: AI-orchestrated, human-led | H38: Oliver Schmitt – CEO Digital Hangar Ecosystem & SVP Digital Solutions, Lufthansa Group Digital Hangar GmbH | I38: Oliver Schmitt | J38: Lufthansa Group Digital Hangar GmbH | K38: 1 | M38: Track 9 (Pavilion 2) | N38: Pavilion 2 | O38: Track 9, Pavilion 2
A39: 38 | B39: Day 2 | C39: 0.52430556 | E39: Customer Experience | F39: Talk | G39: Human connection, effortless digital experiences: premium CX in the age of AI | H39: Bethan Lynch – VP Customer Experience & Loyalty, Virgin Atlantic Jerry Angrave – Customer Experience Director, Empathyce | I39: Bethan Lynch, Jerry Angrave | J39: Virgin Atlantic, Empathyce | K39: 2 | M39: Track 2 (Pavilion 1) | N39: Pavilion 1 | O39: Track 2 (Pavilion 1) | P39: AI will transform how consumers plan, shop and make the most of travel. But what does the future look like for premium travellers who expect personalised, memorable experiences and genuine emotional connection? • In this fireside chat, Virgin Atlantic’s VP Customer Experience & Loyalty, Bethan Lynch, joins Jerry Angrave to share how the airline is embracing innovative use of AI to serve its customers more personally and seamlessly, while upholding its unique culture, built around its people and their unmistakeable warmth and flair. On its journey to become the most loved travel company, Bethan will explain how Virgin Atlantic sees AI as an extension of the human-centred experience. An opportunity to remove friction and make every interaction meaningful and distinctly Virgin, while enabling people to do what only people can do: create trust, build connection and make customers feel genuinely cared for. • Combining humanity with innovation, also hear how Virgin Atlantic is doubling down on its premium experience across the customer journey, including the rollout of free, high speed Starlink Wi-Fi, new expanded Upper and Premium cabins, investment in award-winning Clubhouses, and a new app integrated with Virgin Atlantic Concierge, powered by OpenAI and built in partnership with Tomoro. Through its brand, people, and the award-winning experience they deliver, Virgin Atlantic is creating emotional connections that last long after the journey ends – building loyalty and enticing customers to choose Virgin Atlantic time and again.
A40: 39 | B40: Day 2 | C40: 0.52430556 | E40: Loyalty | F40: Fireside Chat | G40: Fireside Chat: The future outlook for loyalty at Abra Group | H40: Ralph Piket – Chief Loyalty Officer, Abra Group Harald Deprosse – Partner, Envolved GmbH | I40: Ralph Piket, Harald Deprosse | J40: Abra Group, Envolved GmbH | K40: 2 | M40: Track 3 (Pavilion 1) | N40: Pavilion 1 | O40: Track 3, Pavilion 1
A41: 40 | B41: Day 2 | C41: 0.52430556 | E41: IROPS | F41: Presentation | G41: Presentation: Project ConnectOps: Delivering highly contextualised and realtime information to optimise insights for crew, airport and operational staff | H41: Rachel Gaud – Ops Digital Transformation Lead, Etihad | I41: Rachel Gaud | J41: Etihad | K41: 1 | M41: Track 4 (Pavilion 1) | N41: Pavilion 1 | O41: Track 4 (Pavilion 1)
A42: 41 | B42: Day 2 | C42: 0.52430556 | E42: Digital & IT | F42: Fireside Chat | G42: Fireside Chat: From mainframe to cloud: Air Canada’s modernisation playbook | H42: Mel Crocker – CIO, Air Canada David Peller – General Partner & Founder, If Not You Capital | I42: Mel Crocker, David Peller | J42: Air Canada, If Not You Capital | K42: 2 | M42: Track 1 (Pavilion 1) | N42: Pavilion 1 | O42: Track 1(Pavilion 1)
A43: 42 | B43: Day 2 | C43: 0.52430556 | E43: Airport - Operations | F43: Presentation | G43: Presentation: Becoming a more data driven airport system – collaboration between all stakeholders | H43: Samuel C. Ehrat – Senior Project Leader, Zurich Airport Lorenz Wolf – ICT Solution Architect, Zurich Airport | I43: Samuel C. Ehrat, Lorenz Wolf | J43: Zurich Airport | K43: 2 | M43: Track 8 (Pavilion 2) | N43: Pavilion 2 | O43: Track 8 (Pavilion 2)
A44: 43 | B44: Day 2 | C44: 0.52430556 | E44: Airport & Airline Collaboration | F44: Presentation | G44: Presentation: Lisette Looren de Jong-Vonk, Programme Manager Innovation Border Management, Ministry of Justice and Security – The Netherlands | H44: Lisette Looren de Jong – Programme Manager Innovation Border Management, Ministry of Justice and Security | I44: Lisette Looren de Jong | J44: Ministry of Justice and Security | K44: 1 | M44: Keynote Stage 2 (Pavilion 2) | N44: Pavilion 2 | O44: Keynote Stage 2 (Pavilion 2)
A45: 44 | B45: Day 2 | C45: 0.52430556 | E45: Airport - Traveller | F45: Presentation | G45: Presentation: Building the digital airport – using mobile and AI assistance to bridge the digital and physical airport experience | H45: Jorn Korbi – VP Digital Commercialization, Avinor | I45: Jorn Korbi | J45: Avinor | K45: 1 | M45: Track 7 (Pavilion 2) | N45: Pavilion 2 | O45: Track 7 (Pavilion 2)
A46: 45 | B46: Day 2 | C46: 0.52430556 | E46: Retail | F46: Fireside Chat | G46: Fireside Chat: Legacy to leader: What cultural and digital shift does the industry need for a modern retail transition? | H46: Julio Rodriguez – Chief Commercial Strategy Officer, IAG Dennis Cary – Managing Director, Cary Strategic Advisory | I46: Julio Rodriguez, Dennis Cary | J46: IAG, Cary Strategic Advisory | K46: 2 | M46: Track 5 (Pavilion 1) | N46: Pavilion 1 | O46: Track 5 (Pavilion 1)
A47: 46 | B47: Day 2 | C47: 0.52430556 | E47: Payments | F47: Presentation | G47: Presentation: The hardest part of Offer & Order is not Offer & Order | H47: Ozan Berk Karataş – Senior Program Manager, Airline Retailing & Payments, Turkish Airlines | I47: Ozan Berk Karataş | J47: Turkish Airlines | K47: 1 | M47: Track 6 (Pavilion 1) | N47: Pavilion 1 | O47: Track 6 (Pavillion 1)
A48: 47 | B48: Day 2 | C48: 0.52777778 | E48: Airline Keynote | F48: Interview | G48: CEO Interview: Joerg Eberhart, CEO, ITA Airways | H48: Joerg Eberhart – Chief Executive Officer, ITA-Airways Peter Campbell – Global Transport Correspondent, Financial Times | I48: Joerg Eberhart, Peter Campbell | J48: ITA-Airways, Financial Times | K48: 2 | M48: Keynote Stage 1 (Pavilion 1) | N48: Pavilion 1 | O48: Keynote Stage 1 (Pavilion 1)
A49: 48 | B49: Day 2 | C49: 0.52777778 | E49: Startup Theatre | F49: Startup Pitch | G49: Mission-Critical Legal: Why Departments Need an Operating System, Not Another Assistant | H49: Katja Nikolaus – CBDO, JUNE GmbH | I49: Katja Nikolaus | J49: JUNE GmbH | K49: 1 | M49: Startup Theatre | O49: Startup Theatre
A50: 49 | B50: Day 2 | C50: 0.53125 | E50: Sustainability | F50: Presentation | G50: Presentation: Airbus' Environmental Blueprint: Pioneering sustainable flight | H50: Bertrand Lestimé – HO Environment and Sustainability Marketing, Airbus S.A.S | I50: Bertrand Lestimé | J50: Airbus S.A.S | K50: 1 | M50: Track 10 (Pavilion 2) | N50: Pavilion 2 | O50: Track 10 (Pavilion 2)
A51: 50 | B51: Day 2 | C51: 0.53472222 | E51: AI / ML | F51: Talk | G51: A decade of innovative AI use cases at Lufthansa Group and the agentic AI future | H51: Dr. Philipp Schade – Head of Business Development & Senior Data Scientist, zeroG | I51: Dr. Philipp Schade | J51: zeroG | K51: 1 | M51: Track 9 (Pavilion 2) | N51: Pavilion 2 | O51: Track 9 (Pavilion 2)
A52: 51 | B52: Day 2 | C52: 0.53472222 | E52: Customer Experience | F52: Presentation | G52: Presentation: AI agents and the new front door: How Alaska Airlines is reshaping customer experience | H52: Andrea Halverson – Director - Contact Center Experience and Innovation, Alaska Airlines Barry Chester – Head of Airlines, Cresta | I52: Andrea Halverson, Barry Chester | J52: Alaska Airlines, Cresta | K52: 2 | M52: Track 2 (Pavilion 1) | N52: Pavilion 1 | O52: Track 2, Pav 1
A53: 52 | B53: Day 2 | C53: 0.53472222 | E53: Airline Keynote | F53: Presentation | G53: Presentation: Leveraging travel fintech to protect revenues and passenger trust during global disruption | H53: Ella Schreiber – SVP and GM Fintech, Hopper Inc Karen Romanchuk – Director, Ancillary Revenue, WestJet | I53: Ella Schreiber, Karen Romanchuk | J53: Hopper Inc, WestJet | K53: 2 | M53: Keynote Stage 1 (Pavilion 1) | N53: Pavilion 1 | O53: Keynote Stage 1 (Pavilion 1)
A54: 53 | B54: Day 2 | C54: 0.53472222 | E54: Digital & IT | F54: Presentation | G54: Presentation: What Offer & Order Looks Like, Live at Riyadh Air | H54: Sam Chamberlain – Chief Product Officer, FLYR Tristan Thomas – Global Industry Leader, IBM | I54: Sam Chamberlain, Tristan Thomas | J54: FLYR, IBM | K54: 2 | M54: Track 1 (Pavilion 1) | N54: Pavilion 1 | O54: Track 1(Pavilion 1) | P54: A demo of what was once impossible, and is now live
A55: 54 | B55: Day 2 | C55: 0.53472222 | E55: Retail | F55: Presentation | G55: Presentation: From transaction to trust – what actually drives airline customer behaviour today | H55: Peter Smith – SVP Travel, Cover Genius US Trading, LLC | I55: Peter Smith | J55: Cover Genius US Trading, LLC | K55: 1 | M55: Track 5 (Pavilion 1) | N55: Pavilion 1 | O55: Track 5 (Pavilion 1)
A56: 55 | B56: Day 2 | C56: 0.53472222 | E56: Airport - Operations | F56: Talk | G56: Transforming operations through connected resource and turnaround solutions | H56: Thomas Sermon – Global Client Director, ZestIoT Technologies B.V. | I56: Thomas Sermon | J56: ZestIoT Technologies B.V. | K56: 1 | M56: Track 8 (Pavilion 2) | N56: Pavilion 2 | O56: Track 8 (Pavilion 2)
A57: 56 | B57: Day 2 | C57: 0.53472222 | E57: Loyalty | F57: Panel | G57: Panel: Strategy in a Changing Commercial Landscape – What will define the airline loyalty industry as we move into 2027? | H57: Nejib Ben-Khedher – Divisional Senior Vice President, Skywards, EMIRATES GROUP Ralph Piket – Chief Loyalty Officer, Abra Group Pedro Ribeiro – Loyalty Director, Tap Air Portugal | I57: Nejib Ben-Khedher, Ralph Piket, Pedro Ribeiro | J57: EMIRATES GROUP, Abra Group, Tap Air Portugal | K57: 3 | L57: 4 | M57: Track 3 (Pavilion 1) | N57: Pavilion 1 | O57: Track 3 (Pavillion 1) | P57: Process optimisation: How can we make smoother processes, where can I go with new business models, what could be used better • Moving loyalty closer to the commercial and digital core: aligning with revenue management, sales, and marketing • How can programs cut through AI buzzwords to examine real use cases and the ROI metrics that actually matter? • What will define loyalty leadership in the next decade?
A58: 57 | B58: Day 2 | C58: 0.53472222 | E58: Airport - Traveller | F58: Panel | G58: Panel: The airport terminal is changing – how are airports rethinking non-aero revenue with the wider passenger experience in mind? | H58: Arturs Saveljevs – Board member and CCO, Riga International Airport Jorn Korbi – VP Digital Commercialization, Avinor Gintare Norvilaite-Tautevice – Chief Commercial Officer, Lithuanian Airports | I58: Arturs Saveljevs, Jorn Korbi, Gintare Norvilaite-Tautevice | J58: Riga International Airport, Avinor, Lithuanian Airports | K58: 3 | L58: 3 | M58: Track 7 (Pavilion 2) | N58: Pavilion 2 | O58: Track 7 (Pavilion 2) | P58: As airports digitise more of the journey, how are they rethinking retail, services and the overall passenger experience? • How do airports balance dwell time, flow and frictionless processing with the need to protect non-aero revenue? • Lounges and premium services are growing- how are airports working with partners to expand these offerings? • What new partnership models are emerging between airports, brands and commercial operators? • Where is the gap between measured performance (OTP, flow) and perceived experience? • How should we evolve when passenger expectations, capacity constraints and digital journeys are shifting? • Where are airports seeing the most promising opportunities for future non-aero growth?
A59: 58 | B59: Day 2 | C59: 0.53472222 | E59: Payments | F59: Presentation | G59: Presentation: Payments that drive the CFO agenda | H59: Kevin Murphy – Group CEO, CellPoint | I59: Kevin Murphy | J59: CellPoint | K59: 1 | M59: Track 6 (Pavilion 1) | N59: Pavilion 1 | O59: Track 6 (Pavillion 1)
A60: 59 | B60: Day 2 | C60: 0.53472222 | E60: Airport & Airline Collaboration | F60: Presentation | G60: Presentation: A Shared Flight Path: Creating Value Through Airline–Airport Collaboration | H60: Jitender Mohan – EVP & Business Unit Head, Travel & Hospitality, WNS Global Services (UK) Limited Matthew Robinson – Vice President, Airports, Capgemini | I60: Jitender Mohan, Matthew Robinson | J60: WNS Global Services (UK) Limited, Capgemini | K60: 2 | M60: Keynote Stage 2 (Pavilion 2) | N60: Pavilion 2 | O60: Keynote Stage 2 (Pavilion 2) | P60: Airlines and airports share a common goal of delivering seamless passenger journeys and operational excellence, yet often operate with different priorities and systems. • As capacity constraints, operational complexity and passenger expectations intensify, greater collaboration presents an opportunity to unlock shared value. • This session explores how airlines and airports can move beyond individual optimisation towards connected operations, shared insights and strategic partnerships that enhance passenger experience, improve efficiency and drive sustainable growth. • Key Takeaways • Shared Value: Moving beyond individual optimisation to unlock mutual benefits for airlines, airports and passengers. • Passenger Experience & Operational Excellence: Enabling seamless journeys, improved efficiency and better capacity utilisation through closer collaboration. • Data-Driven Collaboration: Leveraging shared insights, connected technologies and strategic partnerships to drive smarter decisions and sustainable growth.
A61: 60 | B61: Day 2 | C61: 0.53472222 | E61: Startup Theatre | F61: Startup Pitch | G61: ONE Order, Many Products: Holidays and Ancillaries in a Single Airline Order | H61: Pete Pohlschmidt – CCO, Altovo | I61: Pete Pohlschmidt | J61: Altovo | K61: 1 | M61: Startup Theatre | O61: Startup Theatre
A62: 61 | B62: Day 2 | C62: 0.53472222 | E62: IROPS | F62: Presentation | G62: Presentation: DPAX: The next generation of passenger disruption management | H62: Matias Escobar – EVP, Strategy and Innovation, Accommodations Plus International (API) | I62: Matias Escobar | J62: Accommodations Plus International (API) | K62: 1 | M62: Track 4 (Pavilion 1) | N62: Pavilion 1 | O62: Track 4 (Pavilion 1)
A63: 62 | B63: Day 2 | C63: 0.54166667 | E63: Sustainability | F63: Fireside Chat | G63: Fireside Chat: Route to Net Zero: Ambition, Regulation and Reality | H63: Owain Jones – Chief Corporate Officer, Wizz Air Hungary Ltd Patrick Edmond – Chief Commercial Officer, Future Energy Global | I63: Owain Jones, Patrick Edmond | J63: Wizz Air Hungary Ltd, Future Energy Global | K63: 2 | M63: Track 10 (Pavilion 2) | N63: Pavilion 2 | O63: Track 10 (Pavilion 2)
A64: 63 | B64: Day 2 | C64: 0.54166667 | E64: Startup Theatre | F64: Startup Pitch | G64: Cleared for Take-Off: Building Cyber Resilience Across the Aviation Ecosystem | H64: Daniel Forrester – CEO, Cybernet Secure | I64: Daniel Forrester | J64: Cybernet Secure | K64: 1 | M64: Startup Theatre | O64: Startup Theatre
A65: 64 | B65: Day 2 | C65: 0.54513889 | E65: AI / ML | F65: Presentation | G65: Presentation: Founded in data, powered by AI: Real-time answers for airline operations | H65: Eugenia Martinez – Solutions Engineer, ThoughtSpot | I65: Eugenia Martinez | J65: ThoughtSpot | K65: 1 | M65: Track 9 (Pavilion 2) | N65: Pavilion 2 | O65: Track 9, Pavilion 2
A66: 65 | B66: Day 2 | C66: 0.54513889 | E66: IROPS | F66: Panel | G66: Panel: How can we enable customers to feel in-control during unavoidable disruption? | H66: Sheryl Lee – Senior Manager- IRROPS Programs & Strategy, United Airlines Emre Devrim – Product & Customer Experience Manager, Ajet Katy Cardwell – Director of Digital Customer Experience, British Airways | I66: Sheryl Lee, Emre Devrim, Katy Cardwell | J66: United Airlines, Ajet, British Airways | K66: 3 | L66: 2 | M66: Track 4 (Pavilion 1) | N66: Pavilion 1 | O66: Track 4 (Pavilion 1) | P66: How is technology helping airlines to improve the impact and experience of disruption on cutomers? • Empowering customers with facts, options and choice: is this vision achievable? • The power of self-service: how have airlines empowered customers to determine their own experience
A67: 66 | B67: Day 2 | C67: 0.54513889 | E67: Airline Keynote | F67: Interview | G67: CEO Interview: Marcus Schnabel, CEO, SunExpress | H67: Marcus Schnabel – CEO, SunExpress Airlines Peter Campbell – Global Transport Correspondent, Financial Times | I67: Marcus Schnabel, Peter Campbell | J67: SunExpress Airlines, Financial Times | K67: 2 | M67: Keynote Stage 1 (Pavilion 1) | N67: Pavilion 1 | O67: Keynote Stage 1 (Pavilion 1)
A68: 67 | B68: Day 2 | C68: 0.54513889 | E68: Airport & Airline Collaboration | F68: Panel | G68: Panel: Digital identity in aviation – who builds the trust layer for seamless travel? | H68: Maurice Jenkins – Chief Innovation Officer, Miami International Airport Amin Lalani – Product Leader of Airport & Sky Club Digital Products & Experiences, Delta Air Lines Lisette Looren de Jong – Programme Manager Innovation Border Management, Ministry of Justice and Security | I68: Maurice Jenkins, Amin Lalani, Lisette Looren de Jong | J68: Miami International Airport, Delta Air Lines, Ministry of Justice and Security | K68: 3 | L68: 2 | M68: Keynote Stage 2 (Pavilion 2) | N68: Pavilion 2 | O68: Keynote Stage 2 (Pavilion 2) | P68: What has changed recently that could finally enable broader biometric travel deployment? • Global interoperability: what role should standards like IATA One ID, ICAO Digital Travel Credentials and digital identity wallets play? • What data exchange and connectivity infrastructure is needed to link airlines, airports and border agencies? • Who ultimately owns and operates digital identity infrastructure across the ecosystem - airlines, airports, governments or global bodies? • Looking ahead to 2030, will passengers realistically be able to travel end-to-end without presenting a traditional passport?
A69: 68 | B69: Day 2 | C69: 0.54513889 | E69: Payments | F69: Presentation | G69: Presentation: Beyond Legacy: The Uncomfortable Truth About Airline Payments | H69: Victor Gaarenstroom – Global Travel & Mobility Lead, adyen Greg Toussaint – Director, Edgar, Dunn & Company | I69: Victor Gaarenstroom, Greg Toussaint | J69: adyen, Edgar, Dunn & Company | K69: 2 | M69: Track 6 (Pavilion 1) | N69: Pavilion 1 | O69: Track 6 (Pavillion 1) | P69: Fresh off the press: Adyen and Edgar, Dunn & Company explore evolving traveler expectations and how airlines can break free from legacy payments that hold back innovation, speed and performance, and unlock the next frontier in airline payments.
A70: 69 | B70: Day 2 | C70: 0.54513889 | E70: Retail | F70: Talk | G70: Next-gen ancillaries: algorithmic pricing, automation and regulatory shifts | H70: Julio Rodriguez – Chief Commercial Strategy Officer, IAG Tiddo Veldhuis – VP Offer Management & Ancillaries, Air France KLM Juan Pablo Lafosse – CEO, TravelX | I70: Julio Rodriguez, Tiddo Veldhuis, Juan Pablo Lafosse | J70: IAG, Air France KLM, TravelX | K70: 3 | L70: 2 | M70: Track 5 (Pavilion 1) | N70: Pavilion 1 | O70: Track 5 (Pavilion 1) | P70: How will new baggage regulations impact airlines’ revenue models and pricing strategies? • Could predictive analytics help to drive the purchase of premium services? • Can AI help to make prices clearer while still allowing airlines to offer unbundled ancillaries? • How can airlines integrate high-margin lifestyle ancillaries, such as hotels or experiences, directly into the booking flow? • How can real-time data orchestration automate instant payouts for flight delays to turn disruption into a service win?
A71: 70 | B71: Day 2 | C71: 0.54513889 | E71: Digital & IT | F71: Talk | G71: The human experience, both sides: where AI makes CX and where it breaks it | H71: Sindhu Shekharan – VP Customer Success, Sutherland Global Services Inc. | I71: Sindhu Shekharan | J71: Sutherland Global Services Inc. | K71: 1 | M71: Track 1 (Pavilion 1) | N71: Pavilion 1 | O71: Track 1(Pavilion 1) | P71: The customer journey. The talk walks through specific moments and shows the result at each one.Abstract: AI's effect on customer experience is not uniform. It depends on the moment. Across industries, the same technology that delights customers at booking frustrates them during disruption. we will maps where AI makes and breaks the human experience across key service moments, using evidence from multiple industries, and translates the findings into the airline journey: booking, disruption, refunds and rebooking.
A72: 71 | B72: Day 2 | C72: 0.54513889 | E72: Customer Experience | F72: Presentation | G72: Presentation: Autopilot was never unsupervised | H72: Alexander Laurie – GTM CTO, PING IDENTITY | I72: Alexander Laurie | J72: PING IDENTITY | K72: 1 | M72: Track 2 (Pavilion 1) | N72: Pavilion 1 | O72: Track 2 (Pavilion 1) | P72: What happens when AI Agents book the tickets, spend the miles and speak to your customers
A73: 72 | B73: Day 2 | C73: 0.54513889 | E73: Airport - Operations | F73: Panel | G73: Panel: Airports are full of data – how do we turn this into better real-time decision making? | H73: Gyorgy Farkas – Head of IT Project and Innovation Management, Budapest Airport Samuel í Hjøllum Rude – Vice President, Head of Operational Airport Services, Copenhagen Airports Nishant Rao – Director, Aviation Business Development, Nieuport Aviation | I73: Gyorgy Farkas, Samuel í Hjøllum Rude, Nishant Rao | J73: Budapest Airport, Copenhagen Airports, Nieuport Aviation | K73: 3 | L73: 4 | M73: Track 8 (Pavilion 2) | N73: Pavilion 2 | O73: Track 8 (Pavilion 2) | P73: Airports are collecting more operational data than ever, but where are operations team still struggling to turn it into action? • Passenger flow, turnaround visibility and resource allocation are increasingly connected. How do airports bring these datasets together in a useful way? • How do airports balance airline demand for slots with operational and capacity constraints? How does good data help here? • AI is moving quickly, but weak data foundations still hold many projects back. What has to be fixed first? • Looking ahead, what will define an intelligent airport operating model over the next five years?
A74: 73 | B74: Day 2 | C74: 0.54861111 | E74: Startup Theatre | F74: Startup Pitch | G74: Passtination: Powering Loyalty Beyond the Flight | H74: Safir Jamal – Founder & CEO, Passtination | I74: Safir Jamal | J74: Passtination | K74: 1 | M74: Startup Theatre | O74: Startup Theatre
A75: 74 | B75: Day 2 | C75: 0.55208333 | E75: Sustainability | F75: Panel | G75: Panel: Scaling sustainable aviation fuel – who carries the risk, cost and responsibility? | H75: Ulrike Ziegler – President of the Board of Directors, Impact on Sustainable Aviation Maria Whittaker – Chief Corporate Responsibility Officer, Abra Group Jan Petter Steinland – Director Strategic Analysis & Transformation, Civil Aviation Authority Norway | I75: Ulrike Ziegler, Maria Whittaker, Jan Petter Steinland | J75: Impact on Sustainable Aviation, Abra Group, Civil Aviation Authority Norway | K75: 3 | L75: 3 | M75: Track 10 (Pavilion 2) | N75: Pavilion 2 | O75: Track 10 (Pavilion 2) | P75: One year into policies like RefuelEU, what has changed and are airlines now facing uneven regional pressures? • Is SAF still supply-constrained, or are investment risk, production economics and market demand now the biggest barriers to scale? • Where is collaboration between airlines, fuel producers, airports and governments working, and where is it breaking down? • As carbon pricing expands and compliance costs rise, how does this change the business case for SAF compared with other decarbonization pathways? • As geopolitical uncertainty continues, how resilient is the long-term business case for SAF? • What would a functioning SAF market look like by 2030?
A76: 75 | B76: Day 2 | C76: 0.55208333 | E76: Airline Keynote | F76: Panel | G76: CEO Panel: Strategy, competition and innovation in a disruptive environment | H76: Marcus Schnabel – CEO, SunExpress Airlines Theo Panagiotoulias – Chief Executive Officer, Star Alliance Sunil John – CEO, PROS | I76: Marcus Schnabel, Theo Panagiotoulias, Sunil John | J76: SunExpress Airlines, Star Alliance, PROS | K76: 3 | L76: 1 | M76: Keynote Stage 1 (Pavilion 1) | N76: Pavilion 1 | O76: Keynote Stage 1 (Pavilion 1) | P76: Investing in AI transformation to support long term goals • Creating smart business models to compete effectively in a complex global market • Identifying new opportunities for collaboration & growth • Creating next-gen products to meet the expectations of next-gen customers
A77: 76 | B77: Day 2 | C77: 0.55555556 | E77: AI / ML | F77: Panel | G77: Panel: Creating safe & effective foundations for AI transformation within the airline | H77: Ben Dias – Chief AI Scientist, IAG Dirk Jungnickel – SVP Enterprise Data & Analytics, Emirates Airline Kevin Lynn – Director – Crew Scheduling Technology, United Airlines | I77: Ben Dias, Dirk Jungnickel, Kevin Lynn | J77: IAG, Emirates Airline, United Airlines | K77: 3 | L77: 4 | M77: Track 9 (Pavilion 2) | N77: Pavilion 2 | O77: Track 9 (Pavilion 2) | P77: What are the priorities for leaders who are focused on creating a safe & reliable AI frameworks? • Building safety into the core of AI usage in Aviation: balancing innovation with risk integrity • How can Airlines best measure the quality and sophistication of their AI maturity? • Building today with tomorrow’s technology innovation in mind: how can leaders build IT platforms in a fast paced tech space
A78: 77 | B78: Day 2 | C78: 0.55555556 | E78: Payments | F78: Panel | G78: Panel: Payments, retailing & offer-order: what changes when retail changes? | H78: Yago Casasnovas – Head of Payments, Fraud Prevention and Distribution, Air Europa Shaun Donaghey – Chief Commercial Officer, CellPoint Dennis Lore – Payments Reconciliations and Credit Risk Accountant Manager, Kenya Airways | I78: Yago Casasnovas, Shaun Donaghey, Dennis Lore | J78: Air Europa, CellPoint, Kenya Airways | K78: 3 | L78: 2 | M78: Track 6 (Pavilion 1) | N78: Pavilion 1 | O78: Track 6 (Pavillion 1) | P78: In an offer-order world, how must payment authorisation, settlement and refunds evolve to avoid operational complexity? • As orders replace tickets, what new payment and servicing processes are required across the airline ecosystem? • How can airlines reduce cost of sale across NDC, aggregators and OTAs without damaging conversion or partner reach? • How are fintech and travel platforms reshaping ancillary revenue and the checkout experience? • What is the future of agency payment - VCCs, A2A and new settlement models? • How are airlines reorganising internally to align commercial, distribution and payments teams around retailing transformation?
A79: 78 | B79: Day 2 | C79: 0.55555556 | E79: Digital & IT | F79: Panel | G79: Panel: How do we drive revenue, resilience and measure return on tech investment? | H79: Mel Crocker – CIO, Air Canada Dan Bartel – Chief Procurement Officer, American Airlines Massimo Morin – Global Head, Travel, AWS for Travel and Hospitality, Amazon Web Services, Inc. (SEA54) | I79: Mel Crocker, Dan Bartel, Massimo Morin | J79: Air Canada, American Airlines, Amazon Web Services, Inc. (SEA54) | K79: 3 | L79: 3 | M79: Track 1 (Pavilion 1) | N79: Pavilion 1 | O79: Track 1(Pavilion 1) | P79: Where should airlines place their biggest technology bets for 2026–2028 – core systems modernisation, AI, cloud or infrastructure resilience? • How do airlines modernise legacy systems while continuing to operate at scale without creating parallel complexity? • When budgets tighten, how do we distinguish between essential investment and “nice to have” innovation? • Which technology investments are genuinely delivering measurable value across the airline – from automation to AI and core platform upgrades?
A80: 79 | B80: Day 2 | C80: 0.55555556 | E80: Customer Experience | F80: Panel | G80: Panel: Supporting the full customer journey with effective customer care: From the importance of human touch to the power of digital | H80: Marco Barbosa – Directior of Guest Care and Delivery, Etihad Jason Ward – Chief Customer Officer, Azul Airlines Renato Ramos – Vice President Corporate Strategy, Star Alliance | I80: Marco Barbosa, Jason Ward, Renato Ramos | J80: Etihad, Azul Airlines, Star Alliance | K80: 3 | L80: 3 | M80: Track 2 (Pavilion 1) | N80: Pavilion 1 | O80: Track 2 (Pavilion 1) | P80: How can airlines navigate smart multi-channel customer communications to optimise cost and increase customer support • Supporting insights with relevant data streams for colleagues and tech support to support customers effectively and efficiently • Shaping the long-term communications strategy: what will the future look like with AI and agentic AI in the mix?
A81: 80 | B81: Day 2 | C81: 0.5625 | E81: Startup Theatre | F81: Startup Pitch | G81: FlyBuddy: Guiding Passengers, Empowering Airports | H81: Eoin Mcnamara – Co-Founder & Chief Operating Officer, FlyBuddy Michael Murphy – Co-Founder & Chief Executive Officer, FlyBuddy | I81: Eoin Mcnamara, Michael Murphy | J81: FlyBuddy | K81: 2 | M81: Startup Theatre | O81: Startup Theatre
A82: 81 | B82: Day 2 | C82: 0.56944444 | E82: Startup Theatre | F82: Startup Pitch | G82: From Information Desk to Personal AI Concierge: Turning Every Passenger Interaction into Experience and Revenue | H82: Samuel Chekroun – CEO, Hubway | I82: Samuel Chekroun | J82: Hubway | K82: 1 | M82: Startup Theatre | O82: Startup Theatre
A83: 82 | B83: Day 2 | C83: 0.57569444 | D83: 0.60763889 | E83: Workshop | F83: Workshop | G83: IBS Workshop Transformation into an agentic AI lead loyalty and aviation organisation **REGISTRATION REQUIRED - Airline & Airport access only anyone else will be turned away** | H83: Christopher Branagan | I83: Christopher Branagan | K83: 1 | M83: Track 3 (Pavilion 1) | N83: Pavilion 1 | O83: Track3, Pavilion 1 | Q83: 2 | R83: 120 | S83: =R83-Q83 -> 118 | T83: Open
A84: 83 | B84: Day 2 | C84: 0.57638889 | E84: Startup Theatre | F84: Startup Pitch | G84: Connecting Airlines is only the beginning (From fragmented airline distribution to intelligent corporate travel management) | H84: Abdurrahman Ural – CCO, AIRVIATECH | I84: Abdurrahman Ural | J84: AIRVIATECH | K84: 1 | M84: Startup Theatre | O84: Startup Theatre
A85: 84 | B85: Day 2 | C85: 0.57638889 | D85: 0.60763889 | E85: Workshop | F85: Workshop | G85: Adobe Workshop: Beyond the co-pilot: The next era of customer experience **REGISRATION REQUIRED** | H85: Gemma Carver Bettina Pickl | I85: Gemma Carver, Bettina Pickl | K85: 2 | M85: Track 2 (Pavilion 2) | N85: Pavilion 2 | O85: Track 2, Pavilion 2 | Q85: 5 | R85: 120 | S85: =R85-Q85 -> 115 | T85: Open
A86: 85 | B86: Day 2 | C86: 0.57708333 | D86: 0.60763889 | E86: Workshop | F86: Workshop | G86: Operational resilience isn't built in the Ops center. It's built in the roster. **Registration required** | H86: Lauren Mann Kevin Ma Gregory Stephans | I86: Lauren Mann, Kevin Ma, Gregory Stephans | K86: 3 | M86: Track 5 (Pavilion 1) | N86: Pavilion 1 | O86: Track 5 (Pavilion 1) | Q86: 80 | R86: 120 | S86: =R86-Q86 -> 40 | T86: Open
A87: 86 | B87: Day 2 | C87: 0.58333333 | E87: Startup Theatre | F87: Startup Pitch | G87: OpenAir — Agentic Revolution for Airlines Customer Services | H87: Jaime Fernandez – CEO, Openair | I87: Jaime Fernandez | J87: Openair | K87: 1 | M87: Startup Theatre | O87: Startup Theatre
A88: 87 | B88: Day 2 | C88: 0.58333333 | E88: Airline Keynote | F88: Panel | G88: Star Alliance CEOs Panel: From fragmented to frictionless: Rethinking alliance travel | H88: Theo Panagiotoulias – Chief Executive Officer, Star Alliance Luís Rodrigues – Chief Executive Officer, Tap Air Portugal Joerg Eberhart – Chief Executive Officer, ITA-Airways | I88: Theo Panagiotoulias, Luís Rodrigues, Joerg Eberhart | J88: Star Alliance, Tap Air Portugal, ITA-Airways | K88: 3 | L88: 1 | M88: Keynote Stage 1 (Pavilion 1) | N88: Pavilion 1 | O88: Keynote Stage 1 (Pavilion 1)
A89: 88 | B89: Day 2 | C89: 0.59027778 | E89: Startup Theatre | F89: Startup Pitch | G89: Your AI assistants are now booking your flights | H89: Dimitri Ewald – Head of Growth Europe, ALPIC | I89: Dimitri Ewald | J89: ALPIC | K89: 1 | M89: Startup Theatre | O89: Startup Theatre
A90: 89 | B90: Day 2 | C90: 0.59722222 | E90: Startup Theatre | F90: Startup Pitch | G90: Half of what we load is thrown away. Is a 25% waste rate achievable today? | H90: Manuel Hübschmann – Chief Solution Advisor, Viktio | I90: Manuel Hübschmann | J90: Viktio | K90: 1 | M90: Startup Theatre | O90: Startup Theatre
A91: 90 | B91: Day 2 | C91: 0.60763889 | E91: Networking | F91: Networking | G91: Aviation Connect: Session 4 | H91: Host, World Aviation Festival | I91: Host | J91: World Aviation Festival | K91: 1 | M91: Aviation Connect Zone (Pavilion 2) | N91: Pavilion 2 | O91: Aviation Connect Zone, Pavilion 2 | P91: Aviation Connect is our dedicated networking hour. Book 15 minute meetings via the Aviation Connect Platform and make the most of your time at WAF. No other sessions, workshops or activities are taking place during this time.
A92: 91 | B92: Day 2 | C92: 0.64930556 | E92: Airline Keynote | F92: Fireside Chat | G92: Commercial leaders fireside chat: Paul Verhagen, CCO, SAS | H92: Paul Verhagen – Executive Vice President and Chief Commercial Officer, SAS Henry Harteveldt – Travel Industry Analyst, Atmosphere Research Group | I92: Paul Verhagen, Henry Harteveldt | J92: SAS, Atmosphere Research Group | K92: 2 | M92: Keynote Stage 1 (Pavilion 1) | N92: Pavilion 1 | O92: Keynote Stage, Pavilion 1
A93: 92 | B93: Day 2 | C93: 0.65277778 | E93: Digital & IT | F93: Fireside Chat | G93: Fireside Chat: Building an AI-led airline – from ambition to execution | H93: Ahmed Naeemi – Chief Information Officer, Gulf Air Group Guido Woska – Chief Client Officer & Executive Partner, Manyone | I93: Ahmed Naeemi, Guido Woska | J93: Gulf Air Group, Manyone | K93: 2 | M93: Track 1 (Pavilion 1) | N93: Pavilion 1 | O93: Track 1(Pavilion 1)
A94: 93 | B94: Day 2 | C94: 0.65277778 | E94: Customer Experience | F94: Fireside Chat | G94: Fireside chat: Putting the customer first with data driven decision making at Iberia | H94: Beatriz Guillen – Chief Customer Officer, Iberia Jerry Angrave – Customer Experience Director, Empathyce | I94: Beatriz Guillen, Jerry Angrave | J94: Iberia, Empathyce | K94: 2 | M94: Track 2 (Pavilion 1) | N94: Pavilion 1 | O94: Track 2 (Pavilion 1)
A95: 94 | B95: Day 2 | C95: 0.65277778 | E95: AI / ML | F95: Presentation | G95: Presentation: Driving efficiency in innovation with AI: finding real value and impact at TUI | H95: Manjinder Singh – Head of Airline Data Science & Analytics, TUI GROUP | I95: Manjinder Singh | J95: TUI GROUP | K95: 1 | M95: Track 9 (Pavilion 2) | N95: Pavilion 2 | O95: Track 9 (Pavilion 2)
A96: 95 | B96: Day 2 | C96: 0.65277778 | E96: Retail | F96: Fireside Chat | G96: Fireside Chat: Bringing the benefits of NDC to corporates: Delivering seamless booking and travel management capabilities for high value travellers | H96: Paloma Sanz de Andino Jimenéz – NDC Onboarding and Operation Manager, Iberia Dennis Cary – Managing Director, Cary Strategic Advisory Rita Ribeiro – Head of General Services, EDP | I96: Paloma Sanz de Andino Jimenéz, Dennis Cary, Rita Ribeiro | J96: Iberia, Cary Strategic Advisory, EDP | K96: 3 | M96: Track 5 (Pavilion 1) | N96: Pavilion 1 | O96: Track 5 (Pavilion 1)
A97: 96 | B97: Day 2 | C97: 0.65277778 | E97: Airport - Traveller | F97: Fireside Chat | G97: Fireside Chat with Cassie Schmid, Chief Strategy Officer, Philadelphia International Airport | H97: Cassie Schmid – Chief Strategy Officer, Philadelphia International Airport Peta Wolmarans – Vice President, Ricondo | I97: Cassie Schmid, Peta Wolmarans | J97: Philadelphia International Airport, Ricondo | K97: 2 | M97: Track 7 (Pavilion 2) | N97: Pavilion 2 | O97: Track 7 (Pavilion 2)
A98: 97 | B98: Day 2 | C98: 0.65277778 | E98: Sustainability | F98: Fireside Chat | G98: Fireside Chat: Jan Petter Steinland, Director Strategic Analysis and Transformation, CAA Norway | H98: Jan Petter Steinland – Director Strategic Analysis & Transformation, Civil Aviation Authority Norway Patrick Edmond – Chief Commercial Officer, Future Energy Global | I98: Jan Petter Steinland, Patrick Edmond | J98: Civil Aviation Authority Norway, Future Energy Global | K98: 2 | M98: Track 10 (Pavilion 2) | N98: Pavilion 2 | O98: Track 10 (Pavilion 2)
A99: 98 | B99: Day 2 | C99: 0.65277778 | E99: Ancillaries | F99: Presentation | G99: Presentation: Airline retailing progress - what do airline employees really think? | H99: Ann Cederhall – Owner, LeapShift | I99: Ann Cederhall | J99: LeapShift | K99: 1 | M99: Track 4 (Pavilion 1) | N99: Pavilion 1 | O99: Track 4, Pav 1
A100: 99 | B100: Day 2 | C100: 0.65277778 | E100: Startup Theatre | F100: Startup Pitch | G100: From Frequent Flyer to Founder: The Story Behind Stand-By Transforming the Boarding Experience | H100: Cesar Hueso – Founder, Stand-By CHO Systems | I100: Cesar Hueso | J100: Stand-By CHO Systems | K100: 1 | M100: Startup Theatre | O100: Startup Theatre
A101: 100 | B101: Day 2 | C101: 0.65277778 | E101: Airport & Airline Collaboration | F101: Fireside Chat | G101: Fireside Chat: Airline & airport partnerships – aligning operations, experience and commercial outcomes | H101: Girish Nair – Chief Operating Officer, Bangalore International Airport Simon Wilcox – Founder and CEO, Wordsworth Consulting Ltd | I101: Girish Nair, Simon Wilcox | J101: Bangalore International Airport, Wordsworth Consulting Ltd | K101: 2 | M101: Keynote Stage 2 (Pavilion 2) | N101: Pavilion 2 | O101: Keynote Stage 2 (Pavilion 2)
A102: 101 | B102: Day 2 | C102: 0.65277778 | E102: Payments | F102: Fireside Chat | G102: Fireside Chat: The customer side of airline payments – trust, loyalty and engagement | H102: Joao Frias – Head of Payments Strategy & Global Fraud, Tap Air Portugal Louis Wapler – Manager, Edgar, Dunn & Company | I102: Joao Frias, Louis Wapler | J102: Tap Air Portugal, Edgar, Dunn & Company | K102: 2 | M102: Track 6 (Pavilion 1) | N102: Pavilion 1 | O102: Track 6 (Pavillion 1)
A103: 102 | B103: Day 2 | C103: 0.65277778 | E103: Loyalty | F103: Fireside Chat | G103: Fireside Chat: Chasing the golden goose: Optimising revenue whilst protecting loyalty value in a pressurised environment. | H103: DANIEL BRETT – Manager, Revenue Management - Loyalty Programs & Flight Pass, Air Canada Harald Deprosse – Partner, Envolved GmbH | I103: DANIEL BRETT, Harald Deprosse | J103: Air Canada, Envolved GmbH | K103: 2 | M103: Track 3 (Pavilion 1) | N103: Pavilion 1 | O103: Track 3, Pavilion 1
A104: 103 | B104: Day 2 | C104: 0.65972222 | E104: Sustainability | F104: Presentation | G104: Presentation: Sustainability strategy - delivering carbon neutrality in a competitive low-cost model | H104: Takuya MATSUO – Executive officer/CMO, Strategy Lead, ZIPAIR Tokyo | I104: Takuya MATSUO | J104: ZIPAIR Tokyo | K104: 1 | M104: Track 10 (Pavilion 2) | N104: Pavilion 2 | O104: Track 10 (Pavilion 2)
A105: 104 | B105: Day 2 | C105: 0.65972222 | E105: Airline Keynote | F105: Presentation | G105: Presentation: An introduction to beyond: Turkish Technology modern airline retailing platform | H105: Serdar Gurbuz – CEO, Turkish Technology | I105: Serdar Gurbuz | J105: Turkish Technology | K105: 1 | M105: Keynote Stage 1 (Pavilion 1) | N105: Pavilion 1 | O105: Keynote Stage 1 (Pavilion 1)
A106: 105 | B106: Day 2 | C106: 0.65972222 | E106: Startup Theatre | F106: Startup Pitch | G106: Why 89% of Travel Checkouts Fail – and How Identity Fixes It | H106: Kameron Bertine – CEO and Cofounder, Movmo | I106: Kameron Bertine | J106: Movmo | K106: 1 | M106: Startup Theatre | O106: Startup Theatre
A107: 106 | B107: Day 2 | C107: 0.66319444 | E107: Digital & IT | F107: Fireside Chat | G107: Fireside Chat: Inside the OCC: what really works with data and Ai | H107: Paulo Aguiar – VP of Airline Solutions & Strategy, Amach Choorah Singh Ark – Managing Director, Ark Advisory | I107: Paulo Aguiar, Choorah Singh Ark | J107: Amach, Ark Advisory | K107: 2 | M107: Track 1 (Pavilion 1) | N107: Pavilion 1 | O107: Track 1(Pavilion 1) | P107: Choorah Singh, who has led operations at Air India and Ryanair, joins Paulo Aguiar from Amach for an honest conversation from inside the Operations Control Centre: what really works with data and AI when the day goes wrong, what doesn’t, and what every airline should fix before buying its next AI tool.
...

Sheet Day 3
A1: # | B1: Day | C1: Start | D1: End | E1: Stream / Category | F1: Format | G1: Session Title | H1: Speakers (Name – Job Title, Company) | I1: Speaker Names | J1: Organisations | K1: Speakers Listed | L1: Additional Speakers (not shown on site) | M1: Room / Stage | N1: Pavilion | O1: Room (as listed on site) | P1: Description / Discussion Points | Q1: Registered | R1: Capacity | S1: Places Left | T1: Registration Status
A2: 1 | B2: Day 3 | E2: Networking | F2: Networking | G2: Aviation Connect: Session 7 | H2: Host, World Aviation Festival | I2: Host | J2: World Aviation Festival | K2: 1 | M2: Aviation Connect Zone (Pavilion 2) | N2: Pavilion 2 | O2: Aviation Connect Zone, Pavilion 2
A3: 2 | B3: Day 3 | C3: 0.39583333 | E3: Airline Keynote | F3: Talk | G3: Fast & Slow Social: Driving engagement with smart social media strategy | H3: Michael Corcoran – Co-Founder, Slice Social Oisin Lunny – Event MC, Journalist, Podcast and Webinar Host, Galaxy of OM, S.L. | I3: Michael Corcoran, Oisin Lunny | J3: Slice Social, Galaxy of OM, S.L. | K3: 2 | M3: Keynote Stage 1 (Pavilion 1) | N3: Pavilion 1 | O3: Keynote Stage 1 (Pavilion 1)
A4: 3 | B4: Day 3 | C4: 0.40625 | E4: Airport Keynote | F4: Interview | G4: Keynote Interview with Lars Redeligx, CEO, Düsseldorf Airport | H4: Lars Redeligx – CEO, Dusseldorf Airport Luis Felipe De Oliveira – Executive Director and CEO, Exactly Consulting and Services Sarl | I4: Lars Redeligx, Luis Felipe De Oliveira | J4: Dusseldorf Airport, Exactly Consulting and Services Sarl | K4: 2 | M4: Keynote Stage 2 (Pavilion 2) | N4: Pavilion 2 | O4: Keynote Stage 2 (Pavilion 2)
A5: 4 | B5: Day 3 | C5: 0.40625 | E5: Airline Keynote | F5: Fireside Chat | G5: Fireside Chat with Amy Burr, CEO, SKY VC | H5: Amy Burr – CEO, SKY VC Lennart Dobravsky – Managing Director, Research+Attitude | I5: Amy Burr, Lennart Dobravsky | J5: SKY VC, Research+Attitude | K5: 2 | M5: Keynote Stage 1 (Pavilion 1) | N5: Pavilion 1 | O5: Keynote Stage 1 (Pavilion 1)
A6: 5 | B6: Day 3 | C6: 0.41666667 | E6: Airport Keynote | F6: Panel | G6: Keynote Panel: Defining the airport of the future – technology, partnerships and people | H6: Lars Redeligx – CEO, Dusseldorf Airport Olubunmi Kuku – Managing Director/Chief Executive, FEDERAL AIRPORTS AUTHORITY OF NIGERIA Javlonbek Umarkhodjaev – Chairman of the Management Board, Uzbekistan Airports JSC | I6: Lars Redeligx, Olubunmi Kuku, Javlonbek Umarkhodjaev | J6: Dusseldorf Airport, FEDERAL AIRPORTS AUTHORITY OF NIGERIA, Uzbekistan Airports JSC | K6: 3 | L6: 1 | M6: Keynote Stage 2 (Pavilion 2) | N6: Pavilion 2 | O6: Keynote Stage 2 (Pavilion 2) | P6: How are airports evolving beyond transport infrastructure into mobility, economic and community hubs? • As automation and digital services expand, how do we preserve the human side of travel? • What role do airlines, airports and ground handlers each play in shaping the passenger journey? • How can the industry collaborate more effectively to deliver growth, resilience and sustainability? • What will distinguish the leading airports of the next decade?
A7: 6 | B7: Day 3 | C7: 0.41666667 | E7: Airline Keynote | F7: Panel | G7: Investor Panel: Innovation at a crossroads – where are aviation’s next big bets? | H7: Amy Burr – CEO, SKY VC Cara Whitehill – Operating Partner, Thayer Investment Partners Amir Amidi – Managing Partner, Plug and Play Tech Center | I7: Amy Burr, Cara Whitehill, Amir Amidi | J7: SKY VC, Thayer Investment Partners, Plug and Play Tech Center | K7: 3 | L7: 2 | M7: Keynote Stage 1 (Pavilion 1) | N7: Pavilion 1 | O7: Keynote Stage 1 (Pavilion 1)
A8: 7 | B8: Day 3 | C8: 0.44791667 | E8: Networking | F8: Networking | G8: Aviation Connect: Session 5 | H8: Host, World Aviation Festival | I8: Host | J8: World Aviation Festival | K8: 1 | M8: Aviation Connect Zone (Pavilion 2) | N8: Pavilion 2 | O8: Aviation Connect Zone, Pavilion 2 | P8: Aviation Connect is our dedicated networking hour. Book 15 minute meetings via the Aviation Connect Platform and make the most of your time at WAF. No other sessions, workshops or activities are taking place during this time.
A9: 8 | B9: Day 3 | C9: 0.49305556 | E9: Startup Theatre | F9: Startup Pitch | G9: Your chatbot knows everything. Except how to help. | H9: Tiernan Mines – CEO & Co-Founder, Hello Airport | I9: Tiernan Mines | J9: Hello Airport | K9: 1 | M9: Startup Theatre | O9: Startup Theatre
A10: 9 | B10: Day 3 | C10: 0.49652778 | E10: Loyalty | F10: Chair Remarks | G10: Chair opening remarks | H10: Harald Deprosse – Partner, Envolved GmbH | I10: Harald Deprosse | J10: Envolved GmbH | K10: 1 | M10: Track 3 (Pavilion 1) | N10: Pavilion 1 | O10: Track 3 (Pavillion 1)
A11: 10 | B11: Day 3 | C11: 0.5 | E11: Digital & IT | F11: Fireside Chat | G11: Fireside Chat: Executing Offer & Order – balancing innovation with operational reality | H11: Dan Fischer – Head of Digital Product, Strategy & Design, Virgin Australia Mark Lenahan – Consultant, Lenahan Consulting Ltd | I11: Dan Fischer, Mark Lenahan | J11: Virgin Australia, Lenahan Consulting Ltd | K11: 2 | M11: Track 1 (Pavilion 1) | N11: Pavilion 1 | O11: Track 1(Pavilion 1)
A12: 11 | B12: Day 3 | C12: 0.5 | E12: Startup Theatre | F12: Startup Pitch | G12: The Growing Threat of Brand Hijacking to Airline Direct Bookings | H12: Shlomi Beer – Co-founder & CEO, ImpersonAlly | I12: Shlomi Beer | J12: ImpersonAlly | K12: 1 | M12: Startup Theatre | O12: Startup Theatre
A13: 12 | B13: Day 3 | C13: 0.5 | E13: Airline Keynote | F13: Interview | G13: CEO Interview: Eivind Roald, CEO, Norse Atlantic Airlines | H13: Eivind Roald – President & CEO, Norse Atlantic Airways John Strickland – Director, JLS Consulting | I13: Eivind Roald, John Strickland | J13: Norse Atlantic Airways, JLS Consulting | K13: 2 | M13: Keynote Stage 1 (Pavilion 1) | N13: Pavilion 1 | O13: Keynote Stage 1 (Pavilion 1)
A14: 13 | B14: Day 3 | C14: 0.5 | E14: Airport & Airline Collaboration | F14: Fireside Chat | G14: Fireside Chat: Beyond AODP - redesigning the airport’s digital foundation | H14: Iyad Hindiyeh – CDO, GAL - GMR Group Maurice Jenkins – Chief Innovation Officer, Miami International Airport | I14: Iyad Hindiyeh, Maurice Jenkins | J14: GAL - GMR Group, Miami International Airport | K14: 2 | M14: Keynote Stage 2 (Pavilion 2) | N14: Pavilion 2 | O14: Keynote Stage 2 (Pavilion 2)
A15: 14 | B15: Day 3 | C15: 0.5 | E15: Loyalty | F15: Presentation | G15: Presentation: How should an airline’s loyalty program position itself within the airline for maximum impact? | H15: Tiffany Funk – Head of Flying Blue, VP Loyalty, Air France KLM | I15: Tiffany Funk | J15: Air France KLM | K15: 1 | M15: Track 3 (Pavilion 1) | N15: Pavilion 1 | O15: Track 3 (Pavillion 1)
A16: 15 | B16: Day 3 | C16: 0.5 | E16: AI / ML | F16: Talk | G16: The agentic Airline of the future: Lessons from Air India’s enterprise AI journey | H16: Murali Karthik – Head of EA, Governance, Data & AI, Agentic COE, Air India | I16: Murali Karthik | J16: Air India | K16: 1 | M16: Track 9 (Pavilion 2) | N16: Pavilion 2 | O16: Track 9 (Pavilion 2)
A17: 16 | B17: Day 3 | C17: 0.5 | E17: Retail | F17: Presentation | G17: Presentation: Disrupting the status quo: Air Europa’s successful distribution journey | H17: Yago Casasnovas – Head of Payments, Fraud Prevention and Distribution, Air Europa Daniel Langhage – Managing Director, Oystin Advisory GmbH | I17: Yago Casasnovas, Daniel Langhage | J17: Air Europa, Oystin Advisory GmbH | K17: 2 | M17: Track 5 (Pavilion 1) | N17: Pavilion 1 | O17: Track 5 (Pavilion 1)
A18: 17 | B18: Day 3 | C18: 0.5 | E18: Airport - Operations | F18: Presentation | G18: Presentation: Gear Up NRT | H18: Yusuke Izawa – Project Manager, Global Business Department, Narita International Airport Corp. | I18: Yusuke Izawa | J18: Narita International Airport Corp. | K18: 1 | M18: Track 8 (Pavilion 2) | N18: Pavilion 2 | O18: Track 8 (Pavilion 2) | P18: Expanding Capacity, Driving Innovation, Overseas Business
A19: 18 | B19: Day 3 | C19: 0.50694444 | E19: Startup Theatre | F19: Startup Pitch | G19: Making better commercial decisions in a world that's never been more complicated | H19: Alex Matson – COO, telos | I19: Alex Matson | J19: telos | K19: 1 | M19: Startup Theatre | O19: Startup Theatre
A20: 19 | B20: Day 3 | C20: 0.51041667 | E20: AI / ML | F20: Presentation | G20: Presentation: Agentic AI and the future of airline competitiveness | H20: Lars Schwabe – Chief Technology Officer, Lufthansa Industry Solutions | I20: Lars Schwabe | J20: Lufthansa Industry Solutions | K20: 1 | M20: Track 9 (Pavilion 2) | N20: Pavilion 2 | O20: Track 9 (Pavilion 2)
A21: 20 | B21: Day 3 | C21: 0.51041667 | E21: Airport - Operations | F21: Panel | G21: Panel: Scaling airport innovation – moving from pilot projects to operational deployment | H21: Vanesa Calvo – Head of Funding and Innovation Trends, A.E.N.A. Sanne Cox – Innovation Manager, Royal Schiphol Group Eric Boromisa – Founder | Managing Partner, Numbers & Letters Advisory | I21: Vanesa Calvo, Sanne Cox, Eric Boromisa | J21: A.E.N.A., Royal Schiphol Group, Numbers & Letters Advisory | K21: 3 | M21: Track 8 (Pavilion 2) | N21: Pavilion 2 | O21: Track 8 (Pavilion 2) | P21: Airports are piloting more tools than ever across AI, automation, robotics and digital passenger services. What actually moves beyond the pilot stage? • Capacity constraints are forcing airports to get more from existing infrastructure. Where is innovation delivering the biggest operational gains? • Some innovations reduce cost, some improve experience, and some create new revenue. How do airports decide what matters most? • What internal conditions really determine whether an innovation scale – governance, funding, culture or partner buy-in? • Looking ahead, where should airports be placing their smartest innovation bets?
A22: 21 | B22: Day 3 | C22: 0.51041667 | E22: Retail | F22: Fireside Chat | G22: Fireside Chat: From infrastructure to intelligence: How ATPCO is building airline retailing's AI-ready foundation | H22: Anand Mishra – VP of Technology, ATPCO Sinead Finn – Founder, affinnity | I22: Anand Mishra, Sinead Finn | J22: ATPCO, affinnity | K22: 2 | M22: Track 5 (Pavilion 1) | N22: Pavilion 1 | O22: Track 5 (Pavilion 1) | P22: Airline retailing is being fundamentally reimagined and the companies that will shape its future aren't just building smarter products, they're building smarter foundations. ATPCO Vice President of Technology Anand Mishra will explore how the industry's most trusted neutral data layer is evolving to meet the moment, as agentic AI moves from concept to commercial reality. With nearly two-thirds of adult travelers under 45 already turning to AI for travel recommendations and AI-driven booking accelerating fast, the window to establish trusted, structured data foundations is open, but for how long? • Anand will pull back the curtain on recent ATPCO's experiments: including those that ask a simple but high-stakes question — can ATPCO's structured data turn general AI into a trusted source for airline retailing? The answer was a resounding yes, and Anand will dive into some of the learnings. • Attendees will leave with a clear view of where airline retailing's AI transformation is heading over the next 18 to 36 months, why the standards and data layer will be the defining battleground, and how ATPCO is positioning itself, and the industry, to make sure that transformation happens for us, not to us
A23: 22 | B23: Day 3 | C23: 0.51041667 | E23: Digital & IT | F23: Talk | G23: FROM FILED FARES TO FLEXIBLE FUTURES OF FARE FILING - MODERNIZE TODAY. BUILD TOMORROW | H23: Christoph Both – Head of Customer, Business Development & Controlling, Lufthansa Process Management | I23: Christoph Both | J23: Lufthansa Process Management | K23: 1 | M23: Track 1 (Pavilion 1) | N23: Pavilion 1 | O23: Track 1(Pavilion 1)
A24: 23 | B24: Day 3 | C24: 0.51041667 | E24: Airport & Airline Collaboration | F24: Presentation | G24: Presentation: 638 Days to Go: Transforming the LAX Passenger Experience for the 2028 Olympics and Paralympics | H24: Erin Trapp – Chief Strategy & External Affairs Officer, Los Angeles World Airports | I24: Erin Trapp | J24: Los Angeles World Airports | K24: 1 | M24: Keynote Stage 2 (Pavilion 2) | N24: Pavilion 2 | O24: Keynote Stage 2 (Pavilion 2)
A25: 24 | B25: Day 3 | C25: 0.51041667 | E25: Loyalty | F25: Presentation | G25: Presentation: Beyond miles and seats: building the future of travel loyalty | H25: Ofir Goldman – Director of Global Marketing & Digital, EL AL Israel Airlines Benny Yonovich – Co-Founder & CEO, Arbitrip | I25: Ofir Goldman, Benny Yonovich | J25: EL AL Israel Airlines, Arbitrip | K25: 2 | M25: Track 3 (Pavilion 1) | N25: Pavilion 1 | O25: Track 3 (Pavillion 1) | P25: How can airlines turn hotel bookings into a new engine for growth? EL AL and Arbitrip will share the story behind EL AL Travel, showcasing how their partnership brings hotels into the airline’s core offering. The session will explore how airlines can expand beyond flights, generate incremental revenue from hotels and ancillary services, and strengthen customer loyalty by making the entire travel experience part of their brand.
A26: 25 | B26: Day 3 | C26: 0.51388889 | E26: Startup Theatre | F26: Startup Pitch | G26: Crew Feedback: From Qualitative to Quantitative Data | H26: Tuur Willio – Junior Commercial Associate, JiGSO | I26: Tuur Willio | J26: JiGSO | K26: 1 | M26: Startup Theatre | O26: Startup Theatre
A27: 26 | B27: Day 3 | C27: 0.52083333 | E27: Digital & IT | F27: Panel | G27: Panel: Delivering modern airline retailing – how do we make offer & order work? | H27: Jörg Ahrens – Head of IT Commercial Systems, Condor Flugdienst GmbH Bhaskara Guntreddy – Senior Vice President, Product, PROS Marco Contento – VP Aviation Business Services, IBS Software | I27: Jörg Ahrens, Bhaskara Guntreddy, Marco Contento | J27: Condor Flugdienst GmbH, PROS, IBS Software | K27: 3 | L27: 2 | M27: Track 1 (Pavilion 1) | N27: Pavilion 1 | O27: Track 1(Pavilion 1) | P27: Where are airlines actually live with Offer & Order today - and what has it taken to get there? • How are teams connecting commercial, distribution and IT to move from roadmap to delivery? • What are the toughest integration challenges across PSS, pricing, payments and fulfilment? How do we work through these? • What delivery models are emerging - phased rollouts, parallel systems or full migration? • What defines success when modern airline retailing is fully embedded into core systems?
A28: 27 | B28: Day 3 | C28: 0.52083333 | E28: Retail | F28: Panel | G28: Panel: Dynamic bundling: Rethinking systems and products for the intuitive traveller | H28: Tiddo Veldhuis – VP Offer Management & Ancillaries, Air France KLM Sharon Huetson – Head of Proposition, easyJet Jay Sorensen – President, IdeaWorksCompany | I28: Tiddo Veldhuis, Sharon Huetson, Jay Sorensen | J28: Air France KLM, easyJet, IdeaWorksCompany | K28: 3 | L28: 1 | M28: Track 5 (Pavilion 1) | N28: Pavilion 1 | O28: Track 5 (Pavilion 1) | P28: Moving away from rigid "Basic/Flex" fare structures toward AI-generated bundles created on-the-fly based on real-time traveller intent • Navigating personalised pricing to ensure it remains a value-add rather than a regulatory or reputational risk • Strategies for seamlessly integrating lifestyle and non-air ancillaries, such as hotels, tours, and carbon offsets, into the initial booking flow • Why has personalisation historically failed to meet expectations and do personalisation tactics in ancillary sales need a rethink?
A29: 28 | B29: Day 3 | C29: 0.52083333 | E29: Airport & Airline Collaboration | F29: Panel | G29: Panel: Who owns the passenger & captures the value – and are airports and airlines ready for co-ownership? | H29: Arturs Saveljevs – Board member and CCO, Riga International Airport Iyad Hindiyeh – CDO, GAL - GMR Group Mihai Tica – CIO, Dusseldorf Airport | I29: Arturs Saveljevs, Iyad Hindiyeh, Mihai Tica | J29: Riga International Airport, GAL - GMR Group, Dusseldorf Airport | K29: 3 | L29: 2 | M29: Keynote Stage 2 (Pavilion 2) | N29: Pavilion 2 | O29: Keynote Stage 2 (Pavilion 2) | P29: Who truly owns passenger data across the journey - and how does that ownership shift between booking, airport and arrival? • What is the real commercial upside of sharing data and which joint revenue opportunities (retail, e-commerce, ancillaries) depend on it? • Where do competitive sensitivities, loyalty programmes and margin pressures still block deeper collaboration? • Can airports build meaningful data platforms without airlines or is joint architecture across airlines, alliances and groups of airports essential? • Looking ahead, will passenger data sit in collaborative platforms, or remain siloed within airline and airport ecosystems?
A30: 29 | B30: Day 3 | C30: 0.52083333 | E30: Loyalty | F30: Talk | G30: Unpacking the next evolution of AI and personalisation within airline loyalty | H30: Tiffany Funk – Head of Flying Blue, VP Loyalty, Air France KLM Omer Faruk Sonmez – Senior Vice President Marketing, Turkish Airlines Nejib Ben-Khedher – Divisional Senior Vice President, Skywards, EMIRATES GROUP | I30: Tiffany Funk, Omer Faruk Sonmez, Nejib Ben-Khedher | J30: Air France KLM, Turkish Airlines, EMIRATES GROUP | K30: 3 | L30: 3 | M30: Track 3 (Pavilion 1) | N30: Pavilion 1 | O30: Track 3 (Pavillion 1) | P30: Moving beyond tier-based recognition • Using loyalty data when the journey goes wrong • Extending member value across the travel ecosystem • Taking AI-powered loyalty from isolated use cases to scale
A31: 30 | B31: Day 3 | C31: 0.52083333 | E31: AI / ML | F31: Presentation | G31: Presentation: One memory, every touchpoint: How AI can connect the traveller journey from app to gate to seat | H31: Mahesh Veda – Managing Director, United Airlines Raj Sivakumar – Corporate Senior Vice President, WNS Global Services (UK) Limited | I31: Mahesh Veda, Raj Sivakumar | J31: United Airlines, WNS Global Services (UK) Limited | K31: 2 | M31: Track 9 (Pavilion 2) | N31: Pavilion 2 | O31: Track 9 (Pavilion 2) | P31: Every airline delivers personalization across multiple channels, but continuity often breaks as the traveler moves from one touchpoint to another. • What changes when AI moves beyond recommending and starts anticipating? • In this session, Mahesh Veda of United Airlines and Jitender Mohan of WNS will explore how airlines can create a connected, context-aware understanding of each traveler across the app, airport, gate and onboard experience. • The discussion will examine how AI, loyalty data and real-time customer insight can come together to simplify journeys, strengthen engagement and unlock new revenue opportunities. • Key Themes • Moving from channel-level personalization to journey-level continuity • Using AI to anticipate traveler needs and determine the next best action • Connecting digital, airport and onboard experiences • Bringing together eCommerce, loyalty, customer data and operations • Converting personalization into stronger engagement, loyalty and enterprise value
A32: 31 | B32: Day 3 | C32: 0.52083333 | E32: Startup Theatre | F32: Startup Pitch | G32: Insights from deploying AI across 50'000 flights per month | H32: Nikita Kaeshko – Co-founder, Overwatch AI | I32: Nikita Kaeshko | J32: Overwatch AI | K32: 1 | M32: Startup Theatre | O32: Startup Theatre
A33: 32 | B33: Day 3 | C33: 0.52777778 | E33: Startup Theatre | F33: Startup Pitch | G33: What a System of Action can do for an Airline | H33: Jim Stathopoulos – Co-founder, dCortex | I33: Jim Stathopoulos | J33: dCortex | K33: 1 | M33: Startup Theatre | O33: Startup Theatre
A34: 33 | B34: Day 3 | C34: 0.53125 | E34: AI / ML | F34: Panel | G34: Panel: Discussing the challenges of driving successful strategic AI adoption, impactful solutions and evaluating the financial return | H34: Ivan Karlovic – Director of data, analytics, and AI, Norwegian Kushal Pasari – Director - AI/ML Engineering & Platforms, United Airlines Tauseef Khan – Manager of Data & AI, Air Canada | I34: Ivan Karlovic, Kushal Pasari, Tauseef Khan | J34: Norwegian, United Airlines, Air Canada | K34: 3 | L34: 2 | M34: Track 9 (Pavilion 2) | N34: Pavilion 2 | O34: Track 9 (Pavilion 2) | P34: How can airlines lay the foundations for effective AI implementation in a rapidly evolving ecosystem? • Working across the business to evaluate impactful opportunities for AI powered solutions to change the game • How are airlines planning to scale data-science powered innovation effectively?
A35: 34 | B35: Day 3 | C35: 0.53472222 | E35: Startup Theatre | F35: Startup Pitch | G35: SeatMaps of Record: data & visualizations for airlines and channel. | H35: Terje Tjostolvsen – Adviser, Seatmaps Ltd | I35: Terje Tjostolvsen | J35: Seatmaps Ltd | K35: 1 | M35: Startup Theatre | O35: Startup Theatre
A36: 35 | B36: Day 3 | C36: 0.54166667 | E36: Startup Theatre | F36: Startup Pitch | G36: Building ReLUGG - solving your own problem as a founder | H36: Melilizwe Gqobo – CEO & Co-founder, ReLUGG | I36: Melilizwe Gqobo | J36: ReLUGG | K36: 1 | M36: Startup Theatre | O36: Startup Theatre
A37: 36 | B37: Day 3 | C37: 0.54861111 | E37: Startup Theatre | F37: Startup Pitch | G37: AEROMOND – The Next-Gen On-Board Service Experience | H37: Sebastian Pruckmair – Founder & CEO, AEROMOND Services e.u. | I37: Sebastian Pruckmair | J37: AEROMOND Services e.u. | K37: 1 | M37: Startup Theatre | O37: Startup Theatre
A38: 37 | B38: Day 3 | C38: 0.55208333 | D38: 0.59375 | E38: Workshop | F38: Workshop | G38: Portugal in the Future Aviation Ecosystem: Clean Aviation, AAM & MR **Registration required | H38: Rui Santos Jose Rui Marcelino Margarida Pinto Dário Pedro Nelson Vaz David Cruz | I38: Rui Santos, Jose Rui Marcelino, Margarida Pinto, Dário Pedro, Nelson Vaz, David Cruz | K38: 6 | M38: Track 5 (Pavilion 1) | N38: Pavilion 1 | O38: Track 5, Pavilion 1 | Q38: 26 | R38: 50 | S38: =R38-Q38 -> 24 | T38: Open
A39: 38 | B39: Day 3 | C39: 0.55555556 | E39: Startup Theatre | F39: Startup Pitch | G39: Beyond the Forecast: Turning Weather into Aviation Intelligence | H39: Sevim Aydın Kotil – Head of Business Development, Buluttan Weather Intelligence | I39: Sevim Aydın Kotil | J39: Buluttan Weather Intelligence | K39: 1 | M39: Startup Theatre | O39: Startup Theatre
A40: 39 | B40: Day 3 | C40: 0.5625 | E40: Airline Keynote | F40: Competition | G40: Competition: Ancillary Arena | H40: Beatriz Guillen – Chief Customer Officer, Iberia Surya Kuchibotla – VP eCommerce, Ancillary and Retailing, OMAN AIR Lissette Castaneda – Head of Ancillary Revenue, Tap Air Portugal | I40: Beatriz Guillen, Surya Kuchibotla, Lissette Castaneda | J40: Iberia, OMAN AIR, Tap Air Portugal | K40: 3 | L40: 7 | M40: Keynote Stage 1 (Pavilion 1) | N40: Pavilion 1 | O40: Keynote Stage (Pavilion 1) | P40: We are on the hunt for the next big ancillary product or service. Join this session to hear from our 5 finalist companies who will be pitching their solution to our expert panel: • Riyadh Air (PointsXchange) • InterLnkd (NEXORA) • Retailaer • VINI (Flyvbird GmbH) • Roamon
A41: 40 | B41: Day 3 | C41: 0.5625 | E41: Startup Theatre | F41: Startup Pitch | G41: Bonafide AI: Context is Everything | H41: Chris Brown – Founder, Chief Product Officer, Bonafide | I41: Chris Brown | J41: Bonafide | K41: 1 | M41: Startup Theatre | O41: Startup Theatre
A42: 41 | B42: Day 3 | C42: 0.5625 | D42: 0.57986111 | E42: Roundtable | F42: Roundtable | G42: Roundtable 1: The Augmented Manager: Empowering middle management in the age of AI | H42: Dirk Jungnickel | I42: Dirk Jungnickel | K42: 1 | M42: Roundtable Area (Pavilion 2) | N42: Pavilion 2 | O42: Round Table Area, Pavilion 2 | Q42: 36 | R42: 40 | S42: =R42-Q42 -> 4 | T42: Open
A43: 42 | B43: Day 3 | C43: 0.5625 | D43: 0.57986111 | E43: Roundtable | F43: Roundtable | G43: Roundtable 2: AI Is Moving Faster Than Us: How Do We Get Our People Ready? | H43: Ben Dias | I43: Ben Dias | K43: 1 | M43: Roundtable Area (Pavilion 2) | N43: Pavilion 2 | O43: Round Table Area, Pavilion 2 | Q43: 39 | R43: 50 | S43: =R43-Q43 -> 11 | T43: Open
A44: 43 | B44: Day 3 | C44: 0.57638889 | E44: Innovation | F44: Talk | G44: Built From Scratch: Insights from female founders | H44: Barbara Bassi Modalek – CEO & Founder, Virtuwella emna TOUIHRI – Co-founder&CEO, AERAUT Sally Bunnell – CEO & Founder, Navi Savi Video Travel Marketplace | I44: Barbara Bassi Modalek, emna TOUIHRI, Sally Bunnell | J44: Virtuwella, AERAUT, Navi Savi Video Travel Marketplace | K44: 3 | L44: 3 | M44: Startup Theatre | O44: Startup Theatre
A45: 44 | B45: Day 3 | C45: 0.58333333 | E45: Digital & IT | F45: Fireside Chat | G45: Fireside Chat: From roadmap to delivery – what it takes to execute digital at scale | H45: Uma Gopinath – SVP and Chief Information Officer, Porter Airlines Mark Lenahan – Consultant, Lenahan Consulting Ltd | I45: Uma Gopinath, Mark Lenahan | J45: Porter Airlines, Lenahan Consulting Ltd | K45: 2 | M45: Track 1 (Pavilion 1) | N45: Pavilion 1 | O45: Track 1(Pavilion 1)
A46: 45 | B46: Day 3 | C46: 0.58333333 | E46: Loyalty | F46: Fireside Chat | G46: Fireside chat: Promise & Execution: creating loyalty benefit alignment and delivery across 15+ airlines | H46: Gilbert Ott – Director, Loyalty, oneworld Alliance Harald Deprosse – Partner, Envolved GmbH | I46: Gilbert Ott, Harald Deprosse | J46: oneworld Alliance, Envolved GmbH | K46: 2 | M46: Track 3 (Pavilion 1) | N46: Pavilion 1 | O46: Track 3 (Pavilion 1)
A47: 46 | B47: Day 3 | C47: 0.58333333 | E47: Airport & Airline Collaboration | F47: Fireside Chat | G47: Fireside Chat: Co-creating the future journey: how CVG turns airport pilots into shared value | H47: Adam Kressler – Vice President of Customer Experience, Cincinnati/Northern Kentucky International Airport (CVG) Luis Felipe De Oliveira – Executive Director and CEO, Exactly Consulting and Services Sarl | I47: Adam Kressler, Luis Felipe De Oliveira | J47: Cincinnati/Northern Kentucky International Airport (CVG), Exactly Consulting and Services Sarl | K47: 2 | M47: Keynote Stage 2 (Pavilion 2) | N47: Pavilion 2 | O47: Keynote Stage 2 (Pavilion 2)
A48: 47 | B48: Day 3 | C48: 0.58333333 | E48: AI / ML | F48: Fireside Chat | G48: Fireside Chat: AI in airports – from experimentation to operational impact | H48: Annemijn Schoenmaker – Head of Business Platform Infrastructure & IT Projects, Schiphol Group Oliver Hendry – Program Director, Airports AI Alliance | I48: Annemijn Schoenmaker, Oliver Hendry | J48: Schiphol Group, Airports AI Alliance | K48: 2 | M48: Track 9 (Pavilion 2) | N48: Pavilion 2 | O48: Track 9 (Pavilion 2)
A49: 48 | B49: Day 3 | C49: 0.59375 | E49: AI / ML | F49: Talk | G49: When the Chatbot Speaks for your Airline: Building Trust in Customer-Facing AI | H49: Balamurali Boggu – Airline Domain Expert, TestSolutions Anupam Krishnamurthy – Head of AI Testing, TestSolutions | I49: Balamurali Boggu, Anupam Krishnamurthy | J49: TestSolutions | K49: 2 | M49: Track 9 (Pavilion 2) | N49: Pavilion 2 | O49: Track 9 (Pavilion 2)
A50: 49 | B50: Day 3 | C50: 0.59375 | E50: Airport & Airline Collaboration | F50: Panel | G50: Panel: Designing the passenger journey together – how do airports, airlines and partners deliver a truly shared experience? | H50: Karen Ellis – Airport Assistant General Manager - Chief Customer Experience Officer, City of Atlanta/ Hartsfield- Jackson International Airport Harry Barrett – Assistant Director of Airports, Sacramento County International Airport Girish Nair – Chief Operating Officer, Bangalore International Airport | I50: Karen Ellis, Harry Barrett, Girish Nair | J50: City of Atlanta/ Hartsfield- Jackson International Airport, Sacramento County International Airport, Bangalore International Airport | K50: 3 | L50: 5 | M50: Keynote Stage 2 (Pavilion 2) | N50: Pavilion 2 | O50: Keynote Stage 2 (Pavilion 2) | P50: Where are airports, airlines and partners still redesigning the journey in isolation rather than taking an end-to-end passenger view? • Can joint experimentation and testbeds reduce duplication and help scale innovations faster? • How do we connect physical and digital journeys? Terminal design, baggage systems and intermodal links with apps and digital tools? • How should performance metrics evolve so NPS, OTP, dwell time and spend reflect joint ownership of the passenger experience? • What will make partnerships across airlines, airports and suppliers work to deliver a joint-up experience? • By 2030, what should passengers tangibly experience if airports and airlines are truly innovating together?
A51: 50 | B51: Day 3 | C51: 0.59375 | E51: Loyalty | F51: Talk | G51: The Loyalty Value Equation – Balancing profitability and customer trust | H51: Jason Cooper – CEO, Gyoza Flights Harald Deprosse – Partner, Envolved GmbH Gilbert Ott – Director, Loyalty, oneworld Alliance | I51: Jason Cooper, Harald Deprosse, Gilbert Ott | J51: Gyoza Flights, Envolved GmbH, oneworld Alliance | K51: 3 | M51: Track 3 (Pavilion 1) | N51: Pavilion 1 | O51: Track 3 (Pavillion 1) | P51: Maintaining the balance between airline profitability and perceived customer value in loyalty programs • How is tech reshaping the loyalty value equation, considering dynamic rewards, flexible redemption, and real-time pricing of benefits? • Transactional vs emotional loyalty in the age of automation: can technology strengthen customer trust rather than erode it? • Creating value from the customer data loyalty schemes create: how is loyalty data being interrogated to support commercial decisions?
A52: 51 | B52: Day 3 | C52: 0.59375 | E52: Digital & IT | F52: Panel | G52: Panel: Turning strategy into delivery - how do we build technology the business actually needs? | H52: Mariana Zaparolli – Director - Digital Capabilities and Accelerators, LATAM Airlines Edem Akan – Director, Enterprise Transformation, Porter Airlines Mustafa Al-Ausaje – Executive consultant, Director, Technology Strategy and Transformation, Greater Toronto Airports Authority | I52: Mariana Zaparolli, Edem Akan, Mustafa Al-Ausaje | J52: LATAM Airlines, Porter Airlines, Greater Toronto Airports Authority | K52: 3 | L52: 2 | M52: Track 1 (Pavilion 1) | N52: Pavilion 1 | O52: Track 1(Pavilion 1) | P52: How do airlines prioritise technology investment against real business outcomes? • Where do digital transformation programmes most often lose momentum? • How do IT, product and business teams share ownership of delivery? • How do airlines avoid building technology that adds complexity instead of solving problems? • What separates airlines that consistently turn digital investment into measurable business value?
A53: 52 | B53: Day 3 | C53: 0.60416667 | E53: AI / ML | F53: Talk | G53: Sharing achievements and learnings from rapid innovation with AI: what solutions progressed beyond POC? | H53: Mark Wallace – Head of Data Science, easyJet Şeniz Gayde Ayata – Vice President Data & AI, Turkish Airlines Murali Karthik – Head of EA, Governance, Data & AI, Agentic COE, Air India | I53: Mark Wallace, Şeniz Gayde Ayata, Murali Karthik | J53: easyJet, Turkish Airlines, Air India | K53: 3 | L53: 1 | M53: Track 9 (Pavilion 2) | N53: Pavilion 2 | O53: Track 9 (Pavilion 2)
A54: 53 | B54: Day 3 | C54: 0.60416667 | E54: Airline Keynote | F54: Panel | G54: Digital Product Panel: What is next for digital platforms in an increasingly online world | H54: Carlos Faxas – Vice President, Digital Products, Air Canada Sara Walter de Freitas – Director Digital & e-Commerce, Tap Air Portugal Ofir Goldman – Director of Global Marketing & Digital, EL AL Israel Airlines | I54: Carlos Faxas, Sara Walter de Freitas, Ofir Goldman | J54: Air Canada, Tap Air Portugal, EL AL Israel Airlines | K54: 3 | L54: 3 | M54: Keynote Stage 1 (Pavilion 1) | N54: Pavilion 1 | O54: Keynote Stage 1 (Pavilion 1) | P54: How are our panellists building AI into the development of digital platforms today to support innovation tomorrow? • Delivering seamless and relevant online experience across the full customer journey • How are airlines increasing relevant personalisation and contextualised communication whilst maintaining customer trust? • Supporting colleagues effectively with digital platforms & insights to optimise job satisfaction, efficiency and value
A55: 54 | B55: Day 3 | C55: 0.61458333 | E55: Startup Theatre | F55: Startup Pitch | G55: How to Cut Boarding Time in Half | H55: Romaric Régnaud – CEO, Gate Stream | I55: Romaric Régnaud | J55: Gate Stream | K55: 1 | M55: Startup Theatre | O55: Startup Theatre
A56: 55 | B56: Day 3 | C56: 0.63541667 | E56: Airline Keynote | F56: Competition | G56: Battle of the Apps | H56: Oisin Lunny – Event MC, Journalist, Podcast and Webinar Host, Galaxy of OM, S.L. Glenn Morgan – Partner, SkiesFifty Jonas von Kruechten – Principal Advisor (dgtlsky), Dgtlsky | I56: Oisin Lunny, Glenn Morgan, Jonas von Kruechten | J56: Galaxy of OM, S.L., SkiesFifty, Dgtlsky | K56: 3 | L56: 6 | M56: Keynote Stage 1 (Pavilion 1) | N56: Pavilion 1 | O56: Keynote Stage (Pavilion 1)

Sheet All Sessions
A1: # | B1: Day | C1: Start | D1: End | E1: Stream / Category | F1: Format | G1: Session Title | H1: Speakers (Name – Job Title, Company) | I1: Speaker Names | J1: Organisations | K1: Speakers Listed | L1: Additional Speakers (not shown on site) | M1: Room / Stage | N1: Pavilion | O1: Room (as listed on site) | P1: Description / Discussion Points | Q1: Registered | R1: Capacity | S1: Places Left | T1: Registration Status
A2: 1 | B2: Day 2 | C2: 0.34375 | E2: Networking | F2: Networking | G2: Aviation Connect: Session 6 | H2: Host, World Aviation Festival | I2: Host | J2: World Aviation Festival | K2: 1 | M2: Aviation Connect Zone (Pavilion 2) | N2: Pavilion 2 | O2: Aviation Connect Zone Pavilion 2
A3: 2 | B3: Day 2 | C3: 0.38194444 | E3: Airline Keynote | F3: Welcome | G3: Official Welcome | H3: Carlos Oliveira – Chairman, Tap Air Portugal | I3: Carlos Oliveira | J3: Tap Air Portugal | K3: 1 | M3: Keynote Stage 1 (Pavilion 1) | N3: Pavilion 1 | O3: Keynote Theatre (Pavilion 1)
A4: 3 | B4: Day 2 | C4: 0.38541667 | E4: Airport Keynote | F4: Welcome | G4: Official Airport Partner Welcome | H4: Thierry Ligonnière – Chief Executive Officer, ANA Aeroportos de Portugal | I4: Thierry Ligonnière | J4: ANA Aeroportos de Portugal | K4: 1 | M4: Keynote Stage 2 (Pavilion 2) | N4: Pavilion 2 | O4: Keynote Stage 2 (Pavilion 2)
A5: 4 | B5: Day 2 | C5: 0.38888889 | E5: Airport Keynote | F5: Interview | G5: CEO Interview: Stefan Schulte, CEO, Fraport AG | H5: Stefan Schulte – Chief Executive Officer, Fraport AG Ben Thompson – Presenter, BBC | I5: Stefan Schulte, Ben Thompson | J5: Fraport AG, BBC | K5: 2 | M5: Keynote Stage 2 (Pavilion 2) | N5: Pavilion 2 | O5: Keynote Stage 2 (Pavilion 2)
A6: 5 | B6: Day 2 | C6: 0.38888889 | E6: Airline Keynote | F6: Interview | G6: CEO Interview: Luis Rodrigues, CEO, TAP Air Portugal | H6: Luís Rodrigues – Chief Executive Officer, Tap Air Portugal Peter Campbell – Global Transport Correspondent, Financial Times | I6: Luís Rodrigues, Peter Campbell | J6: Tap Air Portugal, Financial Times | K6: 2 | M6: Keynote Stage 1 (Pavilion 1) | N6: Pavilion 1 | O6: Keynote Stage 1 (Pavilion 1)
A7: 6 | B7: Day 2 | C7: 0.39583333 | E7: Airline Keynote | F7: Interview | G7: CEO Interview: Adrian Neuhauser, CEO, ABRA Group | H7: Adrian Neuhauser – Chief Executive Officer, Abra Group Peter Campbell – Global Transport Correspondent, Financial Times | I7: Adrian Neuhauser, Peter Campbell | J7: Abra Group, Financial Times | K7: 2 | M7: Keynote Stage 1 (Pavilion 1) | N7: Pavilion 1 | O7: Keynote Stage 1 (Pavilion 1)
A8: 7 | B8: Day 2 | C8: 0.39583333 | E8: Airport Keynote | F8: Interview | G8: CEO Interview: Thierry Ligonnière, CEO, ANA - Aeroportos de Portugal | H8: Thierry Ligonnière – Chief Executive Officer, ANA Aeroportos de Portugal Ben Thompson – Presenter, BBC | I8: Thierry Ligonnière, Ben Thompson | J8: ANA Aeroportos de Portugal, BBC | K8: 2 | M8: Keynote Stage 2 (Pavilion 2) | N8: Pavilion 2 | O8: Keynote Stage 2 (Pavilion 2)
A9: 8 | B9: Day 2 | C9: 0.40277778 | E9: Airport Keynote | F9: Interview | G9: CEO Interview: Pierre-Hugues Schmit, CEO, London Gatwick | H9: Pierre-Hugues Schmit – Chief Executive Officer, London Gatwick Airport Ben Thompson – Presenter, BBC | I9: Pierre-Hugues Schmit, Ben Thompson | J9: London Gatwick Airport, BBC | K9: 2 | M9: Keynote Stage 2 (Pavilion 2) | N9: Pavilion 2 | O9: Keynote Stage 2 (Pavilion 2)
A10: 9 | B10: Day 2 | C10: 0.40277778 | E10: Airline Keynote | F10: Interview | G10: CEO Interview: Roberto Alvo, CEO, LATAM | H10: Roberto Alvo – CEO, Latam Airlines Group Peter Campbell – Global Transport Correspondent, Financial Times | I10: Roberto Alvo, Peter Campbell | J10: Latam Airlines Group, Financial Times | K10: 2 | M10: Keynote Stage 1 (Pavilion 1) | N10: Pavilion 1 | O10: Keynote Stage 1 (Pavilion 1)
A11: 10 | B11: Day 2 | C11: 0.40972222 | E11: Airline Keynote | F11: Panel | G11: Keynote CEO Panel: Writing the next chapter of aviation history in an age of uncertainty | H11: Luís Rodrigues – Chief Executive Officer, Tap Air Portugal Adrian Neuhauser – Chief Executive Officer, Abra Group Roberto Alvo – CEO, Latam Airlines Group | I11: Luís Rodrigues, Adrian Neuhauser, Roberto Alvo | J11: Tap Air Portugal, Abra Group, Latam Airlines Group | K11: 3 | L11: 1 | M11: Keynote Stage 1 (Pavilion 1) | N11: Pavilion 1 | O11: Keynote Stage 1 (Pavilion 1) | P11: Investing in the right areas for growth: identifying true game changes from the trendy fad • Navigating geopolitical instability and preparing for unknowns to reduce the impact of disruption • Long Term Strategy planning by optimising operations and working with industry to solve supply chain constraint • Working as an industry to improve global challenges including sustainability, workforce challenges and safety
A12: 11 | B12: Day 2 | C12: 0.40972222 | E12: Airport Keynote | F12: Interview | G12: CEO Interview: Paul Griffiths, CEO, Dubai Airports | H12: Paul Griffiths – Chief Executive Officer, Dubai Airports Company Ben Thompson – Presenter, BBC | I12: Paul Griffiths, Ben Thompson | J12: Dubai Airports Company, BBC | K12: 2 | M12: Keynote Stage 2 (Pavilion 2) | N12: Pavilion 2 | O12: Keynote Stage 2 (Pavilion 2)
A13: 12 | B13: Day 2 | C13: 0.41666667 | E13: Airport Keynote | F13: Panel | G13: Keynote Panel: Growth without compromise – rethinking the airport model for sustainable growth | H13: Stefan Schulte – Chief Executive Officer, Fraport AG Warwick Brady – President & CEO, SWISSPORT Paul Griffiths – Chief Executive Officer, Dubai Airports Company | I13: Stefan Schulte, Warwick Brady, Paul Griffiths | J13: Fraport AG, SWISSPORT, Dubai Airports Company | K13: 3 | L13: 2 | M13: Keynote Stage 2 (Pavilion 2) | N13: Pavilion 2 | O13: Keynote Stage 2 (Pavilion 2) | P13: How can airports manage growth and capacity through both infrastructure development and smarter use of existing assets? • As traffic rises, how do we maintain operational resilience while protecting the passenger experience? • How can better coordination across airlines, airports and ground handlers reduce operational complexity? • As competition between hubs intensifies, how can airports differentiate through efficiency, technology and experience? • What investments in infrastructure, operations and digital capability will define the most competitive airports over the next 3-5 years?
A14: 13 | B14: Day 2 | C14: 0.44791667 | D14: 0.47916667 | E14: Roundtable | F14: Roundtable | G14: Table 01: FLYR Roundtable - Funding the move to Offer & Order: Creating the right time for the right move | H14: Rodrigo López Josh Crandall | I14: Rodrigo López, Josh Crandall | K14: 2 | M14: Roundtable Area (Pavilion 2) | N14: Pavilion 2 | O14: Roundtable area, Pavilion 2 | Q14: 36 | R14: 40 | S14: =R14-Q14 -> 4 | T14: Open
A15: 14 | B15: Day 2 | C15: 0.44791667 | D15: 0.47916667 | E15: Roundtable | F15: Roundtable | G15: Table 2: ATPCO Roundtable - Airline product catalogs: a foundation for retailing at scale | H15: Doug Sharpe Megan Humphries | I15: Doug Sharpe, Megan Humphries | K15: 2 | M15: Roundtable Area (Pavilion 2) | N15: Pavilion 2 | O15: Roundtable area, Pavilion 2 | Q15: 12 | R15: 40 | S15: =R15-Q15 -> 28 | T15: Open
A16: 15 | B16: Day 2 | C16: 0.44791667 | D16: 0.47916667 | E16: Roundtable | F16: Roundtable | G16: Table 3: 15Below - 10 years of deploying AI in aviation: what works, what doesn’t and what we’ve learned | H16: Ali Tredinnick Joe Bennett | I16: Ali Tredinnick, Joe Bennett | K16: 2 | M16: Roundtable Area (Pavilion 2) | N16: Pavilion 2 | O16: Roundtable area, Pavilion 2 | Q16: 50 | R16: 50 | S16: =R16-Q16 -> 0 | T16: Full
A17: 16 | B17: Day 2 | C17: 0.44791667 | D17: 0.47916667 | E17: Roundtable | F17: Roundtable | G17: Table 4: OneReg Roundtable - Continuous confidence: reimagining how aviation compliance works | H17: Billie Moore Angel Matsis | I17: Billie Moore, Angel Matsis | K17: 2 | M17: Roundtable Area (Pavilion 2) | N17: Pavilion 2 | O17: Roundtable area, Pavilion 2 | Q17: 7 | R17: 40 | S17: =R17-Q17 -> 33 | T17: Open
A18: 17 | B18: Day 2 | C18: 0.44791667 | D18: 0.47916667 | E18: Roundtable | F18: Roundtable | G18: Table 5: Seatboost Roundtable - The gate-side goldmine: Gamification, dynamic pricing, and monetizing the premium cabin | H18: Kevin Stamler | I18: Kevin Stamler | K18: 1 | M18: Roundtable Area (Pavilion 2) | N18: Pavilion 2 | O18: Roundtable area, Pavilion 2 | Q18: 18 | R18: 40 | S18: =R18-Q18 -> 22 | T18: Open
A19: 18 | B19: Day 2 | C19: 0.44791667 | D19: 0.47916667 | E19: Roundtable | F19: Roundtable | G19: Table 6: Ping Identity Roundtable - Whose agent is it anyway? | H19: Alexander Laurie Emanuela Maftieu | I19: Alexander Laurie, Emanuela Maftieu | K19: 2 | M19: Roundtable Area (Pavilion 2) | N19: Pavilion 2 | O19: Roundtable area, Pavilion 2 | Q19: 1 | R19: 40 | S19: =R19-Q19 -> 39 | T19: Open
A20: 19 | B20: Day 2 | C20: 0.44791667 | D20: 0.47916667 | E20: Roundtable | F20: Roundtable | G20: Table 7: ADA Roundtable - Agentic IROPs: Turning flight re-accom into your biggest loyalty moment | H20: Mike Murchison Tatiana Deabreu | I20: Mike Murchison, Tatiana Deabreu | K20: 2 | M20: Roundtable Area (Pavilion 2) | N20: Pavilion 2 | O20: Roundtable area, Pavilion 2 | Q20: 31 | R20: 40 | S20: =R20-Q20 -> 9 | T20: Open
A21: 20 | B21: Day 2 | C21: 0.44791667 | D21: 0.47916667 | E21: Roundtable | F21: Roundtable | G21: Table 8: Lufthansa Industry Solutions Roundtable - How airports, airlines and partners can create value through collaboration | H21: Karina Mehl Michael Kleinert | I21: Karina Mehl, Michael Kleinert | K21: 2 | M21: Roundtable Area (Pavilion 2) | N21: Pavilion 2 | O21: Roundtable area, Pavilion 2 | Q21: 40 | R21: 40 | S21: =R21-Q21 -> 0 | T21: Full
A22: 21 | B22: Day 2 | C22: 0.44791667 | D22: 0.47916667 | E22: Roundtable | F22: Roundtable | G22: Table 9: Chubb Roundtable - When delays happen, payouts shouldn't wait. Using parametrics to turn flight disruption into passenger loyalty. | H22: Ruben Rivero | I22: Ruben Rivero | K22: 1 | M22: Roundtable Area (Pavilion 2) | N22: Pavilion 2 | O22: Roundtable area, Pavilion 2 | Q22: 9 | R22: 40 | S22: =R22-Q22 -> 31 | T22: Open
A23: 22 | B23: Day 2 | C23: 0.44791667 | D23: 0.47916667 | E23: Roundtable | F23: Roundtable | G23: Table10: Intellicene Roundtable - The connected airport: Turning data into operational intelligence | H23: Matthew Maychrowitz Rebecca Rea | I23: Matthew Maychrowitz, Rebecca Rea | K23: 2 | M23: Roundtable Area (Pavilion 2) | N23: Pavilion 2 | O23: Roundtable area, Pavilion 2 | Q23: 26 | R23: 40 | S23: =R23-Q23 -> 14 | T23: Open
A24: 23 | B24: Day 2 | C24: 0.44791667 | D24: 0.47916667 | E24: Roundtable | F24: Roundtable | G24: Table11: Thoughtspot Roundtable - From Insight to Action: How aviation leaders are scaling agentic analytics | H24: James Davies Charlotte Ross | I24: James Davies, Charlotte Ross | K24: 2 | M24: Roundtable Area (Pavilion 2) | N24: Pavilion 2 | O24: Roundtable area, Pavilion 2 | Q24: 23 | R24: 40 | S24: =R24-Q24 -> 17 | T24: Open (you are registered)
A25: 24 | B25: Day 2 | C25: 0.44791667 | D25: 0.47916667 | E25: Roundtable | F25: Roundtable | G25: Table12: Volantio Roundtable - Beyond the AI hype: Can agents finally connect revenue, operations and customer experience? | H25: Ana Maria Escobar Azim Barodawala | I25: Ana Maria Escobar, Azim Barodawala | K25: 2 | M25: Roundtable Area (Pavilion 2) | N25: Pavilion 2 | O25: Roundtable area, Pavilion 2 | Q25: 13 | R25: 40 | S25: =R25-Q25 -> 27 | T25: Open
... A33: 32 | B33: Day 2 | C33: 0.44791667 | D33: 0.47916667 | E33: Roundtable | F33: Roundtable | G33: Table20: Zingly Roundtable - Case study: AI in production at Pegasus Airlines: Beyond deflection to completed passenger journeys | H33: Baris Findik Gaurav Passi | I33: Baris Findik, Gaurav Passi | K33: 2 | M33: Roundtable Area (Pavilion 2) | N33: Pavilion 2 | O33: Roundtable area, Pavilion 2 | Q33: 10 | R33: 40 | S33: =R33-Q33 -> 30 | T33: Open
A34: 33 | B34: Day 2 | C34: 0.47916667 | E34: Networking | F34: Networking | G34: Aviation Connect: Session 3 | H34: Host, World Aviation Festival | I34: Host | J34: World Aviation Festival | K34: 1 | M34: Aviation Connect Zone (Pavilion 2) | N34: Pavilion 2 | O34: Aviation Connect Zone Pavilion 2 | P34: Aviation Connect is our dedicated networking hour. Book 15 minute meetings via the Aviation Connect Platform and make the most of your time at WAF. No other sessions, workshops or activities are taking place during this time.
A35: 34 | B35: Day 2 | C35: 0.51736111 | E35: Loyalty | F35: Chair Remarks | G35: Chair opening remarks | H35: Harald Deprosse – Partner, Envolved GmbH | I35: Harald Deprosse | J35: Envolved GmbH | K35: 1 | M35: Track 3 (Pavilion 1) | N35: Pavilion 1 | O35: Track 3 (Pavilion 1)
A36: 35 | B36: Day 2 | C36: 0.52083333 | E36: Sustainability | F36: Fireside Chat | G36: Fireside Chat: Growth without compromise – can airlines decarbonise while remaining competitive? | H36: Maria Whittaker – Chief Corporate Responsibility Officer, Abra Group Patrick Edmond – Chief Commercial Officer, Future Energy Global | I36: Maria Whittaker, Patrick Edmond | J36: Abra Group, Future Energy Global | K36: 2 | M36: Track 10 (Pavilion 2) | N36: Pavilion 2 | O36: Track 10 (Pavilion 2)
A37: 36 | B37: Day 2 | C37: 0.52083333 | E37: Loyalty | F37: Welcome | G37: Plusgrade Welcome | H37: Richard Wolfman – SVP Global Business Development, Plusgrade | I37: Richard Wolfman | J37: Plusgrade | K37: 1 | M37: Track 3 (Pavilion 1) | N37: Pavilion 1 | O37: Track 3, Pav 1
A38: 37 | B38: Day 2 | C38: 0.52430556 | E38: AI / ML | F38: Presentation | G38: Presentation: Building tomorrow’s airline: AI-orchestrated, human-led | H38: Oliver Schmitt – CEO Digital Hangar Ecosystem & SVP Digital Solutions, Lufthansa Group Digital Hangar GmbH | I38: Oliver Schmitt | J38: Lufthansa Group Digital Hangar GmbH | K38: 1 | M38: Track 9 (Pavilion 2) | N38: Pavilion 2 | O38: Track 9, Pavilion 2
A39: 38 | B39: Day 2 | C39: 0.52430556 | E39: Customer Experience | F39: Talk | G39: Human connection, effortless digital experiences: premium CX in the age of AI | H39: Bethan Lynch – VP Customer Experience & Loyalty, Virgin Atlantic Jerry Angrave – Customer Experience Director, Empathyce | I39: Bethan Lynch, Jerry Angrave | J39: Virgin Atlantic, Empathyce | K39: 2 | M39: Track 2 (Pavilion 1) | N39: Pavilion 1 | O39: Track 2 (Pavilion 1) | P39: AI will transform how consumers plan, shop and make the most of travel. But what does the future look like for premium travellers who expect personalised, memorable experiences and genuine emotional connection? • In this fireside chat, Virgin Atlantic’s VP Customer Experience & Loyalty, Bethan Lynch, joins Jerry Angrave to share how the airline is embracing innovative use of AI to serve its customers more personally and seamlessly, while upholding its unique culture, built around its people and their unmistakeable warmth and flair. On its journey to become the most loved travel company, Bethan will explain how Virgin Atlantic sees AI as an extension of the human-centred experience. An opportunity to remove friction and make every interaction meaningful and distinctly Virgin, while enabling people to do what only people can do: create trust, build connection and make customers feel genuinely cared for. • Combining humanity with innovation, also hear how Virgin Atlantic is doubling down on its premium experience across the customer journey, including the rollout of free, high speed Starlink Wi-Fi, new expanded Upper and Premium cabins, investment in award-winning Clubhouses, and a new app integrated with Virgin Atlantic Concierge, powered by OpenAI and built in partnership with Tomoro. Through its brand, people, and the award-winning experience they deliver, Virgin Atlantic is creating emotional connections that last long after the journey ends – building loyalty and enticing customers to choose Virgin Atlantic time and again.
A40: 39 | B40: Day 2 | C40: 0.52430556 | E40: Loyalty | F40: Fireside Chat | G40: Fireside Chat: The future outlook for loyalty at Abra Group | H40: Ralph Piket – Chief Loyalty Officer, Abra Group Harald Deprosse – Partner, Envolved GmbH | I40: Ralph Piket, Harald Deprosse | J40: Abra Group, Envolved GmbH | K40: 2 | M40: Track 3 (Pavilion 1) | N40: Pavilion 1 | O40: Track 3, Pavilion 1
A41: 40 | B41: Day 2 | C41: 0.52430556 | E41: IROPS | F41: Presentation | G41: Presentation: Project ConnectOps: Delivering highly contextualised and realtime information to optimise insights for crew, airport and operational staff | H41: Rachel Gaud – Ops Digital Transformation Lead, Etihad | I41: Rachel Gaud | J41: Etihad | K41: 1 | M41: Track 4 (Pavilion 1) | N41: Pavilion 1 | O41: Track 4 (Pavilion 1)
A42: 41 | B42: Day 2 | C42: 0.52430556 | E42: Digital & IT | F42: Fireside Chat | G42: Fireside Chat: From mainframe to cloud: Air Canada’s modernisation playbook | H42: Mel Crocker – CIO, Air Canada David Peller – General Partner & Founder, If Not You Capital | I42: Mel Crocker, David Peller | J42: Air Canada, If Not You Capital | K42: 2 | M42: Track 1 (Pavilion 1) | N42: Pavilion 1 | O42: Track 1(Pavilion 1)
A43: 42 | B43: Day 2 | C43: 0.52430556 | E43: Airport - Operations | F43: Presentation | G43: Presentation: Becoming a more data driven airport system – collaboration between all stakeholders | H43: Samuel C. Ehrat – Senior Project Leader, Zurich Airport Lorenz Wolf – ICT Solution Architect, Zurich Airport | I43: Samuel C. Ehrat, Lorenz Wolf | J43: Zurich Airport | K43: 2 | M43: Track 8 (Pavilion 2) | N43: Pavilion 2 | O43: Track 8 (Pavilion 2)
A44: 43 | B44: Day 2 | C44: 0.52430556 | E44: Airport & Airline Collaboration | F44: Presentation | G44: Presentation: Lisette Looren de Jong-Vonk, Programme Manager Innovation Border Management, Ministry of Justice and Security – The Netherlands | H44: Lisette Looren de Jong – Programme Manager Innovation Border Management, Ministry of Justice and Security | I44: Lisette Looren de Jong | J44: Ministry of Justice and Security | K44: 1 | M44: Keynote Stage 2 (Pavilion 2) | N44: Pavilion 2 | O44: Keynote Stage 2 (Pavilion 2)
A45: 44 | B45: Day 2 | C45: 0.52430556 | E45: Airport - Traveller | F45: Presentation | G45: Presentation: Building the digital airport – using mobile and AI assistance to bridge the digital and physical airport experience | H45: Jorn Korbi – VP Digital Commercialization, Avinor | I45: Jorn Korbi | J45: Avinor | K45: 1 | M45: Track 7 (Pavilion 2) | N45: Pavilion 2 | O45: Track 7 (Pavilion 2)
A46: 45 | B46: Day 2 | C46: 0.52430556 | E46: Retail | F46: Fireside Chat | G46: Fireside Chat: Legacy to leader: What cultural and digital shift does the industry need for a modern retail transition? | H46: Julio Rodriguez – Chief Commercial Strategy Officer, IAG Dennis Cary – Managing Director, Cary Strategic Advisory | I46: Julio Rodriguez, Dennis Cary | J46: IAG, Cary Strategic Advisory | K46: 2 | M46: Track 5 (Pavilion 1) | N46: Pavilion 1 | O46: Track 5 (Pavilion 1)
A47: 46 | B47: Day 2 | C47: 0.52430556 | E47: Payments | F47: Presentation | G47: Presentation: The hardest part of Offer & Order is not Offer & Order | H47: Ozan Berk Karataş – Senior Program Manager, Airline Retailing & Payments, Turkish Airlines | I47: Ozan Berk Karataş | J47: Turkish Airlines | K47: 1 | M47: Track 6 (Pavilion 1) | N47: Pavilion 1 | O47: Track 6 (Pavillion 1)
A48: 47 | B48: Day 2 | C48: 0.52777778 | E48: Airline Keynote | F48: Interview | G48: CEO Interview: Joerg Eberhart, CEO, ITA Airways | H48: Joerg Eberhart – Chief Executive Officer, ITA-Airways Peter Campbell – Global Transport Correspondent, Financial Times | I48: Joerg Eberhart, Peter Campbell | J48: ITA-Airways, Financial Times | K48: 2 | M48: Keynote Stage 1 (Pavilion 1) | N48: Pavilion 1 | O48: Keynote Stage 1 (Pavilion 1)
A49: 48 | B49: Day 2 | C49: 0.52777778 | E49: Startup Theatre | F49: Startup Pitch | G49: Mission-Critical Legal: Why Departments Need an Operating System, Not Another Assistant | H49: Katja Nikolaus – CBDO, JUNE GmbH | I49: Katja Nikolaus | J49: JUNE GmbH | K49: 1 | M49: Startup Theatre | O49: Startup Theatre
A50: 49 | B50: Day 2 | C50: 0.53125 | E50: Sustainability | F50: Presentation | G50: Presentation: Airbus' Environmental Blueprint: Pioneering sustainable flight | H50: Bertrand Lestimé – HO Environment and Sustainability Marketing, Airbus S.A.S | I50: Bertrand Lestimé | J50: Airbus S.A.S | K50: 1 | M50: Track 10 (Pavilion 2) | N50: Pavilion 2 | O50: Track 10 (Pavilion 2)
A51: 50 | B51: Day 2 | C51: 0.53472222 | E51: AI / ML | F51: Talk | G51: A decade of innovative AI use cases at Lufthansa Group and the agentic AI future | H51: Dr. Philipp Schade – Head of Business Development & Senior Data Scientist, zeroG | I51: Dr. Philipp Schade | J51: zeroG | K51: 1 | M51: Track 9 (Pavilion 2) | N51: Pavilion 2 | O51: Track 9 (Pavilion 2)
A52: 51 | B52: Day 2 | C52: 0.53472222 | E52: Customer Experience | F52: Presentation | G52: Presentation: AI agents and the new front door: How Alaska Airlines is reshaping customer experience | H52: Andrea Halverson – Director - Contact Center Experience and Innovation, Alaska Airlines Barry Chester – Head of Airlines, Cresta | I52: Andrea Halverson, Barry Chester | J52: Alaska Airlines, Cresta | K52: 2 | M52: Track 2 (Pavilion 1) | N52: Pavilion 1 | O52: Track 2, Pav 1
A53: 52 | B53: Day 2 | C53: 0.53472222 | E53: Airline Keynote | F53: Presentation | G53: Presentation: Leveraging travel fintech to protect revenues and passenger trust during global disruption | H53: Ella Schreiber – SVP and GM Fintech, Hopper Inc Karen Romanchuk – Director, Ancillary Revenue, WestJet | I53: Ella Schreiber, Karen Romanchuk | J53: Hopper Inc, WestJet | K53: 2 | M53: Keynote Stage 1 (Pavilion 1) | N53: Pavilion 1 | O53: Keynote Stage 1 (Pavilion 1)
A54: 53 | B54: Day 2 | C54: 0.53472222 | E54: Digital & IT | F54: Presentation | G54: Presentation: What Offer & Order Looks Like, Live at Riyadh Air | H54: Sam Chamberlain – Chief Product Officer, FLYR Tristan Thomas – Global Industry Leader, IBM | I54: Sam Chamberlain, Tristan Thomas | J54: FLYR, IBM | K54: 2 | M54: Track 1 (Pavilion 1) | N54: Pavilion 1 | O54: Track 1(Pavilion 1) | P54: A demo of what was once impossible, and is now live
A55: 54 | B55: Day 2 | C55: 0.53472222 | E55: Retail | F55: Presentation | G55: Presentation: From transaction to trust – what actually drives airline customer behaviour today | H55: Peter Smith – SVP Travel, Cover Genius US Trading, LLC | I55: Peter Smith | J55: Cover Genius US Trading, LLC | K55: 1 | M55: Track 5 (Pavilion 1) | N55: Pavilion 1 | O55: Track 5 (Pavilion 1)
A56: 55 | B56: Day 2 | C56: 0.53472222 | E56: Airport - Operations | F56: Talk | G56: Transforming operations through connected resource and turnaround solutions | H56: Thomas Sermon – Global Client Director, ZestIoT Technologies B.V. | I56: Thomas Sermon | J56: ZestIoT Technologies B.V. | K56: 1 | M56: Track 8 (Pavilion 2) | N56: Pavilion 2 | O56: Track 8 (Pavilion 2)
A57: 56 | B57: Day 2 | C57: 0.53472222 | E57: Loyalty | F57: Panel | G57: Panel: Strategy in a Changing Commercial Landscape – What will define the airline loyalty industry as we move into 2027? | H57: Nejib Ben-Khedher – Divisional Senior Vice President, Skywards, EMIRATES GROUP Ralph Piket – Chief Loyalty Officer, Abra Group Pedro Ribeiro – Loyalty Director, Tap Air Portugal | I57: Nejib Ben-Khedher, Ralph Piket, Pedro Ribeiro | J57: EMIRATES GROUP, Abra Group, Tap Air Portugal | K57: 3 | L57: 4 | M57: Track 3 (Pavilion 1) | N57: Pavilion 1 | O57: Track 3 (Pavillion 1) | P57: Process optimisation: How can we make smoother processes, where can I go with new business models, what could be used better • Moving loyalty closer to the commercial and digital core: aligning with revenue management, sales, and marketing • How can programs cut through AI buzzwords to examine real use cases and the ROI metrics that actually matter? • What will define loyalty leadership in the next decade?
A58: 57 | B58: Day 2 | C58: 0.53472222 | E58: Airport - Traveller | F58: Panel | G58: Panel: The airport terminal is changing – how are airports rethinking non-aero revenue with the wider passenger experience in mind? | H58: Arturs Saveljevs – Board member and CCO, Riga International Airport Jorn Korbi – VP Digital Commercialization, Avinor Gintare Norvilaite-Tautevice – Chief Commercial Officer, Lithuanian Airports | I58: Arturs Saveljevs, Jorn Korbi, Gintare Norvilaite-Tautevice | J58: Riga International Airport, Avinor, Lithuanian Airports | K58: 3 | L58: 3 | M58: Track 7 (Pavilion 2) | N58: Pavilion 2 | O58: Track 7 (Pavilion 2) | P58: As airports digitise more of the journey, how are they rethinking retail, services and the overall passenger experience? • How do airports balance dwell time, flow and frictionless processing with the need to protect non-aero revenue? • Lounges and premium services are growing- how are airports working with partners to expand these offerings? • What new partnership models are emerging between airports, brands and commercial operators? • Where is the gap between measured performance (OTP, flow) and perceived experience? • How should we evolve when passenger expectations, capacity constraints and digital journeys are shifting? • Where are airports seeing the most promising opportunities for future non-aero growth?
A59: 58 | B59: Day 2 | C59: 0.53472222 | E59: Payments | F59: Presentation | G59: Presentation: Payments that drive the CFO agenda | H59: Kevin Murphy – Group CEO, CellPoint | I59: Kevin Murphy | J59: CellPoint | K59: 1 | M59: Track 6 (Pavilion 1) | N59: Pavilion 1 | O59: Track 6 (Pavillion 1)
A60: 59 | B60: Day 2 | C60: 0.53472222 | E60: Airport & Airline Collaboration | F60: Presentation | G60: Presentation: A Shared Flight Path: Creating Value Through Airline–Airport Collaboration | H60: Jitender Mohan – EVP & Business Unit Head, Travel & Hospitality, WNS Global Services (UK) Limited Matthew Robinson – Vice President, Airports, Capgemini | I60: Jitender Mohan, Matthew Robinson | J60: WNS Global Services (UK) Limited, Capgemini | K60: 2 | M60: Keynote Stage 2 (Pavilion 2) | N60: Pavilion 2 | O60: Keynote Stage 2 (Pavilion 2) | P60: Airlines and airports share a common goal of delivering seamless passenger journeys and operational excellence, yet often operate with different priorities and systems. • As capacity constraints, operational complexity and passenger expectations intensify, greater collaboration presents an opportunity to unlock shared value. • This session explores how airlines and airports can move beyond individual optimisation towards connected operations, shared insights and strategic partnerships that enhance passenger experience, improve efficiency and drive sustainable growth. • Key Takeaways • Shared Value: Moving beyond individual optimisation to unlock mutual benefits for airlines, airports and passengers. • Passenger Experience & Operational Excellence: Enabling seamless journeys, improved efficiency and better capacity utilisation through closer collaboration. • Data-Driven Collaboration: Leveraging shared insights, connected technologies and strategic partnerships to drive smarter decisions and sustainable growth.
A61: 60 | B61: Day 2 | C61: 0.53472222 | E61: Startup Theatre | F61: Startup Pitch | G61: ONE Order, Many Products: Holidays and Ancillaries in a Single Airline Order | H61: Pete Pohlschmidt – CCO, Altovo | I61: Pete Pohlschmidt | J61: Altovo | K61: 1 | M61: Startup Theatre | O61: Startup Theatre
A62: 61 | B62: Day 2 | C62: 0.53472222 | E62: IROPS | F62: Presentation | G62: Presentation: DPAX: The next generation of passenger disruption management | H62: Matias Escobar – EVP, Strategy and Innovation, Accommodations Plus International (API) | I62: Matias Escobar | J62: Accommodations Plus International (API) | K62: 1 | M62: Track 4 (Pavilion 1) | N62: Pavilion 1 | O62: Track 4 (Pavilion 1)
A63: 62 | B63: Day 2 | C63: 0.54166667 | E63: Sustainability | F63: Fireside Chat | G63: Fireside Chat: Route to Net Zero: Ambition, Regulation and Reality | H63: Owain Jones – Chief Corporate Officer, Wizz Air Hungary Ltd Patrick Edmond – Chief Commercial Officer, Future Energy Global | I63: Owain Jones, Patrick Edmond | J63: Wizz Air Hungary Ltd, Future Energy Global | K63: 2 | M63: Track 10 (Pavilion 2) | N63: Pavilion 2 | O63: Track 10 (Pavilion 2)
A64: 63 | B64: Day 2 | C64: 0.54166667 | E64: Startup Theatre | F64: Startup Pitch | G64: Cleared for Take-Off: Building Cyber Resilience Across the Aviation Ecosystem | H64: Daniel Forrester – CEO, Cybernet Secure | I64: Daniel Forrester | J64: Cybernet Secure | K64: 1 | M64: Startup Theatre | O64: Startup Theatre
A65: 64 | B65: Day 2 | C65: 0.54513889 | E65: AI / ML | F65: Presentation | G65: Presentation: Founded in data, powered by AI: Real-time answers for airline operations | H65: Eugenia Martinez – Solutions Engineer, ThoughtSpot | I65: Eugenia Martinez | J65: ThoughtSpot | K65: 1 | M65: Track 9 (Pavilion 2) | N65: Pavilion 2 | O65: Track 9, Pavilion 2
A66: 65 | B66: Day 2 | C66: 0.54513889 | E66: IROPS | F66: Panel | G66: Panel: How can we enable customers to feel in-control during unavoidable disruption? | H66: Sheryl Lee – Senior Manager- IRROPS Programs & Strategy, United Airlines Emre Devrim – Product & Customer Experience Manager, Ajet Katy Cardwell – Director of Digital Customer Experience, British Airways | I66: Sheryl Lee, Emre Devrim, Katy Cardwell | J66: United Airlines, Ajet, British Airways | K66: 3 | L66: 2 | M66: Track 4 (Pavilion 1) | N66: Pavilion 1 | O66: Track 4 (Pavilion 1) | P66: How is technology helping airlines to improve the impact and experience of disruption on cutomers? • Empowering customers with facts, options and choice: is this vision achievable? • The power of self-service: how have airlines empowered customers to determine their own experience
A67: 66 | B67: Day 2 | C67: 0.54513889 | E67: Airline Keynote | F67: Interview | G67: CEO Interview: Marcus Schnabel, CEO, SunExpress | H67: Marcus Schnabel – CEO, SunExpress Airlines Peter Campbell – Global Transport Correspondent, Financial Times | I67: Marcus Schnabel, Peter Campbell | J67: SunExpress Airlines, Financial Times | K67: 2 | M67: Keynote Stage 1 (Pavilion 1) | N67: Pavilion 1 | O67: Keynote Stage 1 (Pavilion 1)
A68: 67 | B68: Day 2 | C68: 0.54513889 | E68: Airport & Airline Collaboration | F68: Panel | G68: Panel: Digital identity in aviation – who builds the trust layer for seamless travel? | H68: Maurice Jenkins – Chief Innovation Officer, Miami International Airport Amin Lalani – Product Leader of Airport & Sky Club Digital Products & Experiences, Delta Air Lines Lisette Looren de Jong – Programme Manager Innovation Border Management, Ministry of Justice and Security | I68: Maurice Jenkins, Amin Lalani, Lisette Looren de Jong | J68: Miami International Airport, Delta Air Lines, Ministry of Justice and Security | K68: 3 | L68: 2 | M68: Keynote Stage 2 (Pavilion 2) | N68: Pavilion 2 | O68: Keynote Stage 2 (Pavilion 2) | P68: What has changed recently that could finally enable broader biometric travel deployment? • Global interoperability: what role should standards like IATA One ID, ICAO Digital Travel Credentials and digital identity wallets play? • What data exchange and connectivity infrastructure is needed to link airlines, airports and border agencies? • Who ultimately owns and operates digital identity infrastructure across the ecosystem - airlines, airports, governments or global bodies? • Looking ahead to 2030, will passengers realistically be able to travel end-to-end without presenting a traditional passport?
A69: 68 | B69: Day 2 | C69: 0.54513889 | E69: Payments | F69: Presentation | G69: Presentation: Beyond Legacy: The Uncomfortable Truth About Airline Payments | H69: Victor Gaarenstroom – Global Travel & Mobility Lead, adyen Greg Toussaint – Director, Edgar, Dunn & Company | I69: Victor Gaarenstroom, Greg Toussaint | J69: adyen, Edgar, Dunn & Company | K69: 2 | M69: Track 6 (Pavilion 1) | N69: Pavilion 1 | O69: Track 6 (Pavillion 1) | P69: Fresh off the press: Adyen and Edgar, Dunn & Company explore evolving traveler expectations and how airlines can break free from legacy payments that hold back innovation, speed and performance, and unlock the next frontier in airline payments.
A70: 69 | B70: Day 2 | C70: 0.54513889 | E70: Retail | F70: Talk | G70: Next-gen ancillaries: algorithmic pricing, automation and regulatory shifts | H70: Julio Rodriguez – Chief Commercial Strategy Officer, IAG Tiddo Veldhuis – VP Offer Management & Ancillaries, Air France KLM Juan Pablo Lafosse – CEO, TravelX | I70: Julio Rodriguez, Tiddo Veldhuis, Juan Pablo Lafosse | J70: IAG, Air France KLM, TravelX | K70: 3 | L70: 2 | M70: Track 5 (Pavilion 1) | N70: Pavilion 1 | O70: Track 5 (Pavilion 1) | P70: How will new baggage regulations impact airlines’ revenue models and pricing strategies? • Could predictive analytics help to drive the purchase of premium services? • Can AI help to make prices clearer while still allowing airlines to offer unbundled ancillaries? • How can airlines integrate high-margin lifestyle ancillaries, such as hotels or experiences, directly into the booking flow? • How can real-time data orchestration automate instant payouts for flight delays to turn disruption into a service win?
A71: 70 | B71: Day 2 | C71: 0.54513889 | E71: Digital & IT | F71: Talk | G71: The human experience, both sides: where AI makes CX and where it breaks it | H71: Sindhu Shekharan – VP Customer Success, Sutherland Global Services Inc. | I71: Sindhu Shekharan | J71: Sutherland Global Services Inc. | K71: 1 | M71: Track 1 (Pavilion 1) | N71: Pavilion 1 | O71: Track 1(Pavilion 1) | P71: The customer journey. The talk walks through specific moments and shows the result at each one.Abstract: AI's effect on customer experience is not uniform. It depends on the moment. Across industries, the same technology that delights customers at booking frustrates them during disruption. we will maps where AI makes and breaks the human experience across key service moments, using evidence from multiple industries, and translates the findings into the airline journey: booking, disruption, refunds and rebooking.
A72: 71 | B72: Day 2 | C72: 0.54513889 | E72: Customer Experience | F72: Presentation | G72: Presentation: Autopilot was never unsupervised | H72: Alexander Laurie – GTM CTO, PING IDENTITY | I72: Alexander Laurie | J72: PING IDENTITY | K72: 1 | M72: Track 2 (Pavilion 1) | N72: Pavilion 1 | O72: Track 2 (Pavilion 1) | P72: What happens when AI Agents book the tickets, spend the miles and speak to your customers
A73: 72 | B73: Day 2 | C73: 0.54513889 | E73: Airport - Operations | F73: Panel | G73: Panel: Airports are full of data – how do we turn this into better real-time decision making? | H73: Gyorgy Farkas – Head of IT Project and Innovation Management, Budapest Airport Samuel í Hjøllum Rude – Vice President, Head of Operational Airport Services, Copenhagen Airports Nishant Rao – Director, Aviation Business Development, Nieuport Aviation | I73: Gyorgy Farkas, Samuel í Hjøllum Rude, Nishant Rao | J73: Budapest Airport, Copenhagen Airports, Nieuport Aviation | K73: 3 | L73: 4 | M73: Track 8 (Pavilion 2) | N73: Pavilion 2 | O73: Track 8 (Pavilion 2) | P73: Airports are collecting more operational data than ever, but where are operations team still struggling to turn it into action? • Passenger flow, turnaround visibility and resource allocation are increasingly connected. How do airports bring these datasets together in a useful way? • How do airports balance airline demand for slots with operational and capacity constraints? How does good data help here? • AI is moving quickly, but weak data foundations still hold many projects back. What has to be fixed first? • Looking ahead, what will define an intelligent airport operating model over the next five years?
A74: 73 | B74: Day 2 | C74: 0.54861111 | E74: Startup Theatre | F74: Startup Pitch | G74: Passtination: Powering Loyalty Beyond the Flight | H74: Safir Jamal – Founder & CEO, Passtination | I74: Safir Jamal | J74: Passtination | K74: 1 | M74: Startup Theatre | O74: Startup Theatre
A75: 74 | B75: Day 2 | C75: 0.55208333 | E75: Sustainability | F75: Panel | G75: Panel: Scaling sustainable aviation fuel – who carries the risk, cost and responsibility? | H75: Ulrike Ziegler – President of the Board of Directors, Impact on Sustainable Aviation Maria Whittaker – Chief Corporate Responsibility Officer, Abra Group Jan Petter Steinland – Director Strategic Analysis & Transformation, Civil Aviation Authority Norway | I75: Ulrike Ziegler, Maria Whittaker, Jan Petter Steinland | J75: Impact on Sustainable Aviation, Abra Group, Civil Aviation Authority Norway | K75: 3 | L75: 3 | M75: Track 10 (Pavilion 2) | N75: Pavilion 2 | O75: Track 10 (Pavilion 2) | P75: One year into policies like RefuelEU, what has changed and are airlines now facing uneven regional pressures? • Is SAF still supply-constrained, or are investment risk, production economics and market demand now the biggest barriers to scale? • Where is collaboration between airlines, fuel producers, airports and governments working, and where is it breaking down? • As carbon pricing expands and compliance costs rise, how does this change the business case for SAF compared with other decarbonization pathways? • As geopolitical uncertainty continues, how resilient is the long-term business case for SAF? • What would a functioning SAF market look like by 2030?
A76: 75 | B76: Day 2 | C76: 0.55208333 | E76: Airline Keynote | F76: Panel | G76: CEO Panel: Strategy, competition and innovation in a disruptive environment | H76: Marcus Schnabel – CEO, SunExpress Airlines Theo Panagiotoulias – Chief Executive Officer, Star Alliance Sunil John – CEO, PROS | I76: Marcus Schnabel, Theo Panagiotoulias, Sunil John | J76: SunExpress Airlines, Star Alliance, PROS | K76: 3 | L76: 1 | M76: Keynote Stage 1 (Pavilion 1) | N76: Pavilion 1 | O76: Keynote Stage 1 (Pavilion 1) | P76: Investing in AI transformation to support long term goals • Creating smart business models to compete effectively in a complex global market • Identifying new opportunities for collaboration & growth • Creating next-gen products to meet the expectations of next-gen customers
A77: 76 | B77: Day 2 | C77: 0.55555556 | E77: AI / ML | F77: Panel | G77: Panel: Creating safe & effective foundations for AI transformation within the airline | H77: Ben Dias – Chief AI Scientist, IAG Dirk Jungnickel – SVP Enterprise Data & Analytics, Emirates Airline Kevin Lynn – Director – Crew Scheduling Technology, United Airlines | I77: Ben Dias, Dirk Jungnickel, Kevin Lynn | J77: IAG, Emirates Airline, United Airlines | K77: 3 | L77: 4 | M77: Track 9 (Pavilion 2) | N77: Pavilion 2 | O77: Track 9 (Pavilion 2) | P77: What are the priorities for leaders who are focused on creating a safe & reliable AI frameworks? • Building safety into the core of AI usage in Aviation: balancing innovation with risk integrity • How can Airlines best measure the quality and sophistication of their AI maturity? • Building today with tomorrow’s technology innovation in mind: how can leaders build IT platforms in a fast paced tech space
A78: 77 | B78: Day 2 | C78: 0.55555556 | E78: Payments | F78: Panel | G78: Panel: Payments, retailing & offer-order: what changes when retail changes? | H78: Yago Casasnovas – Head of Payments, Fraud Prevention and Distribution, Air Europa Shaun Donaghey – Chief Commercial Officer, CellPoint Dennis Lore – Payments Reconciliations and Credit Risk Accountant Manager, Kenya Airways | I78: Yago Casasnovas, Shaun Donaghey, Dennis Lore | J78: Air Europa, CellPoint, Kenya Airways | K78: 3 | L78: 2 | M78: Track 6 (Pavilion 1) | N78: Pavilion 1 | O78: Track 6 (Pavillion 1) | P78: In an offer-order world, how must payment authorisation, settlement and refunds evolve to avoid operational complexity? • As orders replace tickets, what new payment and servicing processes are required across the airline ecosystem? • How can airlines reduce cost of sale across NDC, aggregators and OTAs without damaging conversion or partner reach? • How are fintech and travel platforms reshaping ancillary revenue and the checkout experience? • What is the future of agency payment - VCCs, A2A and new settlement models? • How are airlines reorganising internally to align commercial, distribution and payments teams around retailing transformation?
A79: 78 | B79: Day 2 | C79: 0.55555556 | E79: Digital & IT | F79: Panel | G79: Panel: How do we drive revenue, resilience and measure return on tech investment? | H79: Mel Crocker – CIO, Air Canada Dan Bartel – Chief Procurement Officer, American Airlines Massimo Morin – Global Head, Travel, AWS for Travel and Hospitality, Amazon Web Services, Inc. (SEA54) | I79: Mel Crocker, Dan Bartel, Massimo Morin | J79: Air Canada, American Airlines, Amazon Web Services, Inc. (SEA54) | K79: 3 | L79: 3 | M79: Track 1 (Pavilion 1) | N79: Pavilion 1 | O79: Track 1(Pavilion 1) | P79: Where should airlines place their biggest technology bets for 2026–2028 – core systems modernisation, AI, cloud or infrastructure resilience? • How do airlines modernise legacy systems while continuing to operate at scale without creating parallel complexity? • When budgets tighten, how do we distinguish between essential investment and “nice to have” innovation? • Which technology investments are genuinely delivering measurable value across the airline – from automation to AI and core platform upgrades?
A80: 79 | B80: Day 2 | C80: 0.55555556 | E80: Customer Experience | F80: Panel | G80: Panel: Supporting the full customer journey with effective customer care: From the importance of human touch to the power of digital | H80: Marco Barbosa – Directior of Guest Care and Delivery, Etihad Jason Ward – Chief Customer Officer, Azul Airlines Renato Ramos – Vice President Corporate Strategy, Star Alliance | I80: Marco Barbosa, Jason Ward, Renato Ramos | J80: Etihad, Azul Airlines, Star Alliance | K80: 3 | L80: 3 | M80: Track 2 (Pavilion 1) | N80: Pavilion 1 | O80: Track 2 (Pavilion 1) | P80: How can airlines navigate smart multi-channel customer communications to optimise cost and increase customer support • Supporting insights with relevant data streams for colleagues and tech support to support customers effectively and efficiently • Shaping the long-term communications strategy: what will the future look like with AI and agentic AI in the mix?
A81: 80 | B81: Day 2 | C81: 0.5625 | E81: Startup Theatre | F81: Startup Pitch | G81: FlyBuddy: Guiding Passengers, Empowering Airports | H81: Eoin Mcnamara – Co-Founder & Chief Operating Officer, FlyBuddy Michael Murphy – Co-Founder & Chief Executive Officer, FlyBuddy | I81: Eoin Mcnamara, Michael Murphy | J81: FlyBuddy | K81: 2 | M81: Startup Theatre | O81: Startup Theatre
A82: 81 | B82: Day 2 | C82: 0.56944444 | E82: Startup Theatre | F82: Startup Pitch | G82: From Information Desk to Personal AI Concierge: Turning Every Passenger Interaction into Experience and Revenue | H82: Samuel Chekroun – CEO, Hubway | I82: Samuel Chekroun | J82: Hubway | K82: 1 | M82: Startup Theatre | O82: Startup Theatre
A83: 82 | B83: Day 2 | C83: 0.57569444 | D83: 0.60763889 | E83: Workshop | F83: Workshop | G83: IBS Workshop Transformation into an agentic AI lead loyalty and aviation organisation **REGISTRATION REQUIRED - Airline & Airport access only anyone else will be turned away** | H83: Christopher Branagan | I83: Christopher Branagan | K83: 1 | M83: Track 3 (Pavilion 1) | N83: Pavilion 1 | O83: Track3, Pavilion 1 | Q83: 2 | R83: 120 | S83: =R83-Q83 -> 118 | T83: Open
A84: 83 | B84: Day 2 | C84: 0.57638889 | E84: Startup Theatre | F84: Startup Pitch | G84: Connecting Airlines is only the beginning (From fragmented airline distribution to intelligent corporate travel management) | H84: Abdurrahman Ural – CCO, AIRVIATECH | I84: Abdurrahman Ural | J84: AIRVIATECH | K84: 1 | M84: Startup Theatre | O84: Startup Theatre
A85: 84 | B85: Day 2 | C85: 0.57638889 | D85: 0.60763889 | E85: Workshop | F85: Workshop | G85: Adobe Workshop: Beyond the co-pilot: The next era of customer experience **REGISRATION REQUIRED** | H85: Gemma Carver Bettina Pickl | I85: Gemma Carver, Bettina Pickl | K85: 2 | M85: Track 2 (Pavilion 2) | N85: Pavilion 2 | O85: Track 2, Pavilion 2 | Q85: 5 | R85: 120 | S85: =R85-Q85 -> 115 | T85: Open
A86: 85 | B86: Day 2 | C86: 0.57708333 | D86: 0.60763889 | E86: Workshop | F86: Workshop | G86: Operational resilience isn't built in the Ops center. It's built in the roster. **Registration required** | H86: Lauren Mann Kevin Ma Gregory Stephans | I86: Lauren Mann, Kevin Ma, Gregory Stephans | K86: 3 | M86: Track 5 (Pavilion 1) | N86: Pavilion 1 | O86: Track 5 (Pavilion 1) | Q86: 80 | R86: 120 | S86: =R86-Q86 -> 40 | T86: Open
A87: 86 | B87: Day 2 | C87: 0.58333333 | E87: Startup Theatre | F87: Startup Pitch | G87: OpenAir — Agentic Revolution for Airlines Customer Services | H87: Jaime Fernandez – CEO, Openair | I87: Jaime Fernandez | J87: Openair | K87: 1 | M87: Startup Theatre | O87: Startup Theatre
A88: 87 | B88: Day 2 | C88: 0.58333333 | E88: Airline Keynote | F88: Panel | G88: Star Alliance CEOs Panel: From fragmented to frictionless: Rethinking alliance travel | H88: Theo Panagiotoulias – Chief Executive Officer, Star Alliance Luís Rodrigues – Chief Executive Officer, Tap Air Portugal Joerg Eberhart – Chief Executive Officer, ITA-Airways | I88: Theo Panagiotoulias, Luís Rodrigues, Joerg Eberhart | J88: Star Alliance, Tap Air Portugal, ITA-Airways | K88: 3 | L88: 1 | M88: Keynote Stage 1 (Pavilion 1) | N88: Pavilion 1 | O88: Keynote Stage 1 (Pavilion 1)
A89: 88 | B89: Day 2 | C89: 0.59027778 | E89: Startup Theatre | F89: Startup Pitch | G89: Your AI assistants are now booking your flights | H89: Dimitri Ewald – Head of Growth Europe, ALPIC | I89: Dimitri Ewald | J89: ALPIC | K89: 1 | M89: Startup Theatre | O89: Startup Theatre
A90: 89 | B90: Day 2 | C90: 0.59722222 | E90: Startup Theatre | F90: Startup Pitch | G90: Half of what we load is thrown away. Is a 25% waste rate achievable today? | H90: Manuel Hübschmann – Chief Solution Advisor, Viktio | I90: Manuel Hübschmann | J90: Viktio | K90: 1 | M90: Startup Theatre | O90: Startup Theatre
A91: 90 | B91: Day 2 | C91: 0.60763889 | E91: Networking | F91: Networking | G91: Aviation Connect: Session 4 | H91: Host, World Aviation Festival | I91: Host | J91: World Aviation Festival | K91: 1 | M91: Aviation Connect Zone (Pavilion 2) | N91: Pavilion 2 | O91: Aviation Connect Zone, Pavilion 2 | P91: Aviation Connect is our dedicated networking hour. Book 15 minute meetings via the Aviation Connect Platform and make the most of your time at WAF. No other sessions, workshops or activities are taking place during this time.
A92: 91 | B92: Day 2 | C92: 0.64930556 | E92: Airline Keynote | F92: Fireside Chat | G92: Commercial leaders fireside chat: Paul Verhagen, CCO, SAS | H92: Paul Verhagen – Executive Vice President and Chief Commercial Officer, SAS Henry Harteveldt – Travel Industry Analyst, Atmosphere Research Group | I92: Paul Verhagen, Henry Harteveldt | J92: SAS, Atmosphere Research Group | K92: 2 | M92: Keynote Stage 1 (Pavilion 1) | N92: Pavilion 1 | O92: Keynote Stage, Pavilion 1
A93: 92 | B93: Day 2 | C93: 0.65277778 | E93: Digital & IT | F93: Fireside Chat | G93: Fireside Chat: Building an AI-led airline – from ambition to execution | H93: Ahmed Naeemi – Chief Information Officer, Gulf Air Group Guido Woska – Chief Client Officer & Executive Partner, Manyone | I93: Ahmed Naeemi, Guido Woska | J93: Gulf Air Group, Manyone | K93: 2 | M93: Track 1 (Pavilion 1) | N93: Pavilion 1 | O93: Track 1(Pavilion 1)
A94: 93 | B94: Day 2 | C94: 0.65277778 | E94: Customer Experience | F94: Fireside Chat | G94: Fireside chat: Putting the customer first with data driven decision making at Iberia | H94: Beatriz Guillen – Chief Customer Officer, Iberia Jerry Angrave – Customer Experience Director, Empathyce | I94: Beatriz Guillen, Jerry Angrave | J94: Iberia, Empathyce | K94: 2 | M94: Track 2 (Pavilion 1) | N94: Pavilion 1 | O94: Track 2 (Pavilion 1)
A95: 94 | B95: Day 2 | C95: 0.65277778 | E95: AI / ML | F95: Presentation | G95: Presentation: Driving efficiency in innovation with AI: finding real value and impact at TUI | H95: Manjinder Singh – Head of Airline Data Science & Analytics, TUI GROUP | I95: Manjinder Singh | J95: TUI GROUP | K95: 1 | M95: Track 9 (Pavilion 2) | N95: Pavilion 2 | O95: Track 9 (Pavilion 2)
A96: 95 | B96: Day 2 | C96: 0.65277778 | E96: Retail | F96: Fireside Chat | G96: Fireside Chat: Bringing the benefits of NDC to corporates: Delivering seamless booking and travel management capabilities for high value travellers | H96: Paloma Sanz de Andino Jimenéz – NDC Onboarding and Operation Manager, Iberia Dennis Cary – Managing Director, Cary Strategic Advisory Rita Ribeiro – Head of General Services, EDP | I96: Paloma Sanz de Andino Jimenéz, Dennis Cary, Rita Ribeiro | J96: Iberia, Cary Strategic Advisory, EDP | K96: 3 | M96: Track 5 (Pavilion 1) | N96: Pavilion 1 | O96: Track 5 (Pavilion 1)
A97: 96 | B97: Day 2 | C97: 0.65277778 | E97: Airport - Traveller | F97: Fireside Chat | G97: Fireside Chat with Cassie Schmid, Chief Strategy Officer, Philadelphia International Airport | H97: Cassie Schmid – Chief Strategy Officer, Philadelphia International Airport Peta Wolmarans – Vice President, Ricondo | I97: Cassie Schmid, Peta Wolmarans | J97: Philadelphia International Airport, Ricondo | K97: 2 | M97: Track 7 (Pavilion 2) | N97: Pavilion 2 | O97: Track 7 (Pavilion 2)
A98: 97 | B98: Day 2 | C98: 0.65277778 | E98: Sustainability | F98: Fireside Chat | G98: Fireside Chat: Jan Petter Steinland, Director Strategic Analysis and Transformation, CAA Norway | H98: Jan Petter Steinland – Director Strategic Analysis & Transformation, Civil Aviation Authority Norway Patrick Edmond – Chief Commercial Officer, Future Energy Global | I98: Jan Petter Steinland, Patrick Edmond | J98: Civil Aviation Authority Norway, Future Energy Global | K98: 2 | M98: Track 10 (Pavilion 2) | N98: Pavilion 2 | O98: Track 10 (Pavilion 2)
A99: 98 | B99: Day 2 | C99: 0.65277778 | E99: Ancillaries | F99: Presentation | G99: Presentation: Airline retailing progress - what do airline employees really think? | H99: Ann Cederhall – Owner, LeapShift | I99: Ann Cederhall | J99: LeapShift | K99: 1 | M99: Track 4 (Pavilion 1) | N99: Pavilion 1 | O99: Track 4, Pav 1
A100: 99 | B100: Day 2 | C100: 0.65277778 | E100: Startup Theatre | F100: Startup Pitch | G100: From Frequent Flyer to Founder: The Story Behind Stand-By Transforming the Boarding Experience | H100: Cesar Hueso – Founder, Stand-By CHO Systems | I100: Cesar Hueso | J100: Stand-By CHO Systems | K100: 1 | M100: Startup Theatre | O100: Startup Theatre
A101: 100 | B101: Day 2 | C101: 0.65277778 | E101: Airport & Airline Collaboration | F101: Fireside Chat | G101: Fireside Chat: Airline & airport partnerships – aligning operations, experience and commercial outcomes | H101: Girish Nair – Chief Operating Officer, Bangalore International Airport Simon Wilcox – Founder and CEO, Wordsworth Consulting Ltd | I101: Girish Nair, Simon Wilcox | J101: Bangalore International Airport, Wordsworth Consulting Ltd | K101: 2 | M101: Keynote Stage 2 (Pavilion 2) | N101: Pavilion 2 | O101: Keynote Stage 2 (Pavilion 2)
A102: 101 | B102: Day 2 | C102: 0.65277778 | E102: Payments | F102: Fireside Chat | G102: Fireside Chat: The customer side of airline payments – trust, loyalty and engagement | H102: Joao Frias – Head of Payments Strategy & Global Fraud, Tap Air Portugal Louis Wapler – Manager, Edgar, Dunn & Company | I102: Joao Frias, Louis Wapler | J102: Tap Air Portugal, Edgar, Dunn & Company | K102: 2 | M102: Track 6 (Pavilion 1) | N102: Pavilion 1 | O102: Track 6 (Pavillion 1)
A103: 102 | B103: Day 2 | C103: 0.65277778 | E103: Loyalty | F103: Fireside Chat | G103: Fireside Chat: Chasing the golden goose: Optimising revenue whilst protecting loyalty value in a pressurised environment. | H103: DANIEL BRETT – Manager, Revenue Management - Loyalty Programs & Flight Pass, Air Canada Harald Deprosse – Partner, Envolved GmbH | I103: DANIEL BRETT, Harald Deprosse | J103: Air Canada, Envolved GmbH | K103: 2 | M103: Track 3 (Pavilion 1) | N103: Pavilion 1 | O103: Track 3, Pavilion 1
A104: 103 | B104: Day 2 | C104: 0.65972222 | E104: Sustainability | F104: Presentation | G104: Presentation: Sustainability strategy - delivering carbon neutrality in a competitive low-cost model | H104: Takuya MATSUO – Executive officer/CMO, Strategy Lead, ZIPAIR Tokyo | I104: Takuya MATSUO | J104: ZIPAIR Tokyo | K104: 1 | M104: Track 10 (Pavilion 2) | N104: Pavilion 2 | O104: Track 10 (Pavilion 2)
A105: 104 | B105: Day 2 | C105: 0.65972222 | E105: Airline Keynote | F105: Presentation | G105: Presentation: An introduction to beyond: Turkish Technology modern airline retailing platform | H105: Serdar Gurbuz – CEO, Turkish Technology | I105: Serdar Gurbuz | J105: Turkish Technology | K105: 1 | M105: Keynote Stage 1 (Pavilion 1) | N105: Pavilion 1 | O105: Keynote Stage 1 (Pavilion 1)
A106: 105 | B106: Day 2 | C106: 0.65972222 | E106: Startup Theatre | F106: Startup Pitch | G106: Why 89% of Travel Checkouts Fail – and How Identity Fixes It | H106: Kameron Bertine – CEO and Cofounder, Movmo | I106: Kameron Bertine | J106: Movmo | K106: 1 | M106: Startup Theatre | O106: Startup Theatre
A107: 106 | B107: Day 2 | C107: 0.66319444 | E107: Digital & IT | F107: Fireside Chat | G107: Fireside Chat: Inside the OCC: what really works with data and Ai | H107: Paulo Aguiar – VP of Airline Solutions & Strategy, Amach Choorah Singh Ark – Managing Director, Ark Advisory | I107: Paulo Aguiar, Choorah Singh Ark | J107: Amach, Ark Advisory | K107: 2 | M107: Track 1 (Pavilion 1) | N107: Pavilion 1 | O107: Track 1(Pavilion 1) | P107: Choorah Singh, who has led operations at Air India and Ryanair, joins Paulo Aguiar from Amach for an honest conversation from inside the Operations Control Centre: what really works with data and AI when the day goes wrong, what doesn’t, and what every airline should fix before buying its next AI tool.
...

Sheet Speaker Appearances
A1: Name | B1: Job Title | C1: Organisation | D1: Role | E1: Day | F1: Start | G1: Stream / Category | H1: Format | I1: Session Title | J1: Room / Stage
A2: Host | C2: World Aviation Festival | D2: Speaker | E2: Day 2 | F2: 0.34375 | G2: Networking | H2: Networking | I2: Aviation Connect: Session 6 | J2: Aviation Connect Zone (Pavilion 2)
A3: Carlos Oliveira | B3: Chairman | C3: Tap Air Portugal | D3: Speaker | E3: Day 2 | F3: 0.38194444 | G3: Airline Keynote | H3: Welcome | I3: Official Welcome | J3: Keynote Stage 1 (Pavilion 1)
A4: Thierry Ligonnière | B4: Chief Executive Officer | C4: ANA Aeroportos de Portugal | D4: Speaker | E4: Day 2 | F4: 0.38541667 | G4: Airport Keynote | H4: Welcome | I4: Official Airport Partner Welcome | J4: Keynote Stage 2 (Pavilion 2)
A5: Stefan Schulte | B5: Chief Executive Officer | C5: Fraport AG | D5: Speaker | E5: Day 2 | F5: 0.38888889 | G5: Airport Keynote | H5: Interview | I5: CEO Interview: Stefan Schulte, CEO, Fraport AG | J5: Keynote Stage 2 (Pavilion 2)
A6: Ben Thompson | B6: Presenter | C6: BBC | D6: Speaker | E6: Day 2 | F6: 0.38888889 | G6: Airport Keynote | H6: Interview | I6: CEO Interview: Stefan Schulte, CEO, Fraport AG | J6: Keynote Stage 2 (Pavilion 2)
A7: Luís Rodrigues | B7: Chief Executive Officer | C7: Tap Air Portugal | D7: Speaker | E7: Day 2 | F7: 0.38888889 | G7: Airline Keynote | H7: Interview | I7: CEO Interview: Luis Rodrigues, CEO, TAP Air Portugal | J7: Keynote Stage 1 (Pavilion 1)
A8: Peter Campbell | B8: Global Transport Correspondent | C8: Financial Times | D8: Speaker | E8: Day 2 | F8: 0.38888889 | G8: Airline Keynote | H8: Interview | I8: CEO Interview: Luis Rodrigues, CEO, TAP Air Portugal | J8: Keynote Stage 1 (Pavilion 1)
A9: Adrian Neuhauser | B9: Chief Executive Officer | C9: Abra Group | D9: Speaker | E9: Day 2 | F9: 0.39583333 | G9: Airline Keynote | H9: Interview | I9: CEO Interview: Adrian Neuhauser, CEO, ABRA Group | J9: Keynote Stage 1 (Pavilion 1)
A10: Peter Campbell | B10: Global Transport Correspondent | C10: Financial Times | D10: Speaker | E10: Day 2 | F10: 0.39583333 | G10: Airline Keynote | H10: Interview | I10: CEO Interview: Adrian Neuhauser, CEO, ABRA Group | J10: Keynote Stage 1 (Pavilion 1)
A11: Thierry Ligonnière | B11: Chief Executive Officer | C11: ANA Aeroportos de Portugal | D11: Speaker | E11: Day 2 | F11: 0.39583333 | G11: Airport Keynote | H11: Interview | I11: CEO Interview: Thierry Ligonnière, CEO, ANA - Aeroportos de Portugal | J11: Keynote Stage 2 (Pavilion 2)
A12: Ben Thompson | B12: Presenter | C12: BBC | D12: Speaker | E12: Day 2 | F12: 0.39583333 | G12: Airport Keynote | H12: Interview | I12: CEO Interview: Thierry Ligonnière, CEO, ANA - Aeroportos de Portugal | J12: Keynote Stage 2 (Pavilion 2)
A13: Pierre-Hugues Schmit | B13: Chief Executive Officer | C13: London Gatwick Airport | D13: Speaker | E13: Day 2 | F13: 0.40277778 | G13: Airport Keynote | H13: Interview | I13: CEO Interview: Pierre-Hugues Schmit, CEO, London Gatwick | J13: Keynote Stage 2 (Pavilion 2)
A14: Ben Thompson | B14: Presenter | C14: BBC | D14: Speaker | E14: Day 2 | F14: 0.40277778 | G14: Airport Keynote | H14: Interview | I14: CEO Interview: Pierre-Hugues Schmit, CEO, London Gatwick | J14: Keynote Stage 2 (Pavilion 2)
... A24: Paul Griffiths | B24: Chief Executive Officer | C24: Dubai Airports Company | D24: Speaker | E24: Day 2 | F24: 0.41666667 | G24: Airport Keynote | H24: Panel | I24: Keynote Panel: Growth without compromise – rethinking the airport model for sustainable growth | J24: Keynote Stage 2 (Pavilion 2)
A25: Rodrigo López | D25: Host | E25: Day 2 | F25: 0.44791667 | G25: Roundtable | H25: Roundtable | I25: Table 01: FLYR Roundtable - Funding the move to Offer & Order: Creating the right time for the right move | J25: Roundtable Area (Pavilion 2)
A26: Josh Crandall | D26: Host | E26: Day 2 | F26: 0.44791667 | G26: Roundtable | H26: Roundtable | I26: Table 01: FLYR Roundtable - Funding the move to Offer & Order: Creating the right time for the right move | J26: Roundtable Area (Pavilion 2)
A27: Doug Sharpe | D27: Host | E27: Day 2 | F27: 0.44791667 | G27: Roundtable | H27: Roundtable | I27: Table 2: ATPCO Roundtable - Airline product catalogs: a foundation for retailing at scale | J27: Roundtable Area (Pavilion 2)
A28: Megan Humphries | D28: Host | E28: Day 2 | F28: 0.44791667 | G28: Roundtable | H28: Roundtable | I28: Table 2: ATPCO Roundtable - Airline product catalogs: a foundation for retailing at scale | J28: Roundtable Area (Pavilion 2)
A29: Ali Tredinnick | D29: Host | E29: Day 2 | F29: 0.44791667 | G29: Roundtable | H29: Roundtable | I29: Table 3: 15Below - 10 years of deploying AI in aviation: what works, what doesn’t and what we’ve learned | J29: Roundtable Area (Pavilion 2)
A30: Joe Bennett | D30: Host | E30: Day 2 | F30: 0.44791667 | G30: Roundtable | H30: Roundtable | I30: Table 3: 15Below - 10 years of deploying AI in aviation: what works, what doesn’t and what we’ve learned | J30: Roundtable Area (Pavilion 2)
A31: Billie Moore | D31: Host | E31: Day 2 | F31: 0.44791667 | G31: Roundtable | H31: Roundtable | I31: Table 4: OneReg Roundtable - Continuous confidence: reimagining how aviation compliance works | J31: Roundtable Area (Pavilion 2)
A32: Angel Matsis | D32: Host | E32: Day 2 | F32: 0.44791667 | G32: Roundtable | H32: Roundtable | I32: Table 4: OneReg Roundtable - Continuous confidence: reimagining how aviation compliance works | J32: Roundtable Area (Pavilion 2)
A33: Kevin Stamler | D33: Host | E33: Day 2 | F33: 0.44791667 | G33: Roundtable | H33: Roundtable | I33: Table 5: Seatboost Roundtable - The gate-side goldmine: Gamification, dynamic pricing, and monetizing the premium cabin | J33: Roundtable Area (Pavilion 2)
A34: Alexander Laurie | D34: Host | E34: Day 2 | F34: 0.44791667 | G34: Roundtable | H34: Roundtable | I34: Table 6: Ping Identity Roundtable - Whose agent is it anyway? | J34: Roundtable Area (Pavilion 2)
A35: Emanuela Maftieu | D35: Host | E35: Day 2 | F35: 0.44791667 | G35: Roundtable | H35: Roundtable | I35: Table 6: Ping Identity Roundtable - Whose agent is it anyway? | J35: Roundtable Area (Pavilion 2)
A36: Mike Murchison | D36: Host | E36: Day 2 | F36: 0.44791667 | G36: Roundtable | H36: Roundtable | I36: Table 7: ADA Roundtable - Agentic IROPs: Turning flight re-accom into your biggest loyalty moment | J36: Roundtable Area (Pavilion 2)
... A62: Gaurav Passi | D62: Host | E62: Day 2 | F62: 0.44791667 | G62: Roundtable | H62: Roundtable | I62: Table20: Zingly Roundtable - Case study: AI in production at Pegasus Airlines: Beyond deflection to completed passenger journeys | J62: Roundtable Area (Pavilion 2)
A63: Host | C63: World Aviation Festival | D63: Speaker | E63: Day 2 | F63: 0.47916667 | G63: Networking | H63: Networking | I63: Aviation Connect: Session 3 | J63: Aviation Connect Zone (Pavilion 2)
A64: Harald Deprosse | B64: Partner | C64: Envolved GmbH | D64: Speaker | E64: Day 2 | F64: 0.51736111 | G64: Loyalty | H64: Chair Remarks | I64: Chair opening remarks | J64: Track 3 (Pavilion 1)
A65: Maria Whittaker | B65: Chief Corporate Responsibility Officer | C65: Abra Group | D65: Speaker | E65: Day 2 | F65: 0.52083333 | G65: Sustainability | H65: Fireside Chat | I65: Fireside Chat: Growth without compromise – can airlines decarbonise while remaining competitive? | J65: Track 10 (Pavilion 2)
A66: Patrick Edmond | B66: Chief Commercial Officer | C66: Future Energy Global | D66: Speaker | E66: Day 2 | F66: 0.52083333 | G66: Sustainability | H66: Fireside Chat | I66: Fireside Chat: Growth without compromise – can airlines decarbonise while remaining competitive? | J66: Track 10 (Pavilion 2)
A67: Richard Wolfman | B67: SVP Global Business Development | C67: Plusgrade | D67: Speaker | E67: Day 2 | F67: 0.52083333 | G67: Loyalty | H67: Welcome | I67: Plusgrade Welcome | J67: Track 3 (Pavilion 1)
A68: Oliver Schmitt | B68: CEO Digital Hangar Ecosystem & SVP Digital Solutions | C68: Lufthansa Group Digital Hangar GmbH | D68: Speaker | E68: Day 2 | F68: 0.52430556 | G68: AI / ML | H68: Presentation | I68: Presentation: Building tomorrow’s airline: AI-orchestrated, human-led | J68: Track 9 (Pavilion 2)
A69: Bethan Lynch | B69: VP Customer Experience & Loyalty | C69: Virgin Atlantic | D69: Speaker | E69: Day 2 | F69: 0.52430556 | G69: Customer Experience | H69: Talk | I69: Human connection, effortless digital experiences: premium CX in the age of AI | J69: Track 2 (Pavilion 1)
A70: Jerry Angrave | B70: Customer Experience Director | C70: Empathyce | D70: Speaker | E70: Day 2 | F70: 0.52430556 | G70: Customer Experience | H70: Talk | I70: Human connection, effortless digital experiences: premium CX in the age of AI | J70: Track 2 (Pavilion 1)
A71: Ralph Piket | B71: Chief Loyalty Officer | C71: Abra Group | D71: Speaker | E71: Day 2 | F71: 0.52430556 | G71: Loyalty | H71: Fireside Chat | I71: Fireside Chat: The future outlook for loyalty at Abra Group | J71: Track 3 (Pavilion 1)
A72: Harald Deprosse | B72: Partner | C72: Envolved GmbH | D72: Speaker | E72: Day 2 | F72: 0.52430556 | G72: Loyalty | H72: Fireside Chat | I72: Fireside Chat: The future outlook for loyalty at Abra Group | J72: Track 3 (Pavilion 1)
A73: Rachel Gaud | B73: Ops Digital Transformation Lead | C73: Etihad | D73: Speaker | E73: Day 2 | F73: 0.52430556 | G73: IROPS | H73: Presentation | I73: Presentation: Project ConnectOps: Delivering highly contextualised and realtime information to optimise insights for crew, airport and operational staff | J73: Track 4 (Pavilion 1)
A74: Mel Crocker | B74: CIO | C74: Air Canada | D74: Speaker | E74: Day 2 | F74: 0.52430556 | G74: Digital & IT | H74: Fireside Chat | I74: Fireside Chat: From mainframe to cloud: Air Canada’s modernisation playbook | J74: Track 1 (Pavilion 1)
A75: David Peller | B75: General Partner & Founder | C75: If Not You Capital | D75: Speaker | E75: Day 2 | F75: 0.52430556 | G75: Digital & IT | H75: Fireside Chat | I75: Fireside Chat: From mainframe to cloud: Air Canada’s modernisation playbook | J75: Track 1 (Pavilion 1)
... A150: Samuel Chekroun | B150: CEO | C150: Hubway | D150: Speaker | E150: Day 2 | F150: 0.56944444 | G150: Startup Theatre | H150: Startup Pitch | I150: From Information Desk to Personal AI Concierge: Turning Every Passenger Interaction into Experience and Revenue | J150: Startup Theatre
A151: Christopher Branagan | D151: Host | E151: Day 2 | F151: 0.57569444 | G151: Workshop | H151: Workshop | I151: IBS Workshop Transformation into an agentic AI lead loyalty and aviation organisation **REGISTRATION REQUIRED - Airline & Airport access only anyone else will be turned away** | J151: Track 3 (Pavilion 1)
A152: Abdurrahman Ural | B152: CCO | C152: AIRVIATECH | D152: Speaker | E152: Day 2 | F152: 0.57638889 | G152: Startup Theatre | H152: Startup Pitch | I152: Connecting Airlines is only the beginning (From fragmented airline distribution to intelligent corporate travel management) | J152: Startup Theatre
A153: Gemma Carver | D153: Host | E153: Day 2 | F153: 0.57638889 | G153: Workshop | H153: Workshop | I153: Adobe Workshop: Beyond the co-pilot: The next era of customer experience **REGISRATION REQUIRED** | J153: Track 2 (Pavilion 2)
A154: Bettina Pickl | D154: Host | E154: Day 2 | F154: 0.57638889 | G154: Workshop | H154: Workshop | I154: Adobe Workshop: Beyond the co-pilot: The next era of customer experience **REGISRATION REQUIRED** | J154: Track 2 (Pavilion 2)
A155: Lauren Mann | D155: Host | E155: Day 2 | F155: 0.57708333 | G155: Workshop | H155: Workshop | I155: Operational resilience isn't built in the Ops center. It's built in the roster. **Registration required** | J155: Track 5 (Pavilion 1)
A156: Kevin Ma | D156: Host | E156: Day 2 | F156: 0.57708333 | G156: Workshop | H156: Workshop | I156: Operational resilience isn't built in the Ops center. It's built in the roster. **Registration required** | J156: Track 5 (Pavilion 1)
A157: Gregory Stephans | D157: Host | E157: Day 2 | F157: 0.57708333 | G157: Workshop | H157: Workshop | I157: Operational resilience isn't built in the Ops center. It's built in the roster. **Registration required** | J157: Track 5 (Pavilion 1)
A158: Jaime Fernandez | B158: CEO | C158: Openair | D158: Speaker | E158: Day 2 | F158: 0.58333333 | G158: Startup Theatre | H158: Startup Pitch | I158: OpenAir — Agentic Revolution for Airlines Customer Services | J158: Startup Theatre
A159: Theo Panagiotoulias | B159: Chief Executive Officer | C159: Star Alliance | D159: Speaker | E159: Day 2 | F159: 0.58333333 | G159: Airline Keynote | H159: Panel | I159: Star Alliance CEOs Panel: From fragmented to frictionless: Rethinking alliance travel | J159: Keynote Stage 1 (Pavilion 1)
A160: Luís Rodrigues | B160: Chief Executive Officer | C160: Tap Air Portugal | D160: Speaker | E160: Day 2 | F160: 0.58333333 | G160: Airline Keynote | H160: Panel | I160: Star Alliance CEOs Panel: From fragmented to frictionless: Rethinking alliance travel | J160: Keynote Stage 1 (Pavilion 1)
A161: Joerg Eberhart | B161: Chief Executive Officer | C161: ITA-Airways | D161: Speaker | E161: Day 2 | F161: 0.58333333 | G161: Airline Keynote | H161: Panel | I161: Star Alliance CEOs Panel: From fragmented to frictionless: Rethinking alliance travel | J161: Keynote Stage 1 (Pavilion 1)
A162: Dimitri Ewald | B162: Head of Growth Europe | C162: ALPIC | D162: Speaker | E162: Day 2 | F162: 0.59027778 | G162: Startup Theatre | H162: Startup Pitch | I162: Your AI assistants are now booking your flights | J162: Startup Theatre
A163: Manuel Hübschmann | B163: Chief Solution Advisor | C163: Viktio | D163: Speaker | E163: Day 2 | F163: 0.59722222 | G163: Startup Theatre | H163: Startup Pitch | I163: Half of what we load is thrown away. Is a 25% waste rate achievable today? | J163: Startup Theatre
A164: Host | C164: World Aviation Festival | D164: Speaker | E164: Day 2 | F164: 0.60763889 | G164: Networking | H164: Networking | I164: Aviation Connect: Session 4 | J164: Aviation Connect Zone (Pavilion 2)
A165: Paul Verhagen | B165: Executive Vice President and Chief Commercial Officer | C165: SAS | D165: Speaker | E165: Day 2 | F165: 0.64930556 | G165: Airline Keynote | H165: Fireside Chat | I165: Commercial leaders fireside chat: Paul Verhagen, CCO, SAS | J165: Keynote Stage 1 (Pavilion 1)
A166: Henry Harteveldt | B166: Travel Industry Analyst | C166: Atmosphere Research Group | D166: Speaker | E166: Day 2 | F166: 0.64930556 | G166: Airline Keynote | H166: Fireside Chat | I166: Commercial leaders fireside chat: Paul Verhagen, CCO, SAS | J166: Keynote Stage 1 (Pavilion 1)
A167: Ahmed Naeemi | B167: Chief Information Officer | C167: Gulf Air Group | D167: Speaker | E167: Day 2 | F167: 0.65277778 | G167: Digital & IT | H167: Fireside Chat | I167: Fireside Chat: Building an AI-led airline – from ambition to execution | J167: Track 1 (Pavilion 1)
A168: Guido Woska | B168: Chief Client Officer & Executive Partner | C168: Manyone | D168: Speaker | E168: Day 2 | F168: 0.65277778 | G168: Digital & IT | H168: Fireside Chat | I168: Fireside Chat: Building an AI-led airline – from ambition to execution | J168: Track 1 (Pavilion 1)
A169: Beatriz Guillen | B169: Chief Customer Officer | C169: Iberia | D169: Speaker | E169: Day 2 | F169: 0.65277778 | G169: Customer Experience | H169: Fireside Chat | I169: Fireside chat: Putting the customer first with data driven decision making at Iberia | J169: Track 2 (Pavilion 1)
A170: Jerry Angrave | B170: Customer Experience Director | C170: Empathyce | D170: Speaker | E170: Day 2 | F170: 0.65277778 | G170: Customer Experience | H170: Fireside Chat | I170: Fireside chat: Putting the customer first with data driven decision making at Iberia | J170: Track 2 (Pavilion 1)
A171: Manjinder Singh | B171: Head of Airline Data Science & Analytics | C171: TUI GROUP | D171: Speaker | E171: Day 2 | F171: 0.65277778 | G171: AI / ML | H171: Presentation | I171: Presentation: Driving efficiency in innovation with AI: finding real value and impact at TUI | J171: Track 9 (Pavilion 2)
A172: Paloma Sanz de Andino Jimenéz | B172: NDC Onboarding and Operation Manager | C172: Iberia | D172: Speaker | E172: Day 2 | F172: 0.65277778 | G172: Retail | H172: Fireside Chat | I172: Fireside Chat: Bringing the benefits of NDC to corporates: Delivering seamless booking and travel management capabilities for high value travellers | J172: Track 5 (Pavilion 1)
A173: Dennis Cary | B173: Managing Director | C173: Cary Strategic Advisory | D173: Speaker | E173: Day 2 | F173: 0.65277778 | G173: Retail | H173: Fireside Chat | I173: Fireside Chat: Bringing the benefits of NDC to corporates: Delivering seamless booking and travel management capabilities for high value travellers | J173: Track 5 (Pavilion 1)
A174: Rita Ribeiro | B174: Head of General Services | C174: EDP | D174: Speaker | E174: Day 2 | F174: 0.65277778 | G174: Retail | H174: Fireside Chat | I174: Fireside Chat: Bringing the benefits of NDC to corporates: Delivering seamless booking and travel management capabilities for high value travellers | J174: Track 5 (Pavilion 1)
A175: Cassie Schmid | B175: Chief Strategy Officer | C175: Philadelphia International Airport | D175: Speaker | E175: Day 2 | F175: 0.65277778 | G175: Airport - Traveller | H175: Fireside Chat | I175: Fireside Chat with Cassie Schmid, Chief Strategy Officer, Philadelphia International Airport | J175: Track 7 (Pavilion 2)
A176: Peta Wolmarans | B176: Vice President | C176: Ricondo | D176: Speaker | E176: Day 2 | F176: 0.65277778 | G176: Airport - Traveller | H176: Fireside Chat | I176: Fireside Chat with Cassie Schmid, Chief Strategy Officer, Philadelphia International Airport | J176: Track 7 (Pavilion 2)
... A199: Erika Moore | B199: Chief Officer Strategy and Growth, TTH | C199: Coforge U.k. Limited | D199: Speaker | E199: Day 2 | F199: 0.66319444 | G199: Ancillaries | H199: Presentation | I199: Presentation: Aeronova: Building the intelligent enterprise for the next generation airline | J199: Track 4 (Pavilion 1)
A200: Enzo Skandella | B200: VP Commercial – Global Aviation | C200: Draxon | D200: Speaker | E200: Day 2 | F200: 0.66319444 | G200: Airport & Airline Collaboration | H200: Presentation | I200: Presentation: Train for the Disruption: Building Operational Resilience Before Things Go Wrong
A201: Samer Alhaider | B201: Senior Manager Online Sales | C201: Emirates Airline | D201: Speaker | E201: Day 2 | F201: 0.66319444 | G201: Payments | H201: Fireside Chat | I201: Fireside Chat: Why flexible payments are becoming a revenue driver for airlines, not just a checkout feature. | J201: Track 6 (Pavilion 1)
A202: Bryony Macdonald | B202: Head of Partner Success, UK | C202: Klarna | D202: Speaker | E202: Day 2 | F202: 0.66319444 | G202: Payments | H202: Fireside Chat | I202: Fireside Chat: Why flexible payments are becoming a revenue driver for airlines, not just a checkout feature. | J202: Track 6 (Pavilion 1)
A203: Harry Owen | B203: Product Solutions Manager | C203: ICTS Europe Systems | D203: Speaker | E203: Day 2 | F203: 0.66319444 | G203: Airport - Traveller | H203: Talk | I203: From Friction to Flow: How TravelDoc Compliance Shapes the Passenger Experience | J203: Track 7 (Pavilion 2)
A204: Alex Mattos | B204: Co-Founder & Managing Director | C204: i6 Group | D204: Speaker | E204: Day 2 | F204: 0.66666667 | G204: Sustainability | H204: Fireside Chat | I204: Fireside Chat: Every minute matters: how Ryanair is digitising fuel operations at scale | J204: Track 10 (Pavilion 2)
A205: Steven Fitzgerald | B205: Director of Sustainability & Finance | C205: Ryanair Holdings PLC | D205: Speaker | E205: Day 2 | F205: 0.66666667 | G205: Sustainability | H205: Fireside Chat | I205: Fireside Chat: Every minute matters: how Ryanair is digitising fuel operations at scale | J205: Track 10 (Pavilion 2)
A206: Lauren Anders Brown | B206: CEO & Founder | C206: PadsPass | D206: Speaker | E206: Day 2 | F206: 0.66666667 | G206: Startup Theatre | H206: Startup Pitch | I206: Aviation Digitised Every Document Except One: Why Pet Documents Never Made the Transition | J206: Startup Theatre
A207: Surain Adyanthaya | B207: President | C207: PROS | D207: Speaker | E207: Day 2 | F207: 0.67013889 | G207: Airline Keynote | H207: Presentation | I207: Presentation: When machines shop: The new rules of airline retailing | J207: Keynote Stage 1 (Pavilion 1)
A208: Alex Desbans | B208: Lead FDE | C208: HappyRobot | D208: Speaker | E208: Day 2 | F208: 0.67361111 | G208: AI / ML | H208: Presentation | I208: Presentation: The agentic IROPS: Automating cancellation and passenger recovery at scale | J208: Track 9 (Pavilion 2)
A209: Mustafa Egilmezbilek | B209: CIO | C209: SunExpress Airlines | D209: Speaker | E209: Day 2 | F209: 0.67361111 | G209: Digital & IT | H209: Panel | I209: Panel: Data platforms, interoperability and AI – are our foundations ready for scale? | J209: Track 1 (Pavilion 1)
A210: Ahmed Naeemi | B210: Chief Information Officer | C210: Gulf Air Group | D210: Speaker | E210: Day 2 | F210: 0.67361111 | G210: Digital & IT | H210: Panel | I210: Panel: Data platforms, interoperability and AI – are our foundations ready for scale? | J210: Track 1 (Pavilion 1)
A211: Paulo Aguiar | B211: VP of Airline Solutions & Strategy | C211: Amach | D211: Speaker | E211: Day 2 | F211: 0.67361111 | G211: Digital & IT | H211: Panel | I211: Panel: Data platforms, interoperability and AI – are our foundations ready for scale? | J211: Track 1 (Pavilion 1)
A212: Ali Akbarian | B212: CEO | C212: InovativAI Ltd. | D212: Speaker | E212: Day 2 | F212: 0.67361111 | G212: Startup Theatre | H212: Startup Pitch | I212: The Intelligent Cabin: Live Announcement Captioning, Real-Time Translation & a Flight-Aware AI Concierge | J212: Startup Theatre
... A251: Ben Maynard | B251: Director AI & Customer Experience | C251: OAG | D251: Speaker | E251: Day 2 | F251: 0.72222222 | G251: Airline Keynote | H251: Panel | I251: Data Leaders Panel: Maximising benefits for aviation with smart data strategies and AI investment | J251: Keynote Stage 1 (Pavilion 1)
A252: Host | C252: World Aviation Festival | D252: Speaker | E252: Day 3 | G252: Networking | H252: Networking | I252: Aviation Connect: Session 7 | J252: Aviation Connect Zone (Pavilion 2)
A253: Michael Corcoran | B253: Co-Founder | C253: Slice Social | D253: Speaker | E253: Day 3 | F253: 0.39583333 | G253: Airline Keynote | H253: Talk | I253: Fast & Slow Social: Driving engagement with smart social media strategy | J253: Keynote Stage 1 (Pavilion 1)
A254: Oisin Lunny | B254: Event MC, Journalist, Podcast and Webinar Host | C254: Galaxy of OM, S.L. | D254: Speaker | E254: Day 3 | F254: 0.39583333 | G254: Airline Keynote | H254: Talk | I254: Fast & Slow Social: Driving engagement with smart social media strategy | J254: Keynote Stage 1 (Pavilion 1)
A255: Lars Redeligx | B255: CEO | C255: Dusseldorf Airport | D255: Speaker | E255: Day 3 | F255: 0.40625 | G255: Airport Keynote | H255: Interview | I255: Keynote Interview with Lars Redeligx, CEO, Düsseldorf Airport | J255: Keynote Stage 2 (Pavilion 2)
A256: Luis Felipe De Oliveira | B256: Executive Director and CEO | C256: Exactly Consulting and Services Sarl | D256: Speaker | E256: Day 3 | F256: 0.40625 | G256: Airport Keynote | H256: Interview | I256: Keynote Interview with Lars Redeligx, CEO, Düsseldorf Airport | J256: Keynote Stage 2 (Pavilion 2)
A257: Amy Burr | B257: CEO | C257: SKY VC | D257: Speaker | E257: Day 3 | F257: 0.40625 | G257: Airline Keynote | H257: Fireside Chat | I257: Fireside Chat with Amy Burr, CEO, SKY VC | J257: Keynote Stage 1 (Pavilion 1)
A258: Lennart Dobravsky | B258: Managing Director | C258: Research+Attitude | D258: Speaker | E258: Day 3 | F258: 0.40625 | G258: Airline Keynote | H258: Fireside Chat | I258: Fireside Chat with Amy Burr, CEO, SKY VC | J258: Keynote Stage 1 (Pavilion 1)
A259: Lars Redeligx | B259: CEO | C259: Dusseldorf Airport | D259: Speaker | E259: Day 3 | F259: 0.41666667 | G259: Airport Keynote | H259: Panel | I259: Keynote Panel: Defining the airport of the future – technology, partnerships and people | J259: Keynote Stage 2 (Pavilion 2)
A260: Olubunmi Kuku | B260: Managing Director/Chief Executive | C260: FEDERAL AIRPORTS AUTHORITY OF NIGERIA | D260: Speaker | E260: Day 3 | F260: 0.41666667 | G260: Airport Keynote | H260: Panel | I260: Keynote Panel: Defining the airport of the future – technology, partnerships and people | J260: Keynote Stage 2 (Pavilion 2)
A261: Javlonbek Umarkhodjaev | B261: Chairman of the Management Board | C261: Uzbekistan Airports JSC | D261: Speaker | E261: Day 3 | F261: 0.41666667 | G261: Airport Keynote | H261: Panel | I261: Keynote Panel: Defining the airport of the future – technology, partnerships and people | J261: Keynote Stage 2 (Pavilion 2)
A262: Amy Burr | B262: CEO | C262: SKY VC | D262: Speaker | E262: Day 3 | F262: 0.41666667 | G262: Airline Keynote | H262: Panel | I262: Investor Panel: Innovation at a crossroads – where are aviation’s next big bets? | J262: Keynote Stage 1 (Pavilion 1)
A263: Cara Whitehill | B263: Operating Partner | C263: Thayer Investment Partners | D263: Speaker | E263: Day 3 | F263: 0.41666667 | G263: Airline Keynote | H263: Panel | I263: Investor Panel: Innovation at a crossroads – where are aviation’s next big bets? | J263: Keynote Stage 1 (Pavilion 1)
A264: Amir Amidi | B264: Managing Partner | C264: Plug and Play Tech Center | D264: Speaker | E264: Day 3 | F264: 0.41666667 | G264: Airline Keynote | H264: Panel | I264: Investor Panel: Innovation at a crossroads – where are aviation’s next big bets? | J264: Keynote Stage 1 (Pavilion 1)
A265: Host | C265: World Aviation Festival | D265: Speaker | E265: Day 3 | F265: 0.44791667 | G265: Networking | H265: Networking | I265: Aviation Connect: Session 5 | J265: Aviation Connect Zone (Pavilion 2)
A266: Tiernan Mines | B266: CEO & Co-Founder | C266: Hello Airport | D266: Speaker | E266: Day 3 | F266: 0.49305556 | G266: Startup Theatre | H266: Startup Pitch | I266: Your chatbot knows everything. Except how to help. | J266: Startup Theatre
A267: Harald Deprosse | B267: Partner | C267: Envolved GmbH | D267: Speaker | E267: Day 3 | F267: 0.49652778 | G267: Loyalty | H267: Chair Remarks | I267: Chair opening remarks | J267: Track 3 (Pavilion 1)
A268: Dan Fischer | B268: Head of Digital Product, Strategy & Design | C268: Virgin Australia | D268: Speaker | E268: Day 3 | F268: 0.5 | G268: Digital & IT | H268: Fireside Chat | I268: Fireside Chat: Executing Offer & Order – balancing innovation with operational reality | J268: Track 1 (Pavilion 1)
...

Sheet Speaker Directory
A1: Name | B1: Job Title | C1: Organisation | D1: No. of Sessions
A2: Abdulrahman Alkhatabi | B2: Senior Manager Crew Utilization | C2: Saudia | D2: =COUNTIF('Speaker Appearances'!$A$2:$A$358,A2) -> 1
A3: Abdurrahman Ural | B3: CCO | C3: AIRVIATECH | D3: =COUNTIF('Speaker Appearances'!$A$2:$A$358,A3) -> 1
A4: Adam Kressler | B4: Vice President of Customer Experience | C4: Cincinnati/Northern Kentucky International Airport (CVG) | D4: =COUNTIF('Speaker Appearances'!$A$2:$A$358,A4) -> 1
A5: Adam Schipper | B5: Global Aviation Lead | C5: Ericsson | D5: =COUNTIF('Speaker Appearances'!$A$2:$A$358,A5) -> 1
A6: Adrian Neuhauser | B6: Chief Executive Officer | C6: Abra Group | D6: =COUNTIF('Speaker Appearances'!$A$2:$A$358,A6) -> 2
A7: Ahmed Naeemi | B7: Chief Information Officer | C7: Gulf Air Group | D7: =COUNTIF('Speaker Appearances'!$A$2:$A$358,A7) -> 2
A8: Alex Desbans | B8: Lead FDE | C8: HappyRobot | D8: =COUNTIF('Speaker Appearances'!$A$2:$A$358,A8) -> 1
A9: Alex Matson | B9: COO | C9: telos | D9: =COUNTIF('Speaker Appearances'!$A$2:$A$358,A9) -> 1
A10: Alex Mattos | B10: Co-Founder & Managing Director | C10: i6 Group | D10: =COUNTIF('Speaker Appearances'!$A$2:$A$358,A10) -> 2
A11: Alexander Laurie | B11: GTM CTO | C11: PING IDENTITY | D11: =COUNTIF('Speaker Appearances'!$A$2:$A$358,A11) -> 2
A12: Alexandra Halberg Hüneburg-Møller | B12: Senior Innovation Manager | C12: CPH Airport | D12: =COUNTIF('Speaker Appearances'!$A$2:$A$358,A12) -> 1
A13: Ali Akbarian | B13: CEO | C13: InovativAI Ltd. | D13: =COUNTIF('Speaker Appearances'!$A$2:$A$358,A13) -> 1
A14: Ali Tredinnick | D14: =COUNTIF('Speaker Appearances'!$A$2:$A$358,A14) -> 1
A15: Amal Ahmed | D15: =COUNTIF('Speaker Appearances'!$A$2:$A$358,A15) -> 1
A16: Amin Lalani | B16: Product Leader of Airport & Sky Club Digital Products & Experiences | C16: Delta Air Lines | D16: =COUNTIF('Speaker Appearances'!$A$2:$A$358,A16) -> 1
A17: Amir Amidi | B17: Managing Partner | C17: Plug and Play Tech Center | D17: =COUNTIF('Speaker Appearances'!$A$2:$A$358,A17) -> 1
A18: Amy Burr | B18: CEO | C18: SKY VC | D18: =COUNTIF('Speaker Appearances'!$A$2:$A$358,A18) -> 2
A19: Ana Maria Escobar | D19: =COUNTIF('Speaker Appearances'!$A$2:$A$358,A19) -> 1
A20: Anand Mishra | B20: VP of Technology | C20: ATPCO | D20: =COUNTIF('Speaker Appearances'!$A$2:$A$358,A20) -> 1
A21: Andrea Halverson | B21: Director - Contact Center Experience and Innovation | C21: Alaska Airlines | D21: =COUNTIF('Speaker Appearances'!$A$2:$A$358,A21) -> 1
A22: Angel Matsis | D22: =COUNTIF('Speaker Appearances'!$A$2:$A$358,A22) -> 1
A23: Ann Cederhall | B23: Owner | C23: LeapShift | D23: =COUNTIF('Speaker Appearances'!$A$2:$A$358,A23) -> 1
A24: Annemijn Schoenmaker | B24: Head of Business Platform Infrastructure & IT Projects | C24: Schiphol Group | D24: =COUNTIF('Speaker Appearances'!$A$2:$A$358,A24) -> 1
A25: Anupam Krishnamurthy | B25: Head of AI Testing | C25: TestSolutions | D25: =COUNTIF('Speaker Appearances'!$A$2:$A$358,A25) -> 1
A26: Anvar Kasimov | B26: Head of the Strategic Development, Project Management and International Relations Department | C26: Uzbekistan Airports JSC | D26: =COUNTIF('Speaker Appearances'!$A$2:$A$358,A26) -> 1
A27: Arturs Saveljevs | B27: Board member and CCO | C27: Riga International Airport | D27: =COUNTIF('Speaker Appearances'!$A$2:$A$358,A27) -> 2
A28: Azim Barodawala | D28: =COUNTIF('Speaker Appearances'!$A$2:$A$358,A28) -> 1
A29: Balamurali Boggu | B29: Airline Domain Expert | C29: TestSolutions | D29: =COUNTIF('Speaker Appearances'!$A$2:$A$358,A29) -> 1
A30: Barbara Bassi Modalek | B30: CEO & Founder | C30: Virtuwella | D30: =COUNTIF('Speaker Appearances'!$A$2:$A$358,A30) -> 1
A31: Baris Findik | D31: =COUNTIF('Speaker Appearances'!$A$2:$A$358,A31) -> 1
A32: Barry Chester | B32: Head of Airlines | C32: Cresta | D32: =COUNTIF('Speaker Appearances'!$A$2:$A$358,A32) -> 1
A33: Beatriz Guillen | B33: Chief Customer Officer | C33: Iberia | D33: =COUNTIF('Speaker Appearances'!$A$2:$A$358,A33) -> 2
A34: Ben Dias | B34: Chief AI Scientist | C34: IAG | D34: =COUNTIF('Speaker Appearances'!$A$2:$A$358,A34) -> 3
A35: Ben Maynard | B35: Director AI & Customer Experience | C35: OAG | D35: =COUNTIF('Speaker Appearances'!$A$2:$A$358,A35) -> 2
A36: Ben Thompson | B36: Presenter | C36: BBC | D36: =COUNTIF('Speaker Appearances'!$A$2:$A$358,A36) -> 4
A37: Benny Yonovich | B37: Co-Founder & CEO | C37: Arbitrip | D37: =COUNTIF('Speaker Appearances'!$A$2:$A$358,A37) -> 1
A38: Bertrand Lestimé | B38: HO Environment and Sustainability Marketing | C38: Airbus S.A.S | D38: =COUNTIF('Speaker Appearances'!$A$2:$A$358,A38) -> 1
A39: Bethan Lynch | B39: VP Customer Experience & Loyalty | C39: Virgin Atlantic | D39: =COUNTIF('Speaker Appearances'!$A$2:$A$358,A39) -> 1
A40: Bettina Pickl | D40: =COUNTIF('Speaker Appearances'!$A$2:$A$358,A40) -> 1
A41: Bhaskara Guntreddy | B41: Senior Vice President, Product | C41: PROS | D41: =COUNTIF('Speaker Appearances'!$A$2:$A$358,A41) -> 1
A42: Billie Moore | D42: =COUNTIF('Speaker Appearances'!$A$2:$A$358,A42) -> 1
A43: Boyan Manev | D43: =COUNTIF('Speaker Appearances'!$A$2:$A$358,A43) -> 1
A44: Bryony Macdonald | B44: Head of Partner Success, UK | C44: Klarna | D44: =COUNTIF('Speaker Appearances'!$A$2:$A$358,A44) -> 1
A45: Cam Price | B45: Senior Data Scientist | C45: Cirium | D45: =COUNTIF('Speaker Appearances'!$A$2:$A$358,A45) -> 1
A46: Cara Whitehill | B46: Operating Partner | C46: Thayer Investment Partners | D46: =COUNTIF('Speaker Appearances'!$A$2:$A$358,A46) -> 1
A47: Carlos Faxas | B47: Vice President, Digital Products | C47: Air Canada | D47: =COUNTIF('Speaker Appearances'!$A$2:$A$358,A47) -> 1
A48: Carlos Oliveira | B48: Chairman | C48: Tap Air Portugal | D48: =COUNTIF('Speaker Appearances'!$A$2:$A$358,A48) -> 1
A49: Cassie Schmid | B49: Chief Strategy Officer | C49: Philadelphia International Airport | D49: =COUNTIF('Speaker Appearances'!$A$2:$A$358,A49) -> 2
A50: Cesar Hueso | B50: Founder | C50: Stand-By CHO Systems | D50: =COUNTIF('Speaker Appearances'!$A$2:$A$358,A50) -> 1
A51: Chamith Seneviratne | B51: Manager, Airport Operations | C51: Air Canada | D51: =COUNTIF('Speaker Appearances'!$A$2:$A$358,A51) -> 1
A52: Charlotte Ross | D52: =COUNTIF('Speaker Appearances'!$A$2:$A$358,A52) -> 1
A53: Choorah Singh Ark | B53: Managing Director | C53: Ark Advisory | D53: =COUNTIF('Speaker Appearances'!$A$2:$A$358,A53) -> 1
A54: Chris Brown | B54: Founder, Chief Product Officer | C54: Bonafide | D54: =COUNTIF('Speaker Appearances'!$A$2:$A$358,A54) -> 1
A55: Christoph Both | B55: Head of Customer, Business Development & Controlling | C55: Lufthansa Process Management | D55: =COUNTIF('Speaker Appearances'!$A$2:$A$358,A55) -> 1
A56: Christopher Branagan | D56: =COUNTIF('Speaker Appearances'!$A$2:$A$358,A56) -> 1
A57: Dan Bartel | B57: Chief Procurement Officer | C57: American Airlines | D57: =COUNTIF('Speaker Appearances'!$A$2:$A$358,A57) -> 1
A58: Dan Fischer | B58: Head of Digital Product, Strategy & Design | C58: Virgin Australia | D58: =COUNTIF('Speaker Appearances'!$A$2:$A$358,A58) -> 1
A59: DANIEL BRETT | B59: Manager, Revenue Management - Loyalty Programs & Flight Pass | C59: Air Canada | D59: =COUNTIF('Speaker Appearances'!$A$2:$A$358,A59) -> 1
A60: Daniel Forrester | B60: CEO | C60: Cybernet Secure | D60: =COUNTIF('Speaker Appearances'!$A$2:$A$358,A60) -> 1
A61: Daniel Langhage | B61: Managing Director | C61: Oystin Advisory GmbH | D61: =COUNTIF('Speaker Appearances'!$A$2:$A$358,A61) -> 1
A62: Danielle Harvey | B62: VP, Travel & Hospitality Strategy | C62: Quantum Metric (UK) Limited | D62: =COUNTIF('Speaker Appearances'!$A$2:$A$358,A62) -> 1
A63: David Buckley | B63: Flight Operations Manager - Efficiencies & Sustainability | C63: easyJet | D63: =COUNTIF('Speaker Appearances'!$A$2:$A$358,A63) -> 1
A64: David Cruz | D64: =COUNTIF('Speaker Appearances'!$A$2:$A$358,A64) -> 1
A65: David Peller | B65: General Partner & Founder | C65: If Not You Capital | D65: =COUNTIF('Speaker Appearances'!$A$2:$A$358,A65) -> 1
A66: Dennis Cary | B66: Managing Director | C66: Cary Strategic Advisory | D66: =COUNTIF('Speaker Appearances'!$A$2:$A$358,A66) -> 2
A67: Dennis Lore | B67: Payments Reconciliations and Credit Risk Accountant Manager | C67: Kenya Airways | D67: =COUNTIF('Speaker Appearances'!$A$2:$A$358,A67) -> 1
A68: Dilan Toplu | B68: Sales Manager | C68: PixoAnalytics | D68: =COUNTIF('Speaker Appearances'!$A$2:$A$358,A68) -> 1
A69: Dimitri Ewald | B69: Head of Growth Europe | C69: ALPIC | D69: =COUNTIF('Speaker Appearances'!$A$2:$A$358,A69) -> 1
A70: Dirk Jungnickel | B70: SVP Enterprise Data & Analytics | C70: Emirates Airline | D70: =COUNTIF('Speaker Appearances'!$A$2:$A$358,A70) -> 2
A71: Doug Sharpe | D71: =COUNTIF('Speaker Appearances'!$A$2:$A$358,A71) -> 1
A72: Dr. Philipp Schade | B72: Head of Business Development & Senior Data Scientist | C72: zeroG | D72: =COUNTIF('Speaker Appearances'!$A$2:$A$358,A72) -> 1
A73: Dário Pedro | D73: =COUNTIF('Speaker Appearances'!$A$2:$A$358,A73) -> 1
A74: Edem Akan | B74: Director, Enterprise Transformation | C74: Porter Airlines | D74: =COUNTIF('Speaker Appearances'!$A$2:$A$358,A74) -> 1
A75: Eivind Roald | B75: President & CEO | C75: Norse Atlantic Airways | D75: =COUNTIF('Speaker Appearances'!$A$2:$A$358,A75) -> 1
A76: Ella Schreiber | B76: SVP and GM Fintech | C76: Hopper Inc | D76: =COUNTIF('Speaker Appearances'!$A$2:$A$358,A76) -> 1
A77: Emanuela Maftieu | D77: =COUNTIF('Speaker Appearances'!$A$2:$A$358,A77) -> 1
A78: emna TOUIHRI | B78: Co-founder&CEO | C78: AERAUT | D78: =COUNTIF('Speaker Appearances'!$A$2:$A$358,A78) -> 1
A79: Emre Devrim | B79: Product & Customer Experience Manager | C79: Ajet | D79: =COUNTIF('Speaker Appearances'!$A$2:$A$358,A79) -> 1
A80: Enzo Skandella | B80: VP Commercial – Global Aviation | C80: Draxon | D80: =COUNTIF('Speaker Appearances'!$A$2:$A$358,A80) -> 1
A81: Eoin Mcnamara | B81: Co-Founder & Chief Operating Officer | C81: FlyBuddy | D81: =COUNTIF('Speaker Appearances'!$A$2:$A$358,A81) -> 1
A82: Eric Boromisa | B82: Founder | Managing Partner | C82: Numbers & Letters Advisory | D82: =COUNTIF('Speaker Appearances'!$A$2:$A$358,A82) -> 1
A83: Erika Moore | B83: Chief Officer Strategy and Growth, TTH | C83: Coforge U.k. Limited | D83: =COUNTIF('Speaker Appearances'!$A$2:$A$358,A83) -> 1
A84: Erin Trapp | B84: Chief Strategy & External Affairs Officer | C84: Los Angeles World Airports | D84: =COUNTIF('Speaker Appearances'!$A$2:$A$358,A84) -> 1
A85: Eugenia Martinez | B85: Solutions Engineer | C85: ThoughtSpot | D85: =COUNTIF('Speaker Appearances'!$A$2:$A$358,A85) -> 1
A86: Felix Velazquez | B86: Chief Revenue Officer | C86: Vivaaerobus | D86: =COUNTIF('Speaker Appearances'!$A$2:$A$358,A86) -> 1
A87: Frank de Boer | B87: Director Data and Technology | Customer Loyalty | Flying Blue | C87: Air France / KLM | D87: =COUNTIF('Speaker Appearances'!$A$2:$A$358,A87) -> 1
A88: Gabriella Solti | D88: =COUNTIF('Speaker Appearances'!$A$2:$A$358,A88) -> 1
A89: Gaurav Passi | D89: =COUNTIF('Speaker Appearances'!$A$2:$A$358,A89) -> 1
A90: Gemma Carver | D90: =COUNTIF('Speaker Appearances'!$A$2:$A$358,A90) -> 1
A91: Gilbert Ott | B91: Director, Loyalty | C91: oneworld Alliance | D91: =COUNTIF('Speaker Appearances'!$A$2:$A$358,A91) -> 2
A92: Gintare Norvilaite-Tautevice | B92: Chief Commercial Officer | C92: Lithuanian Airports | D92: =COUNTIF('Speaker Appearances'!$A$2:$A$358,A92) -> 1
A93: Girish Nair | B93: Chief Operating Officer | C93: Bangalore International Airport | D93: =COUNTIF('Speaker Appearances'!$A$2:$A$358,A93) -> 2
A94: Glenn Morgan | B94: Partner | C94: SkiesFifty | D94: =COUNTIF('Speaker Appearances'!$A$2:$A$358,A94) -> 1
A95: Greg Toussaint | B95: Director | C95: Edgar, Dunn & Company | D95: =COUNTIF('Speaker Appearances'!$A$2:$A$358,A95) -> 1
A96: Gregory Stephans | D96: =COUNTIF('Speaker Appearances'!$A$2:$A$358,A96) -> 1
A97: Guido Woska | B97: Chief Client Officer & Executive Partner | C97: Manyone | D97: =COUNTIF('Speaker Appearances'!$A$2:$A$358,A97) -> 1
A98: Gyorgy Farkas | B98: Head of IT Project and Innovation Management | C98: Budapest Airport | D98: =COUNTIF('Speaker Appearances'!$A$2:$A$358,A98) -> 1
A99: Harald Deprosse | B99: Partner | C99: Envolved GmbH | D99: =COUNTIF('Speaker Appearances'!$A$2:$A$358,A99) -> 7
A100: Harry Barrett | B100: Assistant Director of Airports | C100: Sacramento County International Airport | D100: =COUNTIF('Speaker Appearances'!$A$2:$A$358,A100) -> 1
...
